{"BuildLengthInSeconds":610,"BuildOrderItems":["DefaultItem","SCV","SCV","SCV","SCV","SupplyDepot","SCV","SCV","Refinery","SCV","Barracks","GasScv","GasScv","GasScv","SCV","SCV","SCV","Marine","Factory","OrbitalCommand","SupplyDepot","Marine","SCV","CallMule","ReactorOnBarracks","SCV","Starport","WidowMine","Refinery","SCV","SupplyDepot","SCV","Marine","MarineOnReactor","GasScv","GasScv","GasScv","SCV","Medivac","SupplyDepot","Marine","MarineOnReactor","SCV","CallMule","TechLabOnFactory","SCV","Marine","MarineOnReactor","LiftFactoryFromTechLab","LandStarportOnTechLab","Banshee","SCV","SupplyDepot","Marine","MarineOnReactor","SCV","SCV","Marine","MarineOnReactor","SupplyDepot","SCV","CallMule","Raven","Marine","MarineOnReactor","Starport","SCV","SupplyDepot","SCV","Marine","MarineOnReactor","Hellion","SupplyDepot","SCV","Marine","MarineOnReactor","TechLabOnStarport","Banshee","SCV","Hellion","Marine","MarineOnReactor","Banshee","SCV","CallMule","SupplyDepot","Marine","MarineOnReactor","Hellion","SupplyDepot","Banshee","Marine","MarineOnReactor","WidowMine","Banshee","SupplyDepot","Marine","MarineOnReactor","WidowMine","Banshee","Marine","MarineOnReactor","Banshee"],"Description":"This is all-in build which designed to kill protoss while he is trying to get Colossi or High Templar tech at around 10 minutes.\r\n\r\nGeneral plan is the following:\r\n1. Go standard 1-1-1 6 marines + 1 mine drop.\r\n2. Get 1 banshee after drop to continue harassing probes.\r\n3. Get 2nd proxy starport and Raven.\r\n4. Continue using banshees to harass probes, make sure not to lose banshees. Use SCV to repair them.\r\n5. Send medivac (which you used for first drop) with 3 hellions to protoss main meanwhile gather entire army near protoss natural. Rally all your buildings to protoss natural.\r\n6. While doing hellion harras do major push to natural at around 10:00 with 4 banshees, 1 raven, 20 marines and kind of 14SCVs on repair. Use PDD near nexus to counter Photon Overcharge and stalkers. Try to kill as many probes as possible. If you will see Colosus during the push make sure to focus fire it with banshees. Use resource you have to constantly build banshees.\r\n","Name":"1-1-2 MarineMineDrop to RavenBansheeMarines AllIn","Race":"Terran","SC2VersionID":"2.2.0","VsRace":"Protoss","CreationDate":1427819253224,"VisitedDate":1427819253224}