{"BuildLengthInSeconds":811,"BuildOrderItems":["DefaultItem","SCV","SCV","SupplyDepot","SCV","SCV","Barracks","SCV","SupplyDepot","Refinery","SCV","Refinery","SCV","Marine","OrbitalCommand","GasScv","GasScv","GasScv","Marine","Factory","Marine","SCV","SupplyDepot","SCV","Marine","SCV","Starport","ReactorOnFactory","ReactorOnBarracks","Barracks","SCV","Liberator","Liberator","SupplyDepot","LiftFactoryFromReactor","LandStarportOnReactor","TechLabOnFactory","Marine","Marine","Marine","SupplyDepot","SiegeTank","Marine","Marine","Marine","SCV","SupplyDepot","Marine","Marine","Marine","SiegeTank","Viking","SiegeTank","Marine","Marine","Marine","SiegeTank","SupplyDepot","SupplyDepot","Liberator","Liberator","SupplyDepot","SiegeTank","SiegeTank","Marine","Marine","Marine","SupplyDepot","Cyclone"],"CreationDate":1449909119443,"Name":"1-1-1 Liberator-Tank-Marine All-In","Race":"Terran","SC2VersionID":"3.8.0","VisitedDate":1470914096592,"VsRace":"Protoss"}