{"BuildLengthInSeconds":246,"BuildOrderItems":["DefaultItem","SCV","SCV","SupplyDepot","SCV","SCV","Barracks","Refinery","SCV","Refinery","GoOutScv","SCV","GasScv","GasScv","GasScv","SCV","GasScv","GasScv","GasScv","Marine","OrbitalCommand","Factory","Marine","SCV","CallMule","SupplyDepot","ReactorOnBarracks","SCV","SCV","Starport","ReactorOnFactory","SupplyDepot","Marine","MarineOnReactor","Marine","MarineOnReactor","LiftFactoryFromReactor","LandStarportOnReactor","CallMule","Liberator","MedivacOnReactor","TechLabOnFactory","SCV","SupplyDepot","Marine","MarineOnReactor","SiegeTank","SCV","Marine","MarineOnReactor","SupplyDepot","SCV","Marine","MarineOnReactor","SCV","SupplyDepot","SiegeTank","Marine","MarineOnReactor"],"CreationDate":1453565440590,"Description":"Go @4:00. Take a few SCV to repair and put the tank in medivac in siege mode.\nThis is soft all-in. You must defeat your opponent,  or deal really a lot of damage, course our eco is not great at all.","Name":"1-CC Marine Tank Medivac Liberator push","Race":"Terran","SC2VersionID":"5.0.3","VisitedDate":1470911961901,"VsRace":"Terran"}