{"BuildLengthInSeconds":508,"BuildOrderItems":["DefaultItem","SCV","SCV","SCV","SCV","SupplyDepot","SCV","SCV","SCV","SCV","CommandCenter","SCV","Barracks","SCV","Refinery","SCV","SCV","GasScv","GasScv","GasScv","OrbitalCommand","Marine","Bunker","OrbitalCommand","Marine","SCV","CallMule","Factory","SCV","CallMule","SCV","ReactorOnBarracks","SupplyDepot","SCV","SCV","SCV","SCV","Barracks","Barracks","Refinery","SCV","SCV","LiftRaxFromReactor","LandFactoryOnReactor","Hellion","HellionOnReactor","SupplyDepot","TechLabOnBarracks","SCV","SCV","GasScv","GasScv","GasScv","CallMule","SCV","CallMule","SCV","Hellion","HellionOnReactor","SupplyDepot","StimPack","ReactorOnBarracks","ReactorOnBarracks","SCV","SCV","Marine","SCV","SCV","Hellion","HellionOnReactor","SupplyDepot","Marine","Starport","SCV","SCV","SupplyDepot","SupplyDepot","SCV","Hellion","HellionOnReactor","Marine","MarineOnReactor","Marine","MarineOnReactor","CallMule","Marauder","SupplyDepot","SCV","SCV","CallMule","Marine","MarineOnReactor","Marine","MarineOnReactor","LiftFactoryFromReactor","LandStarportOnReactor","Medivac","MedivacOnReactor","Armory","Marauder","SCV","SCV","ReactorOnFactory","Marine","MarineOnReactor","Marine","MarineOnReactor","SCV","SCV","Marauder"],"CreationDate":1437647293188,"Description":"Build was executed by Flash vs Impact in the first game of Code A.","Name":"14CC to Helbat Bio push with 2 medivacs","Race":"Terran","SC2VersionID":"2.2.0","VisitedDate":1437647379795,"VsRace":"Zerg"}