{"BuildLengthInSeconds":454,"BuildOrderItems":["DefaultItem","SCV","SCV","SCV","SCV","SupplyDepot","SCV","SCV","Barracks","SCV","SCV","SCV","Refinery","OrbitalCommand","GoOutScv","Marine","SupplyDepot","GasScv","GasScv","GasScv","Marine","SCV","CallMule","ReactorOnBarracks","SCV","SCV","CommandCenter","SCV","Factory","Marine","MarineOnReactor","SCV","SupplyDepot","SCV","CallMule","Marine","MarineOnReactor","SCV","Starport","LiftRaxFromReactor","LandFactoryOnReactor","Hellion","HellionOnReactor","SCV","Marine","OrbitalCommand","SCV","Hellion","HellionOnReactor","Marine","SCV","SupplyDepot","Medivac","CallMule","CallMule","SCV","SCV","SupplyDepot","SCV","SCV","Hellion","HellionOnReactor","TechLabOnBarracks","SCV","SCV","Barracks","Barracks","StimPack","SCV","SCV","SupplyDepot","EngineeringBay","SCV","SCV","WidowMine","WidowMineOnReactor","Marine","Refinery"],"CreationDate":1433491774839,"Description":"Dream executed this build against Hero in the first game of Semi-Finals june 5 2015. Main idea is to drop 8 marines into protoss main to call photon or force protoss to get his units from natural and run with 6 hellions straight into natural mineral line.","Name":"15 Gas 8 Marines Drop + 6 hellions attack","Race":"Terran","SC2VersionID":"2.2.0","VisitedDate":1433753413241,"VsRace":"Protoss"}