{"BuildLengthInSeconds":297,"BuildOrderItems":["DefaultItem","Probe","Probe","Pylon","Probe","Probe","Nexus","Gateway","Probe","Probe","Assimilator","Assimilator","GoOutProbe","Probe","Probe","Gateway","GasProbe","GasProbe","GasProbe","GasProbe","GasProbe","GasProbe","Probe","Pylon","Probe","CyberneticsCore","Probe","Probe","Probe","Probe","Probe","Probe","Probe","Probe","Adept","Chronoboost","Adept","Chronoboost","WarpgateUpgrade","MothershipCore","Probe","Probe","Stalker","Stalker","Pylon","Probe","Probe","RoboticsFacility","Probe","Probe","Probe","Probe","Stalker","Stalker","Pylon","Probe","Probe","Pylon","Probe","Probe","Observer","Stalker","Stalker","Probe","Probe","Pylon","TwilightCouncil","Assimilator","Assimilator","Probe","Probe","Observer","Probe","Probe","Pylon","GasProbe","GasProbe","GasProbe","GasProbe","GasProbe","GasProbe","Probe","Probe","SwitchToWarpgate","SwitchToWarpgate","Blink","Chronoboost","Probe","Probe","WarpInStalker","WarpInStalker","Pylon"],"CreationDate":1449921030321,"Description":"","Name":"16 Nexus into double adept with safe robo","Race":"Protoss","SC2VersionID":"3.8.0","VisitedDate":1449921077957,"VsRace":"Protoss"}