{"BuildLengthInSeconds":337,"BuildOrderItems":["DefaultItem","SCV","SCV","SupplyDepot","SCV","SCV","SCV","CommandCenter","SCV","Barracks","SCV","Barracks","SCV","SCV","Marine","OrbitalCommand","OrbitalCommand","Barracks","Marine","Marine","SCV","CallMule","Refinery","Refinery","Marine","Marine","SCV","CallMule","SCV","Bunker","GasScv","GasScv","GasScv","GasScv","GasScv","GasScv","SCV","SCV","Marine","Marine","SupplyDepot","TechLabOnBarracks","SCV","SCV","Marine","Marine","SupplyDepot","SCV","SCV","StimPack","Marine","SCV","SCV","Marine","Marine","ScannerSweep","Factory","EngineeringBay","SCV","SCV","CallMule","SupplyDepot","Refinery","Marine","Marine","Marauder","SCV","SCV","SupplyDepot","InfantryWeaponsLevel1","GasScv","GasScv","GasScv","SCV","SCV","Marine","Marine","Marauder","SCV","SCV","Starport","ReactorOnFactory","SupplyDepot","Marine","Marine","SCV","SCV","Marauder","CallMule","SupplyDepot","SCV","CallMule","SCV","TechLabOnBarracks","ReactorOnBarracks","SCV","SCV","Marauder","SupplyDepot","LiftFactoryFromReactor","LandStarportOnReactor","CommandCenter","Medivac","MedivacOnReactor","SCV","SCV","Refinery","Marauder","Marauder","ReactorOnFactory","CombatShield","SCV","SCV","Marine","MarineOnReactor","ConcussiveShells","GasScv","GasScv","GasScv","ScannerSweep"],"CreationDate":1446115488163,"Description":"This is adopdet 14 CC into 3 Rax build from HOTS. Idea is the same - get CC first and 3 rax after that. Go to medivac tech while research stim pack and push out when medivacs and stim ready.","Name":"17 CC into 3 Rax Bio","Race":"Terran","SC2VersionID":"4.11.3","VisitedDate":1470913909988,"VsRace":"Protoss"}