{"BuildLengthInSeconds":351,"BuildOrderItems":["DefaultItem","SCV","SCV","SupplyDepot","SCV","SCV","SCV","CommandCenter","SCV","Barracks","SCV","Barracks","SCV","SCV","Barracks","GoOutScv","OrbitalCommand","Marine","OrbitalCommand","Marine","Marine","SCV","CallMule","Refinery","Refinery","Marine","Marine","Marine","SCV","CallMule","SCV","SupplyDepot","GasScv","GasScv","GasScv","GasScv","GasScv","GasScv","Bunker","SCV","SCV","Marine","TechLabOnBarracks","Marine","SCV","SCV","Marine","SCV","StimPack","Marine","SCV","Marine","SupplyDepot","SCV","SCV","CallMule","Marine","Marine","Factory","Marine","CallMule","SCV","SCV","Refinery","SupplyDepot","Marine","Marine","Marine","SCV","SCV","EngineeringBay","GasScv","GasScv","GasScv","SupplyDepot","SCV","SCV","Marauder","ReactorOnBarracks","TechLabOnBarracks","SCV","SCV","Starport","ReactorOnFactory","InfantryWeaponsLevel1","SCV","SCV","Marauder","Marauder","CallMule","SupplyDepot","SCV","SCV","CallMule","SCV","SCV","CommandCenter","SupplyDepot","LiftFactoryFromReactor","LandStarportOnReactor","Medivac","MedivacOnReactor","SCV","SCV","Marauder","SupplyDepot","Refinery","SCV","SCV","Marine","MarineOnReactor","Marauder","Marauder","SCV","SCV","GasScv","GasScv","GasScv","SupplyDepot","Liberator","LiberatorOnReactor","ScannerSweep","SupplyDepot","SCV","CallMule","CombatShield","ConcussiveShells"],"CreationDate":1449848342407,"Description":"","Name":"17 CC into 3 Rax Bio-Liberator","Race":"Terran","SC2VersionID":"4.11.3","VisitedDate":1450083168517,"VsRace":"Protoss"}