{"BuildLengthInSeconds":337,"BuildOrderItems":["DefaultItem","Drone","Overlord","Drone","Drone","Drone","Drone","Hatchery","Drone","Drone","Extractor","Drone","SpawningPool","Drone","GasDrone","GasDrone","GasDrone","Drone","Overlord","Zergling","Zergling","Queen","Queen","MetabolicBoost","Drone","Drone","Drone","Zergling","Drone","Drone","Overlord","InjectLarva","InjectLarva","Queen","Drone","Drone","Drone","Drone","Overlord","Drone","InjectLarva","InjectLarva","Hatchery","Drone","SpawnCreepTumor","Drone","Drone","Drone","Drone","Drone","Drone","Drone","Drone","Overlord","Drone","InjectLarva","InjectLarva","RoachWarren","Drone","Drone","Queen","Drone","Drone","EvolutionChamber","EvolutionChamber","Drone","Drone","Overlord","InjectLarva","InjectLarva","Drone","Drone","Drone","Drone","Drone","Drone","Drone","Drone","Extractor","Extractor","SpawnCreepTumor","Lair","Zergling","Zergling","MissleAttacksLevel1","GroundCarapaceLevel1","InjectLarva","Drone","Drone","Drone","Drone","GasDrone","GasDrone","GasDrone","GasDrone","GasDrone","GasDrone","InjectLarva","Overlord","Extractor","Drone","Drone","Drone","Drone","Drone","Drone","InjectLarva","Overlord","Roach","Roach","Roach","Roach","Roach","Roach","InjectLarva","GasDrone","GasDrone","GasDrone","Extractor","Extractor","Overlord","Overlord","InjectLarva","Roach","Roach","Roach","Roach","Roach","InjectLarva","GasDrone","GasDrone","GasDrone","GasDrone","GasDrone","GasDrone","Ravager","Ravager","Ravager","Ravager"],"CreationDate":1448121847947,"Description":"Solar vs TY game 2. Solar easily crushed TY\u0027s tank-marine-liberator push.","Name":"17 Hatch into 3 base double evo RoachRavager","Race":"Zerg","SC2VersionID":"4.11.3","VisitedDate":1448270308969,"VsRace":"Terran"}