{"BuildLengthInSeconds":356,"BuildOrderItems":["DefaultItem","Drone","Overlord","Drone","Drone","Drone","Drone","Hatchery","Drone","Drone","Extractor","Drone","SpawningPool","GasDrone","GasDrone","GasDrone","Drone","Drone","Overlord","Queen","Queen","Zergling","Zergling","Drone","MetabolicBoost","Drone","Drone","Drone","Drone","Drone","Queen","InjectLarva","InjectLarva","Hatchery","Overlord","Drone","Drone","Drone","Drone","InjectLarva","InjectLarva","Drone","Drone","SpawnCreepTumor","Drone","Drone","Drone","Drone","RoachWarren","Overlord","Drone","Drone","Drone","InjectLarva","InjectLarva","Overlord","Overlord","Queen","Drone","Drone","Drone","Drone","Drone","Drone","Extractor","Extractor","InjectLarva","InjectLarva","Drone","Drone","Roach","Roach","Roach","Roach","Lair","Drone","Drone","Overlord","GasDrone","GasDrone","GasDrone","GasDrone","GasDrone","GasDrone","SporeCrawler","SporeCrawler","SporeCrawler","SpawnCreepTumor","Overlord","Overlord","Overlord","InjectLarva","InjectLarva","Roach","Roach","Roach","Roach","InjectLarva","InjectLarva","InjectLarva","GlialReconstitution","NydusNetwork","Roach","Roach","Roach","Roach","Roach","Roach","Roach","Roach","Roach","Roach","InjectLarva","InjectLarva","InjectLarva","Roach","Roach","Roach","Roach","Roach","Roach","Roach","Overlord","Overlord","NydusWorm"],"CreationDate":1448120485556,"Description":"This build was executed by Solar against TY in Grand Finals Sandisk ShoutCraft Invitational II Game 1. Very safe opener with strong timing attack.","Name":"17 Hatch into 3 base RoachLing Nydus","Race":"Zerg","SC2VersionID":"4.11.3","VisitedDate":1448270325931,"VsRace":"Terran"}