{"BuildLengthInSeconds":287,"BuildOrderItems":["DefaultItem","Drone","Overlord","Drone","Drone","Drone","Drone","Drone","Hatchery","Drone","Extractor","Drone","SpawningPool","Drone","GasDrone","GasDrone","GasDrone","Drone","Overlord","MetabolicBoost","Queen","Queen","Zergling","Zergling","Drone","Drone","Drone","Drone","Drone","Overlord","Drone","InjectLarva","Queen","InjectLarva","Drone","Drone","Drone","Drone","Overlord","InjectLarva","InjectLarva","RoachWarren","SpawnCreepTumor","Zergling","Zergling","Drone","Drone","Drone","Hatchery","Drone","Drone","Drone","Extractor","Drone","InjectLarva","InjectLarva","Drone","Overlord","SpawnCreepTumor","Drone","Drone","GasDrone","GasDrone","GasDrone","Extractor","Roach","Roach","Roach","Roach","Overlord","Drone","Drone","Drone","InjectLarva","InjectLarva","SpawnCreepTumor","Zergling","Zergling","Zergling","Drone","GasDrone","GasDrone","GasDrone","Lair","Drone","Drone","Drone","Drone","Drone","Overlord","InjectLarva","InjectLarva","SpawnCreepTumor"],"CreationDate":1446454314806,"Description":"","Name":"17 Hatch into 3 base Lair","Race":"Zerg","SC2VersionID":"4.11.3","VisitedDate":1446454331394,"VsRace":"Terran"}