{"BuildLengthInSeconds":369,"BuildOrderItems":["DefaultItem","SCV","SCV","SupplyDepot","SCV","SCV","Barracks","Refinery","SCV","SCV","GasScv","GasScv","GasScv","SCV","OrbitalCommand","ReactorOnBarracks","CommandCenter","SCV","SupplyDepot","SCV","CallMule","Marine","MarineOnReactor","Factory","SCV","Refinery","Marine","MarineOnReactor","SCV","Bunker","SCV","GasScv","GasScv","GasScv","Marine","MarineOnReactor","SCV","OrbitalCommand","CallMule","Marine","MarineOnReactor","Armory","TechLabOnFactory","SCV","Marine","MarineOnReactor","SCV","SCV","CallMule","SupplyDepot","SiegeTank","SCV","SCV","Marine","MarineOnReactor","SCV","SCV","VehicleAndShipPlatingLevel1","SupplyDepot","Marine","MarineOnReactor","SCV","SCV","CallMule","Refinery","SupplyDepot","SCV","SCV","Marine","MarineOnReactor","Thor","SCV","SCV","GasScv","GasScv","GasScv","CallMule","LiftRaxFromReactor","Factory","SCV","SCV","SupplyDepot","SCV","SCV","CommandCenter","SCV","SCV","SupplyDepot","Thor","SCV","SCV","Refinery","CallMule","SupplyDepot","LandFactoryOnReactor","Hellion","HellionOnReactor","SCV","SCV","SupplyDepot","GasScv","GasScv","GasScv","CallMule","SCV","SCV","Hellion","HellionOnReactor","SCV","SCV","VehicleAndShipPlatingLevel2","Thor","OrbitalCommand","SCV","SCV","Hellion","HellionOnReactor","Factory","TechLabOnBarracks","SCV","SCV","SupplyDepot","SupplyDepot","CallMule"],"CreationDate":1606048578966,"Description":"","Name":"2 Base Thor-Hellion","Race":"Terran","SC2VersionID":"5.0.3","VisitedDate":1606048602350,"VsRace":"Zerg"}