{"BuildLengthInSeconds":287,"BuildOrderItems":["DefaultItem","Drone","Overlord","Drone","Drone","Drone","Drone","Drone","Hatchery","Drone","Extractor","Drone","Drone","SpawningPool","GasDrone","GasDrone","GasDrone","Drone","Overlord","Drone","Drone","Queen","Queen","MetabolicBoost","Zergling","Zergling","Zergling","Drone","Drone","Drone","RoachWarren","Overlord","InjectLarva","InjectLarva","Drone","Drone","Extractor","Overlord","Drone","EvolutionChamber","Drone","GasDrone","GasDrone","GasDrone","Zergling","InjectLarva","InjectLarva","Roach","Roach","Roach","Roach","Roach","Roach","MutateVentralSacs","Overlord","InjectLarva","InjectLarva","Zergling","Zergling","Zergling","Zergling","Zergling","Zergling","Zergling","Ravager","Ravager","Ravager","Ravager","Overlord","InjectLarva","InjectLarva","Zergling","Zergling","Zergling","Zergling","Ravager","Ravager","Overlord","InjectLarva","InjectLarva","Zergling","Zergling","Zergling","Zergling","Zergling","Zergling"],"CreationDate":1449908903427,"Description":"","Name":"2 Base Ling drop into Ling-Ravager all-in","Race":"Zerg","SC2VersionID":"4.11.3","VisitedDate":1449908977611,"VsRace":"Terran"}