{"BuildLengthInSeconds":312,"BuildOrderItems":["DefaultItem","Probe","Probe","Pylon","Probe","Gateway","Probe","Assimilator","Probe","Chronoboost","Probe","GoOutProbe","Assimilator","Probe","GasProbe","Gateway","Probe","GasProbe","CyberneticsCore","GasProbe","Probe","GasProbe","Pylon","Probe","GasProbe","Probe","GasProbe","Adept","Adept","WarpgateUpgrade","TwilightCouncil","Adept","Adept","Pylon","DarkShrine","Adept","Adept","Adept","Adept","Pylon","Nexus","SwitchToWarpgate","SwitchToWarpgate","WarpInDarkTemplar","WarpInDarkTemplar","StartIdle","StopIdleIn10Seconds","StartIdle","StopIdleIn10Seconds","Gateway","Gateway","WarpInDarkTemplar","WarpInSentry","Probe","Probe","Assimilator","Assimilator","Pylon","SwitchToWarpgate","SwitchToWarpgate","GasProbe","GasProbe","WarpInStalker","WarpInStalker"],"CreationDate":1541916705477,"Description":"Test","Name":"2 Gate 6 Adept rush DT allin","Race":"Protoss","SC2VersionID":"5.0.3","VisitedDate":1608217795746,"VsRace":"Protoss"}