{"BuildLengthInSeconds":275,"BuildOrderItems":["DefaultItem","SCV","SCV","SupplyDepot","SCV","SCV","Barracks","Refinery","GoOutScv","SCV","SCV","GasScv","GasScv","GasScv","Barracks","SCV","SupplyDepot","Reaper","OrbitalCommand","Refinery","Reaper","CallMule","SCV","GasScv","GasScv","GasScv","Reaper","SCV","Reaper","SCV","CommandCenter","SCV","Reaper","SupplyDepot","SCV","Reaper","SCV","Factory","CallMule","TechLabOnBarracks","SCV","SCV","ReactorOnBarracks","StimPack","Marine","EngineeringBay","SCV","OrbitalCommand","TechLabOnFactory","Marine","SCV","Starport","SCV","SCV","Marine","MarineOnReactor","Marine","CallMule","CallMule","SiegeTank","Refinery","SCV","SCV","SupplyDepot","Marine","Marine","MarineOnReactor","Medivac","SCV","SCV","GasScv","GasScv","GasScv"],"CreationDate":1449265969779,"Description":"Use double reapers to hit opponent\u0027s economy. 2nd barracks may be proxied.","Name":"2 Rax Reaper CC","Race":"Terran","SC2VersionID":"4.11.3","VisitedDate":1449266033122,"VsRace":"Terran"}