{"BuildLengthInSeconds":461,"BuildOrderItems":["DefaultItem","SCV","SCV","SCV","SCV","SupplyDepot","SCV","SCV","Barracks","Refinery","SCV","SCV","GasScv","GasScv","GasScv","SCV","OrbitalCommand","Reaper","SupplyDepot","SCV","CallMule","Reaper","SCV","SCV","CommandCenter","Factory","SCV","ReactorOnBarracks","SCV","SupplyDepot","SCV","CallMule","SCV","Refinery","LiftRaxFromReactor","LandFactoryOnReactor","Hellion","HellionOnReactor","Starport","SCV","TechLabOnBarracks","GasScv","GasScv","GasScv","OrbitalCommand","SCV","Hellion","HellionOnReactor","SCV","LiftRaxFromTechLab","LandStarportOnTechLab","Banshee","SCV","CallMule","SCV","CallMule","SupplyDepot","Hellion","HellionOnReactor","Armory","SCV","SCV","SupplyDepot","Hellion","HellionOnReactor","Banshee","SCV","SCV","SCV","CommandCenter","SCV","SCV","WidowMine","WidowMineOnReactor","ScannerSweep","TechLabOnBarracks"],"CreationDate":1439884108286,"Description":"","Name":"2 Reaper CC into Helbat-Banshee push","Race":"Terran","SC2VersionID":"2.2.0","VisitedDate":1439884151092,"VsRace":"Zerg"}