{"BuildLengthInSeconds":268,"BuildOrderItems":["DefaultItem","SCV","SCV","SupplyDepot","SCV","SCV","Barracks","Refinery","SCV","SCV","Refinery","GasScv","GasScv","GasScv","SCV","GasScv","GasScv","GasScv","ReactorOnBarracks","OrbitalCommand","SupplyDepot","Bunker","Factory","SCV","CallMule","Marine","MarineOnReactor","SCV","SCV","Marine","MarineOnReactor","SupplyDepot","SCV","Armory","TechLabOnFactory","Marine","MarineOnReactor","SCV","SupplyDepot","CallMule","SCV","Marine","MarineOnReactor","SCV","Marine","MarineOnReactor","SCV","Thor","SupplyDepot","SCV","Marine","MarineOnReactor","SCV","SupplyDepot","SCV","Marine","MarineOnReactor","Thor","SCV","CallMule","Marine","MarineOnReactor","SupplyDepot","SCV","VehicleAndShipPlatingLevel1"],"CreationDate":1606047752320,"Description":"","Name":"2 Thor Push","Race":"Terran","SC2VersionID":"5.0.3","VisitedDate":1606047773272,"VsRace":"Protoss"}