{"BuildLengthInSeconds":288,"BuildOrderItems":["DefaultItem","SCV","SCV","SupplyDepot","SCV","SCV","Barracks","Refinery","GoOutScv","SCV","SCV","GasScv","GasScv","GasScv","SCV","SupplyDepot","Marine","OrbitalCommand","Marine","Factory","SCV","CallMule","Marine","SCV","CommandCenter","SCV","Marine","SCV","Starport","Refinery","Marine","SCV","SupplyDepot","TechLabOnFactory","SCV","Marine","CallMule","GasScv","GasScv","GasScv","LiftFactoryFromTechLab","LandStarportOnTechLab","Banshee","SCV","TechLabOnFactory","Marine","SCV","OrbitalCommand","SCV","Marine","SiegeTank","SupplyDepot","SCV","SCV","Marine","CallMule","Banshee","SCV","Barracks","SCV","SCV","Marine","SCV","SiegeTank","SupplyDepot","SCV","Refinery","SCV","Marine","SCV","SCV","Liberator","SCV","GasScv","GasScv","GasScv","SupplyDepot","Marine","Barracks"],"CreationDate":1453553146897,"Description":"Build non-stop marines,  2 banshees and 2 tanks.\n\n@04:06 when second tank is ready - take 4-5 SCV and go to push. In move buy liberators,  tanks, marines.\n\nWe have good eco,  and if not defeat opponent instantly - can go third CC and play macro.\n\n","Name":"2-CC Marine Banshee Tank Liberator push","Race":"Terran","SC2VersionID":"4.11.3","VisitedDate":1470914148315,"VsRace":"Zerg"}