{"BuildLengthInSeconds":272,"BuildOrderItems":["DefaultItem","SCV","SCV","SupplyDepot","SCV","Barracks","SCV","Refinery","SCV","SCV","GasScv","GasScv","GasScv","SCV","OrbitalCommand","ReactorOnBarracks","SupplyDepot","Barracks","Barracks","SCV","CallMule","SCV","Marine","MarineOnReactor","Bunker","SCV","SupplyDepot","TechLabOnBarracks","Marine","MarineOnReactor","TechLabOnBarracks","SCV","StimPack","Marauder","Marine","MarineOnReactor","SCV","Marauder","SupplyDepot","CallMule","SCV","Marine","MarineOnReactor","Marauder","SalvageBunker","SupplyDepot","SCV","Marauder","Marine","MarineOnReactor","Refinery","SCV","Marauder","SupplyDepot","Marine","MarineOnReactor","Marauder","GasScv","GasScv","GasScv","SCV","Marauder","Marine","MarineOnReactor","CallSupplyDrop","Marauder","CombatShield","Marine","MarineOnReactor","Marauder","Marauder","Marine","MarineOnReactor"],"CreationDate":1516282906623,"Description":"Fake that you took natural with bunker on low ground.\n\nPush out wnen stim is done. Bring 10 scv with you (4 from gas and 6 from minerals). You must destroy natural and kill a lot of probes or you lose.","Name":"3Rax Stim Rush","Race":"Terran","SC2VersionID":"5.0.3","VisitedDate":1607959254334,"VsRace":"Protoss"}