{"BuildLengthInSeconds":317,"BuildOrderItems":["DefaultItem","SCV","SCV","SupplyDepot","SCV","SCV","Barracks","Refinery","SCV","Refinery","SCV","GasScv","GasScv","GasScv","SCV","GasScv","GasScv","GasScv","Marine","OrbitalCommand","GhostAcademy","TechLabOnBarracks","SupplyDepot","SCV","CallMule","Ghost","SCV","Factory","SCV","SupplyDepot","SCV","Ghost","SCV","CallMule","SCV","TechLabOnFactory","SCV","CommandCenter","SiegeTank","SCV","Ghost","SCV","SupplyDepot","SCV","Starport","SCV","Refinery","Refinery","CallMule","SCV","Ghost","SCV","GasScv","GasScv","GasScv","GasScv","GasScv","GasScv","OrbitalCommand","Medivac","SCV","SiegeTank","SCV","SCV","CallMule","SupplyDepot","SCV","SCV","Liberator","CallMule","CommandCenter"],"CreationDate":1520134983380,"Name":"4 Ghost Drop","Race":"Terran","SC2VersionID":"5.0.3","VisitedDate":1607959253721,"VsRace":"Zerg"}