{"BuildLengthInSeconds":380,"BuildOrderItems":["DefaultItem","SCV","SCV","SupplyDepot","SCV","Refinery","SCV","Barracks","SCV","GasScv","GasScv","GasScv","Refinery","SCV","SCV","GasScv","GasScv","GasScv","OrbitalCommand","Factory","Reaper","SupplyDepot","SCV","CallMule","SCV","Marine","Starport","Hellion","SCV","ReactorOnBarracks","SupplyDepot","SCV","Hellion","SCV","FusionCore","SCV","CallMule","LiftRaxFromReactor","LandFactoryOnReactor","SupplyDepot","WidowMine","WidowMineOnReactor","TechLabOnStarport","CommandCenter","BattleCruiser","SupplyDepot","WidowMine","WidowMineOnReactor","CallMule","SCV","EngineeringBay","SCV","Refinery","Refinery","Marine","SCV","MissileTurret","SCV","GasScv","GasScv","GasScv","GasScv","GasScv","GasScv","BattleCruiser","OrbitalCommand","CallMule","WidowMine","WidowMineOnReactor","Armory","Marine","SCV","SCV","CallMule","Bunker","SupplyDepot","WidowMine","WidowMineOnReactor","TechLabOnBarracks","SCV","SCV","BattleCruiser","LiftFactoryFromReactor","LiftRaxFromTechLab","LandFactoryOnTechLab","LandRaxOnReactor","CallMule","SupplyDepot","SCV","SCV","Marine","DrillingClaws","VehicleAndShipPlatingLevel1"],"CreationDate":1547407073427,"Description":"In TvT its better to go by air and blink to base when hit points on red.\nIn TvZ its better to blink in mineral line ASAP with 1st battlecruiser. Its better to learn Yamato gun in TvZ after 1st BC will be in 50%. YG very good against zerg\u0027s Queen. \nMines - for early deffence in mineral line. or it can save you from ling/bain cheese.\nGood for 2x2 if at least 1 zerg playing against you.\nNot good in TvP","Name":"Battelecruiser TvT and TvZ","Race":"Terran","SC2VersionID":"5.0.3","VisitedDate":1607959253108,"VsRace":"Terran"}