{"BuildLengthInSeconds":378,"BuildOrderItems":["DefaultItem","SCV","SCV","SupplyDepot","SCV","Refinery","SCV","Barracks","GasScv","GasScv","GasScv","SCV","SCV","SCV","OrbitalCommand","Reaper","CommandCenter","SCV","CallMule","Factory","SCV","ReactorOnBarracks","SupplyDepot","SCV","Refinery","SCV","GasScv","GasScv","GasScv","SCV","Starport","LiftRaxFromReactor","LandFactoryOnReactor","Hellion","HellionOnReactor","OrbitalCommand","SCV","TechLabOnBarracks","CallMule","SCV","Hellion","HellionOnReactor","SCV","SCV","CallMule","LiftRaxFromTechLab","LandStarportOnTechLab","Viking","SupplyDepot","SCV","SCV","Hellion","HellionOnReactor","SCV","SCV","SupplyDepot","Raven","SCV","Hellion","HellionOnReactor","CallMule","SupplyDepot","SCV","SCV","Armory","Hellion","HellionOnReactor","SCV","SCV","SupplyDepot","CallMule","SupplyDepot","SCV","SCV","Banshee","Hellion","HellionOnReactor","SCV","SCV","SupplyDepot","Refinery","Refinery","SCV","SCV","Hellion","HellionOnReactor","Factory","Factory","CallMule","SCV","SCV","GasScv","GasScv","GasScv","GasScv","GasScv","GasScv","LiftStarportFromTechLab","TechLabOnStarport","CommandCenter","SCV","SCV","Hellion","HellionOnReactor","CallMule","SupplyDepot","SupplyDepot","SCV","SCV","LiftStarportFromTechLab","ReactorOnStarport","SupplyDepot","SCV","SCV","LandFactoryOnTechLab","LandFactoryOnTechLab","SCV","SCV","Thor","Thor","Hellion","HellionOnReactor","SupplyDepot","Medivac","MedivacOnReactor"],"CreationDate":1515757223722,"Description":"","Name":"Beastyqt ReaperCC into ThorHelbat","Race":"Terran","SC2VersionID":"5.0.3","VisitedDate":1515966728136,"VsRace":"Zerg"}