{"BuildLengthInSeconds":333,"BuildOrderItems":["DefaultItem","Drone","Overlord","Drone","Drone","Drone","Drone","Hatchery","Drone","Drone","Extractor","Drone","SpawningPool","Drone","GasDrone","GasDrone","GasDrone","Drone","Drone","Overlord","Drone","Drone","Queen","Queen","Drone","Zergling","MetabolicBoost","Drone","Drone","Drone","Zergling","InjectLarva","InjectLarva","Hatchery","Overlord","Drone","Queen","Drone","Drone","Overlord","InjectLarva","InjectLarva","Drone","Drone","Drone","Drone","Drone","Drone","Drone","Drone","Overlord","Extractor","Extractor","Zergling","Zergling","InjectLarva","InjectLarva","Drone","Drone","Drone","Drone","Drone","Drone","Drone","GasDrone","GasDrone","GasDrone","GasDrone","GasDrone","GasDrone","Drone","Lair","Drone","SporeCrawler","SporeCrawler","Zergling","Extractor","InjectLarva","InjectLarva","Queen","SporeCrawler","Drone","Drone","Drone","Drone","Drone","Drone","Drone","Drone","GasDrone","GasDrone","GasDrone","Overlord","Overlord","Overlord","InjectLarva","InjectLarva","InjectLarva","HydraliskDen","Drone","Drone","Drone","Drone","Drone","Drone","Drone","Drone","Drone","InjectLarva","InjectLarva","InjectLarva","Hydralisk","Hydralisk","Hydralisk","Hydralisk","Hydralisk","Hydralisk","Hydralisk","Hydralisk","Hydralisk","Hydralisk","Hydralisk","MuscularAugments","Overlord","Overlord"],"CreationDate":1514998881806,"Description":"","Name":"Birdys 3 base linghydra timing attack","Race":"Zerg","SC2VersionID":"4.11.3","VisitedDate":1514998920963,"VsRace":"Protoss"}