{"BuildLengthInSeconds":538,"BuildOrderItems":["DefaultItem","Drone","Drone","Drone","Overlord","Drone","Drone","Drone","Drone","Drone","Drone","SpawningPool","Drone","Drone","Hatchery","Drone","Extractor","Drone","Drone","GasDrone","GasDrone","GasDrone","Overlord","Drone","Queen","Zergling","Drone","MetabolicBoost","Queen","Overlord","Drone","Drone","BanelingNest","InjectLarva","Drone","Drone","Drone","Overlord","Drone","InjectLarva","InjectLarva","Drone","Drone","Drone","Drone","Drone","Drone","Drone","Drone","Drone","Overlord","Drone","Drone","InjectLarva","Drone","Drone","Extractor","Extractor","InjectLarva","Lair","Drone","Drone","Drone","Drone","Drone","Drone","Extractor","GasDrone","GasDrone","GasDrone","GasDrone","GasDrone","GasDrone","Overlord","Drone","Drone","Drone","Drone","InjectLarva","Drone","Drone","Drone","InjectLarva","GasDrone","GasDrone","GasDrone","Overlord","Zergling","Zergling","Drone","Drone","Drone","Drone","InjectLarva","InjectLarva","Spire","Hatchery","Drone","Drone","Drone","Drone","Overlord","Drone","Drone","Drone","Drone","Drone","Drone","Drone","InjectLarva","InjectLarva","Overlord","Overlord","Overlord","Overlord","InjectLarva","InjectLarva","FlyerCarapaceLevel1","Mutalisk","Mutalisk","Mutalisk","Mutalisk","Mutalisk","Mutalisk","Mutalisk","Mutalisk","Mutalisk","Zergling","Zergling","Zergling","Zergling","Zergling"],"CreationDate":1428424396991,"Description":"","Name":"Blade Mutalisk Opening","Race":"Zerg","SC2VersionID":"2.2.0","VisitedDate":1428424396991,"VsRace":"Zerg"}