{"BuildLengthInSeconds":413,"BuildOrderItems":["DefaultItem","SCV","SCV","SupplyDepot","SCV","Refinery","SCV","Barracks","GasScv","GasScv","GasScv","SCV","Refinery","SCV","SCV","GasScv","GasScv","GasScv","Factory","OrbitalCommand","ReactorOnBarracks","MineralScv","MineralScv","MineralScv","SupplyDepot","SCV","CallMule","SCV","Starport","LiftRaxFromReactor","LandFactoryOnReactor","Hellion","HellionOnReactor","SCV","SupplyDepot","SCV","Hellion","HellionOnReactor","GasScv","GasScv","GasScv","Medivac","CallMule","CommandCenter","ReactorOnBarracks","SCV","SupplyDepot","Liberator","SCV","Hellion","HellionOnReactor","SupplyDepot","SCV","WidowMine","WidowMineOnReactor","SCV","LiftRaxFromReactor","LandStarportOnReactor","SupplyDepot","Liberator","Refinery","Refinery","OrbitalCommand","LiberatorOnReactor","SCV","GasScv","GasScv","GasScv","WidowMine","WidowMineOnReactor","GasScv","GasScv","GasScv","Liberator","SCV","CallMule","SCV","Armory","SCV","SCV","TechLabOnBarracks","SupplyDepot","CallMule","SCV","SCV","WidowMine","WidowMineOnReactor","Liberator","LiberatorOnReactor","SupplyDepot","SCV","SCV","CallMule","LiftRaxFromTechLab","LiftFactoryFromReactor","LandRaxOnReactor","LandFactoryOnTechLab","DrillingClaws","VehicleAndShipPlatingLevel1","SCV","SCV","CallMule","Cyclone","EngineeringBay","SupplyDepot","SCV","SCV","Liberator","LiberatorOnReactor","SCV","SCV","SupplyDepot","Cyclone","CommandCenter","SCV","SCV","CallMule"],"CreationDate":1547406280253,"Description":"Very good cheese built order for 2x2 in some open maps that good for air.\nSome times it may be played through proxy starport for yearly drop.","Name":"BratOK hellion drop for 2x2","Race":"Terran","SC2VersionID":"5.0.3","VisitedDate":1607959252518,"VsRace":"Zerg"}