{"BuildLengthInSeconds":347,"BuildOrderItems":["DefaultItem","Drone","Overlord","Drone","Drone","Drone","Drone","Hatchery","Drone","Drone","Extractor","SpawningPool","Drone","Drone","GasDrone","GasDrone","GasDrone","Drone","Overlord","Queen","Zergling","Zergling","Queen","MetabolicBoost","Zergling","Drone","Drone","Drone","Drone","InjectLarva","InjectLarva","Hatchery","Drone","Drone","Drone","Drone","Overlord","Drone","InjectLarva","Drone","InjectLarva","Zergling","Zergling","Zergling","Zergling","Zergling","Zergling","RoachWarren","Drone","Overlord","Drone","InjectLarva","Drone","Drone","InjectLarva","Overlord","Queen","Drone","Drone","Drone","Drone","Roach","Roach","Roach","Roach","Roach","InjectLarva","InjectLarva","Extractor","Lair","Overlord","Zergling","Drone","Drone","Drone","SpawnCreepTumor","EvolutionChamber","Extractor","GasDrone","GasDrone","GasDrone","Drone","Drone","InjectLarva","InjectLarva","Zergling","Zergling","Zergling","Drone","Drone","Drone","Drone","Drone","Drone","Drone","Drone","GasDrone","GasDrone","GasDrone","MissleAttacksLevel1","Overlord","InjectLarva","InjectLarva","InjectLarva","GlialReconstitution","Burrow","Drone","Drone","Drone","Drone","Overlord","Drone","Extractor","Drone","Drone","Drone","Drone","Overlord","InjectLarva","InjectLarva","InjectLarva","GasDrone","GasDrone","GasDrone","Roach","Roach","Roach","Roach","Overlord","Roach","Roach","Roach","Roach"],"CreationDate":1514441670496,"Description":"Solid ZvZ build, instant win if opponent does not scout or build an overseer.\n\nHatch - Extractor - Pool (17-18-17)\n\n@Pool - x2 Zergling, Metabolic boost, 2 Queens\n\n@30 supply - 3rd Hatch\n\n@35 supply - x7 Zergling\n\n@42 supply - Roach Warren\n\n@50 supply - x5 Roach\n\n@58 supply - (4:18) Lair, x2 Evolution Chamber\n\n@Liar - Roach speed\n\n@Roach Speed - Burrow and Tunneling claws\n\n","Name":"Burrow Roach solid build","Race":"Zerg","SC2VersionID":"4.11.3","VisitedDate":1514441807734,"VsRace":"Zerg"}