{"BuildLengthInSeconds":548,"BuildOrderItems":["DefaultItem","SCV","SCV","SCV","SCV","SupplyDepot","SCV","SCV","SCV","SCV","CommandCenter","SCV","Barracks","SCV","Barracks","SCV","GoOutScv","SCV","OrbitalCommand","Marine","OrbitalCommand","Marine","Marine","Refinery","Refinery","SCV","CallMule","Marine","SCV","CallMule","Marine","SCV","GasScv","GasScv","GasScv","GasScv","GasScv","GasScv","SupplyDepot","SCV","SCV","Marine","Marine","Bunker","SCV","SCV","TechLabOnBarracks","ReactorOnBarracks","EngineeringBay","SCV","SCV","SupplyDepot","Marauder","StimPack","CallMule","SCV","SCV","InfantryWeaponsLevel1","CallMule","SupplyDepot","SCV","SCV","Marine","MarineOnReactor","Marauder","SCV","SCV","Barracks","SupplyDepot","Marine","MarineOnReactor","SCV","SCV","Marauder","SCV","SCV","Factory","Marine","MarineOnReactor","SupplyDepot","SCV","CallMule","SCV","Marauder","Refinery","Marine","MarineOnReactor","CallMule","SupplyDepot","TechLabOnBarracks","SCV","SCV","SupplyDepot","Marauder","GasScv","GasScv","GasScv","Marine","MarineOnReactor","SCV","SCV","Starport","ReactorOnFactory","Marauder","CombatShield","SCV","SCV","SupplyDepot","Marauder","Marine","MarineOnReactor","SupplyDepot","SCV","SCV","Marauder","InfantryArmorLevel1","ConcussiveShells","CallMule","SCV","SCV","Marine","MarineOnReactor","Marauder","LiftFactoryFromReactor","LandStarportOnReactor","CallMule","Medivac","MedivacOnReactor","Barracks","Barracks","Refinery"],"CreationDate":1439828934267,"Description":"","Name":" CC First - 2 Rax 2 Gas EBay - 3 Rax Stim with plus 1 push","Race":"Terran","SC2VersionID":"2.2.0","VisitedDate":1439901404150,"VsRace":"Protoss"}