{"BuildLengthInSeconds":307,"BuildOrderItems":["DefaultItem","SCV","SCV","SupplyDepot","SCV","SCV","Barracks","Refinery","SCV","Barracks","SCV","GasScv","GasScv","GasScv","Refinery","SCV","Reaper","SCV","GasScv","GasScv","GasScv","Barracks","SupplyDepot","Reaper","SCV","Reaper","OrbitalCommand","Barracks","Reaper","Reaper","SCV","CallMule","Reaper","SupplyDepot","SCV","Reaper","Reaper","SCV","Reaper","Reaper","SupplyDepot","SCV","Reaper","Reaper","CallMule","SCV","Reaper","Reaper","CommandCenter","Reaper","SCV","Reaper","Reaper","Reaper","Reaper","Reaper","Reaper","Reaper","Reaper","Barracks","Barracks","Barracks","Barracks"],"CreationDate":1449154852167,"Name":"cheese mass reaper","Race":"Terran","SC2VersionID":"5.0.3","VisitedDate":1470914149552,"VsRace":"Zerg"}