{"BuildLengthInSeconds":297,"BuildOrderItems":["DefaultItem","SCV","SCV","SupplyDepot","SCV","SCV","Barracks","Refinery","SCV","Barracks","SCV","GasScv","GasScv","GasScv","SCV","Barracks","Reaper","Refinery","SupplyDepot","SCV","Reaper","GasScv","GasScv","GasScv","Reaper","Barracks","Reaper","SupplyDepot","Reaper","Reaper","SCV","Reaper","SCV","Reaper","SCV","Reaper","Reaper","SupplyDepot","SCV","Reaper","Reaper","Reaper","Reaper","CommandCenter","Reaper","Reaper","SupplyDepot","Reaper","Reaper","SCV","Reaper","SCV","Reaper","Refinery","Refinery","SCV","Reaper"],"CreationDate":1547405935633,"Description":"Build by BratOK. Very good for early pushing with zerg in 2x2, but in 1x1 good either. Also may works against terran","Name":"Cheese mass reaper BratOK","Race":"Terran","SC2VersionID":"5.0.3","VisitedDate":1607959251828,"VsRace":"Zerg"}