{"BuildLengthInSeconds":433,"BuildOrderItems":["DefaultItem","SCV","SCV","SupplyDepot","SCV","SCV","Barracks","Refinery","SCV","GoOutScv","SCV","GasScv","GasScv","GasScv","SCV","OrbitalCommand","Reaper","CommandCenter","SCV","CallMule","SupplyDepot","ReactorOnBarracks","SCV","SCV","Bunker","Factory","Refinery","SCV","Marine","MarineOnReactor","SCV","GasScv","GasScv","GasScv","SCV","Marine","MarineOnReactor","CallMule","OrbitalCommand","SCV","Starport","Hellion","SCV","Marine","MarineOnReactor","SCV","CallMule","SCV","TechLabOnFactory","SupplyDepot","SCV","Marine","MarineOnReactor","SCV","SCV","SCV","LiftFactoryFromTechLab","LandStarportOnTechLab","Raven","TechLabOnFactory","SupplyDepot","Marine","MarineOnReactor","SCV","SCV","CallMule","CommandCenter","SCV","SCV","SiegeTank","SupplyDepot","Marine","MarineOnReactor","SCV","SCV","CallMule","Refinery","Refinery","Banshee","CloakingField","SCV","SCV","SupplyDepot","Marine","MarineOnReactor","GasScv","GasScv","GasScv","GasScv","GasScv","GasScv","SCV","SCV","SupplyDepot","CallMule","SiegeTank","SCV","SCV","Marine","MarineOnReactor","SCV","SCV","Banshee","OrbitalCommand","Marine","MarineOnReactor","Factory","Factory","CallMule","SCV","SCV","SiegeTank","SupplyDepot","SCV","SCV","LiftRaxFromReactor","TechLabOnBarracks","SCV","Refinery","Refinery","CallMule","SupplyDepot","SCV","SCV","SCV","Banshee","SupplyDepot","LiftRaxFromTechLab","SCV","SCV","SCV","GasScv","GasScv","GasScv","GasScv","GasScv","GasScv","CallMule","SiegeTank","SupplyDepot","LandFactoryOnReactor","LandFactoryOnTechLab","SiegeTank","Hellion","HellionOnReactor","SCV","SCV","SCV","Armory","Armory","InfernalPreIgniter","SCV","SCV","SCV","CallMule","SupplyDepot","Hellion","HellionOnReactor","SiegeTank","SiegeTank","SCV","SCV","SCV","CallMule","Banshee","SupplyDepot","SupplyDepot","SCV","SCV","SCV","Hellion","HellionOnReactor","VehicleWeaponsLevel1","VehicleAndShipPlatingLevel1"],"CreationDate":1608237387843,"Description":"https://youtu.be/GBp-Y53LaNQ\n\nA solid way of opening into speed banshee mech in tvp. Special vs Parting - https://lotv.spawningtool.com/64332/ Replay - https://drop.sc/replay/17531590","Name":"Classic ReaperCC into Mech","Race":"Terran","SC2VersionID":"5.0.3","VisitedDate":1608315914058,"VsRace":"Protoss"}