{"BuildLengthInSeconds":596,"BuildOrderItems":["DefaultItem","Probe","Probe","Probe","Pylon","Probe","Probe","Chronoboost","Probe","Probe","Chronoboost","Gateway","Probe","Assimilator","Probe","Pylon","Probe","Chronoboost","GasProbe","GasProbe","GasProbe","Probe","Probe","CyberneticsCore","Assimilator","Probe","Chronoboost","Probe","GasProbe","GasProbe","GasProbe","Probe","MothershipCore","Nexus","Pylon","WarpgateUpgrade","Sentry","Probe","Chronoboost","Probe","Probe","RoboticsFacility","Sentry","Probe","Probe","Gateway","Probe","Pylon","Probe","Stalker","Probe","Probe","Observer","Probe","Chronoboost","Probe","Probe","Chronoboost","Probe","Stalker","Pylon","Probe","Probe","RoboticsBay","Probe","Probe","Assimilator","Assimilator","Probe","Probe","WarpPrism","Pylon","Stalker","Probe","Probe","GasProbe","GasProbe","GasProbe","GasProbe","GasProbe","GasProbe","Probe","Probe","Pylon","Colossus","Chronoboost","ExtendedThermalLance","Chronoboost","Chronoboost","Chronoboost","Chronoboost","Chronoboost","Probe","Probe","Pylon","Probe","Probe","Gateway","Gateway","Gateway","Gateway","Gateway","Pylon","Colossus","Chronoboost","Chronoboost","Chronoboost","Probe","Probe","Pylon","SwitchToWarpgate","SwitchToWarpgate","WarpInSentry","WarpInSentry","Probe","Probe","SwitchToWarpgate","SwitchToWarpgate","SwitchToWarpgate","SwitchToWarpgate","SwitchToWarpgate","WarpInZealot","WarpInZealot","WarpInZealot","WarpInZealot","WarpInZealot","WarpInZealot","WarpInZealot"],"CreationDate":1429701950075,"Description":"This build was executed by Classic in game 2 of RO16 WCS 2015 versus Polt. The idea is to tech fast to warp prism and Colossus with range upgrade. Drop colossus and warp in a bunch of zealots to destroy terran economy.","Name":"Classic 2 Base Colossus Drop","Race":"Protoss","SC2VersionID":"2.2.0","VisitedDate":1429701950075,"VsRace":"Terran"}