{"BuildLengthInSeconds":352,"BuildOrderItems":["DefaultItem","SCV","SCV","SupplyDepot","SCV","Refinery","SCV","Barracks","GasScv","GasScv","GasScv","SCV","SCV","SCV","OrbitalCommand","Reaper","CommandCenter","Refinery","SCV","CallMule","SupplyDepot","Reaper","SCV","GasScv","GasScv","GasScv","Factory","SCV","SCV","Marine","SCV","OrbitalCommand","SCV","Starport","TechLabOnBarracks","CallMule","Cyclone","SCV","LiftRaxFromTechLab","TechLabOnBarracks","SCV","SCV","CallMule","SupplyDepot","SCV","SCV","LandStarportOnTechLab","Banshee","CloakingField","SCV","SCV","Barracks","Barracks","SCV","SCV","LiftRaxFromTechLab","LandFactoryOnTechLab","SiegeTank","TechLabOnBarracks","SCV","SCV","CallMule","SupplyDepot","Refinery","Refinery","SCV","SCV","Banshee","CallMule","SCV","SCV","CommandCenter","GasScv","GasScv","GasScv","GasScv","GasScv","GasScv","SupplyDepot","SCV","SCV","SiegeTank","ReactorOnBarracks","ReactorOnBarracks","SCV","SCV","StimPack","CallMule","SCV","SCV","EngineeringBay","EngineeringBay","LiftStarportFromTechLab","ReactorOnStarport","SupplyDepot","SupplyDepot","SCV","SCV","Marine","MarineOnReactor","Marine","MarineOnReactor","SCV","SCV","CallMule","InfantryWeaponsLevel1","InfantryArmorLevel1","Marine","SiegeTank","SCV","SCV","OrbitalCommand","Marine","MarineOnReactor","Marine","MarineOnReactor","Marine","Medivac","MedivacOnReactor"],"CreationDate":1517056274850,"Name":"DoubleReaperCC into Cloakshee","Race":"Terran","SC2VersionID":"5.0.3","VisitedDate":1607959251167,"VsRace":"Terran"}