{"BuildLengthInSeconds":439,"BuildOrderItems":["DefaultItem","SCV","SCV","SCV","SCV","SupplyDepot","SCV","SCV","Barracks","SCV","Refinery","SCV","SCV","GasScv","GasScv","GasScv","SCV","Reaper","OrbitalCommand","CommandCenter","CallMule","SCV","SupplyDepot","ReactorOnBarracks","SCV","Factory","SCV","Bunker","SCV","Marine","MarineOnReactor","SCV","CallMule","LiftRaxFromReactor","SCV","LandFactoryOnReactor","OrbitalCommand","Hellion","HellionOnReactor","SCV","Factory","ReactorOnBarracks","SCV","Hellion","HellionOnReactor","CallMule","SupplyDepot","SCV","SCV","SupplyDepot","SCV","SCV","Hellion","HellionOnReactor","LiftRaxFromReactor","LandFactoryOnReactor","CallMule","Hellion","HellionOnReactor","SupplyDepot","SCV","SCV","Armory","SCV","Hellion","HellionOnReactor","Hellion","HellionOnReactor","SCV","SCV","SupplyDepot","SupplyDepot","CallMule","SCV","SCV"],"CreationDate":1442392877636,"Description":"","Name":"Double Reactor Helbat push","Race":"Terran","SC2VersionID":"2.2.0","VisitedDate":1442392891624,"VsRace":"Zerg"}