{"BuildLengthInSeconds":584,"BuildOrderItems":["DefaultItem","SCV","SCV","SCV","SCV","SupplyDepot","SCV","SCV","Refinery","SCV","Barracks","GasScv","GasScv","GasScv","SCV","SCV","SCV","Factory","OrbitalCommand","Marine","SupplyDepot","Reaper","SCV","CallMule","Refinery","SCV","Hellion","SCV","GasScv","GasScv","GasScv","Starport","SupplyDepot","SCV","TechLabOnBarracks","Hellion","SCV","LiftRaxFromTechLab","LandStarportOnTechLab","CloakingField","SCV","CallMule","Banshee","SupplyDepot","SCV","ReactorOnBarracks","SCV","SCV","CommandCenter","SCV","Banshee","LiftRaxFromReactor","SupplyDepot","LandFactoryOnReactor","SCV","CallMule","Hellion","HellionOnReactor","SCV","Factory","ReactorOnBarracks","SupplyDepot","SCV","Hellion","HellionOnReactor","LiftStarportFromTechLab","Viking","SCV","OrbitalCommand","SCV","LandFactoryOnTechLab","LiftRaxFromReactor","Hellion","HellionOnReactor","Hellion","CallMule","SCV","InfernalPreIgniter","SupplyDepot","LandStarportOnReactor","CallMule","Viking","VikingOnReactor","SCV","Hellion","HellionOnReactor","SCV","Hellion","SupplyDepot","SCV","SCV","Viking","VikingOnReactor","SupplyDepot","SCV","SCV","Hellion","HellionOnReactor","Hellion","CallMule","SupplyDepot","SCV","SCV"],"CreationDate":1438254358855,"Description":"ForGG build.\n\nGame plan is the following:\n- Deny scout with first marine\n- Do your own scout with reaper\n- Start getting hellions while teching into Cloakshee\n- Use reaper and 2 hellions to scout and try to hit svcs which will increase potential of banshee harras\n- Expand while using your banshee to harras oponent\n- Start building hellions from reactor, build 2nd factory and 2nd reactor\n- Land starport on reactor, 2nd factory on lab and research BlueFlame while pumping 3 hellions and 2 vikings in a cycle\n- Push opponent when Blue Flame is done","Name":"Gas First Marine-Reaper-Hellion-Cloakshee into BF-Viking push","Race":"Terran","SC2VersionID":"2.2.0","VisitedDate":1438254363661,"VsRace":"Terran"}