{"BuildLengthInSeconds":519,"BuildOrderItems":["DefaultItem","SCV","SCV","SCV","SCV","SupplyDepot","SCV","Refinery","SCV","SCV","GasScv","GasScv","GasScv","Barracks","SCV","SCV","SCV","Factory","OrbitalCommand","ReactorOnBarracks","GoOutScv","SupplyDepot","SCV","CallMule","SupplyDepot","SCV","LiftRaxFromReactor","LandFactoryOnReactor","Hellion","HellionOnReactor","SCV","Starport","WidowMine","WidowMineOnReactor","SCV","SupplyDepot","SCV","CallMule","SCV","Hellion","HellionOnReactor","Medivac","SupplyDepot","SCV","Hellion","HellionOnReactor","SCV","SCV","CommandCenter","SCV","TechLabOnStarport","Factory","CallMule","SCV","Refinery","SupplyDepot","SCV","Hellion","HellionOnReactor","SCV","GasScv","GasScv","GasScv","LiftStarportFromTechLab","TechLabOnStarport","SCV","Hellion","HellionOnReactor","LandFactoryOnTechLab","SiegeTank","OrbitalCommand","SCV","Banshee","SupplyDepot","CallMule","Hellion","HellionOnReactor","SCV","SCV","CallMule","SupplyDepot","SiegeTank"],"CreationDate":1438264408844,"Description":"Walloff your ramp with supply, barracks and reactor.\nCheck if opponent has 2 gas and chose to get 2 mines after first 2 hellions or build another 2 hellions.\nUse your 6-8 hellions with medivac to harras probes.","Name":"Gas First reactored hellions into mech","Race":"Terran","SC2VersionID":"2.2.0","VisitedDate":1438264482711,"VsRace":"Protoss"}