{"BuildLengthInSeconds":367,"BuildOrderItems":["DefaultItem","SCV","SCV","SupplyDepot","SCV","Refinery","SCV","Barracks","GoOutScv","GasScv","GasScv","GasScv","SCV","SCV","SCV","OrbitalCommand","Marine","Factory","Refinery","SupplyDepot","ReactorOnBarracks","SCV","CallMule","GasScv","GasScv","GasScv","SCV","Starport","SCV","LiftRaxFromReactor","LandFactoryOnReactor","Hellion","HellionOnReactor","SCV","TechLabOnBarracks","SupplyDepot","SCV","LiftRaxFromTechLab","LandStarportOnTechLab","MineralScv","MineralScv","MineralScv","MineralScv","SCV","Hellion","HellionOnReactor","ScannerSweep","SupplyDepot","SCV","CloakingField","Banshee","SCV","SCV","Hellion","HellionOnReactor","SupplyDepot","GasScv","GasScv","SCV","Banshee","SCV","CallMule","SCV","CommandCenter","GasScv","GasScv","SCV","SCV","LiftFactoryFromReactor","Barracks","Barracks","ReactorOnFactory","LiftStarportFromTechLab","LandRaxOnTechLab","StimPack","Marine","ReactorOnStarport","SCV","SupplyDepot","SCV","EngineeringBay","Refinery","CallMule","SCV","Marine","LiftFactoryFromReactor","TechLabOnFactory","SCV","GasScv","GasScv","GasScv","LandRaxOnReactor","LandRaxOnReactor","OrbitalCommand","Marine","MarineOnReactor","Marine","MarineOnReactor","Marine","InfantryWeaponsLevel1","SCV","SiegeTank","Refinery","SCV","SCV","CallMule","Marine","Marine","MarineOnReactor","Marine","MarineOnReactor","SupplyDepot","Medivac","MedivacOnReactor","GasScv","GasScv","GasScv"],"CreationDate":1449764237296,"Description":"","Name":"Gas-Rax into 6 hellion 2 banshee push","Race":"Terran","SC2VersionID":"3.8.0","VisitedDate":1449780147958,"VsRace":"Terran"}