{"BuildLengthInSeconds":472,"BuildOrderItems":["DefaultItem","Probe","Probe","Pylon","Probe","Gateway","Probe","Assimilator","Probe","Assimilator","Probe","Chronoboost","GasProbe","GasProbe","GasProbe","Gateway","Probe","GasProbe","GasProbe","GasProbe","Probe","CyberneticsCore","Probe","Pylon","Probe","Probe","Adept","Adept","WarpgateUpgrade","Chronoboost","Chronoboost","Stalker","Stalker","Nexus","Pylon","Probe","RoboticsFacility","Probe","TwilightCouncil","Probe","SwitchToWarpgate","SwitchToWarpgate","WarpInSentry","WarpInSentry","Probe","Immortal","Chronoboost","Probe","Probe","WarpInStalker","WarpInStalker","Probe","Probe","Pylon","Observer","Chronoboost","Probe","Probe","Charge","Chronoboost","Chronoboost","Pylon","Immortal","Chronoboost","Probe","Probe","Assimilator","Assimilator","Forge","Probe","Probe","Pylon","GasProbe","GasProbe","GasProbe","GasProbe","GasProbe","GasProbe","Probe","Probe","Immortal","Probe","Probe","Pylon","GroundWeaponsLevel1","Chronoboost","Chronoboost","Probe","Probe","TemplarArchives","Probe","Probe","Pylon","Observer","Gateway","Gateway","Gateway","Gateway","Observer","Gateway","Gateway","Nexus","WarpPrism","SwitchToWarpgate","SwitchToWarpgate","SwitchToWarpgate","SwitchToWarpgate","WarpInHighTemplar","WarpInHighTemplar","WarpInHighTemplar","WarpInHighTemplar","Pylon","Pylon","Probe","Probe","SwitchToWarpgate","SwitchToWarpgate","WarpInZealot","WarpInZealot","WarpInZealot","WarpInZealot","GroundWeaponsLevel2","Chronoboost","Chronoboost","Chronoboost","Pylon","Pylon","Probe","Probe","ArchonFromTwoHT","ArchonFromTwoHT","Probe","Probe","Probe","Probe","WarpInZealot","WarpInZealot","WarpInZealot","WarpInZealot","WarpInHighTemplar","WarpInHighTemplar","WarpInHighTemplar","WarpInHighTemplar"],"CreationDate":1514378017625,"Description":"","Name":"Gate-DoubleGas expand into Archons-Chargelots","Race":"Protoss","SC2VersionID":"4.11.3","VisitedDate":1514378077331,"VsRace":"Protoss"}