{"BuildLengthInSeconds":290,"BuildOrderItems":["DefaultItem","Probe","Chronoboost","Probe","Pylon","Probe","Gateway","Probe","Assimilator","GoOutProbe","Probe","Probe","GasProbe","GasProbe","GasProbe","Probe","Probe","Nexus","CyberneticsCore","Probe","Assimilator","Probe","Pylon","Probe","GasProbe","GasProbe","GasProbe","Stalker","Chronoboost","WarpgateUpgrade","Probe","Probe","Stalker","Chronoboost","Probe","Probe","Chronoboost","RoboticsFacility","Probe","Probe","Probe","Probe","Probe","Probe","Chronoboost","Gateway","Gateway","Probe","Probe","Pylon","Probe","Probe","RoboticsBay","Observer","Chronoboost","Probe","Probe","Assimilator","Assimilator","Probe","Probe","Observer","Probe","Probe","GasProbe","GasProbe","GasProbe","GasProbe","GasProbe","GasProbe","SwitchToWarpgate","SwitchToWarpgate","SwitchToWarpgate","Pylon","Pylon","Probe","Probe","Observer","Chronoboost","ExtendedThermalLance","Probe","Probe","WarpInStalker","WarpInStalker","WarpInStalker","Observer","Pylon","Pylon","Probe","Probe","Colossus","Chronoboost","Chronoboost"],"CreationDate":1514364903855,"Description":"","Name":"Gate-Nexus into Colossus","Race":"Protoss","SC2VersionID":"4.11.3","VisitedDate":1514364993877,"VsRace":"Terran"}