{"BuildLengthInSeconds":304,"BuildOrderItems":["DefaultItem","Probe","Probe","Pylon","Probe","Probe","Gateway","Assimilator","Probe","Probe","GasProbe","GasProbe","GasProbe","Probe","Probe","Nexus","CyberneticsCore","Probe","GoOutProbe","Assimilator","Probe","Pylon","Probe","GasProbe","GasProbe","GasProbe","WarpgateUpgrade","MothershipCore","Adept","Probe","RoboticsFacility","Probe","Probe","Adept","Probe","Probe","Probe","Probe","Probe","Probe","Adept","Pylon","Observer","Probe","Probe","Probe","Probe","Adept","Gateway","Gateway","Observer","TwilightCouncil","Probe","Probe","Pylon","Probe","Probe","Assimilator","Assimilator","Immortal","Chronoboost","SwitchToWarpgate","Probe","Probe","Pylon","Blink","Chronoboost","GasProbe","GasProbe","GasProbe","GasProbe","GasProbe","GasProbe","Probe","Probe","SwitchToWarpgate","SwitchToWarpgate","WarpInSentry","Pylon","Probe","Probe","WarpInSentry","Pylon","Probe","Probe","Probe","Probe","Nexus","RoboticsBay"],"CreationDate":1449910265035,"Description":"","Name":"Gate-Nexus Adepts defense into Robo","Race":"Protoss","SC2VersionID":"3.8.0","VisitedDate":1449910487287,"VsRace":"Terran"}