{"BuildLengthInSeconds":551,"BuildOrderItems":["DefaultItem","SCV","SCV","SCV","SCV","SupplyDepot","SCV","SCV","Barracks","SCV","Refinery","SCV","SCV","GasScv","GasScv","GasScv","SCV","Reaper","OrbitalCommand","CallMule","CommandCenter","SCV","SupplyDepot","SCV","Factory","ReactorOnBarracks","MineralScv","MineralScv","SCV","SCV","SCV","CommandCenter","CallMule","LiftRaxFromReactor","LandFactoryOnReactor","SCV","OrbitalCommand","Hellion","HellionOnReactor","GasScv","GasScv","Marine","SCV","SupplyDepot","SCV","SCV","CallMule","Hellion","HellionOnReactor","TechLabOnBarracks","SCV","SCV","SCV","StimPack","Marine","SCV","Barracks","CallMule","OrbitalCommand","SCV","LiftFactoryFromReactor","Barracks","ReactorOnFactory","Refinery","Marine","SCV","SCV","SupplyDepot","SCV","SCV","SCV","CallMule","Refinery","Marine","GasScv","GasScv","GasScv","CallMule","SCV","SCV","SCV","EngineeringBay","EngineeringBay","LandRaxOnReactor","Marine","MarineOnReactor","LiftFactoryFromReactor","Starport","ReactorOnFactory","Marine","GasScv","GasScv","GasScv","SCV","SCV","SCV","LandRaxOnReactor","Marine","MarineOnReactor","SupplyDepot","Marine","MarineOnReactor","SupplyDepot","CallMule","Marine","SCV","SCV","SCV","InfantryWeaponsLevel1","InfantryArmorLevel1","SupplyDepot","SCV","SCV","SCV","Marine","MarineOnReactor","Marine","MarineOnReactor","Marine","LiftFactoryFromReactor","LandStarportOnReactor","Medivac","MedivacOnReactor","CallMule","SupplyDepot","SCV","SCV","SCV","ReactorOnFactory","CallMule","Marine","MarineOnReactor","Marine","MarineOnReactor","Marine","SCV","SCV","Barracks","Barracks","SupplyDepot","SCV","SCV","CombatShield","Marine","MarineOnReactor","Marine","MarineOnReactor","Marine"],"CreationDate":1441036326436,"Description":"","Name":"GuMiho Reaper CC into Bio-Helbat Push","Race":"Terran","SC2VersionID":"2.2.0","VisitedDate":1444505598683,"VsRace":"Zerg"}