{"BuildLengthInSeconds":489,"BuildOrderItems":["DefaultItem","SCV","SCV","SCV","SCV","SupplyDepot","SCV","SCV","Barracks","SCV","Refinery","SCV","SCV","GasScv","GasScv","GasScv","SCV","Reaper","OrbitalCommand","CallMule","CommandCenter","SCV","ReactorOnBarracks","SupplyDepot","SCV","Factory","SCV","Marine","MarineOnReactor","SCV","SCV","Marine","MarineOnReactor","CallMule","Starport","SCV","OrbitalCommand","SupplyDepot","LiftRaxFromReactor","LandFactoryOnReactor","Hellion","HellionOnReactor","SCV","Marine","SCV","SCV","CallMule","SupplyDepot","Hellion","HellionOnReactor","Marine","Medivac","SCV","SCV","Refinery","SupplyDepot","Marine","CallMule","Hellion","HellionOnReactor","SCV","SCV","GasScv","GasScv","GasScv","Viking","Marine","SCV","SCV","SupplyDepot","Hellion","HellionOnReactor","SCV","SCV","CallMule","Armory","SupplyDepot","Marine","SCV","Medivac","Hellion","HellionOnReactor","SupplyDepot","SCV","SCV","Marine","CallMule","Hellion","HellionOnReactor","SCV","SCV"],"CreationDate":1441033550202,"Description":"","Name":"GuMiho 2 medivac marine helbat push","Race":"Terran","SC2VersionID":"2.2.0","VisitedDate":1444505580145,"VsRace":"Zerg"}