{"BuildLengthInSeconds":322,"BuildOrderItems":["DefaultItem","SCV","SCV","GoOutScv","SupplyDepot","SCV","Refinery","SCV","Barracks","GasScv","GasScv","GasScv","SCV","SCV","Refinery","SCV","GasScv","GasScv","GasScv","OrbitalCommand","GhostAcademy","Reaper","SupplyDepot","SCV","CallMule","MoebiusReactor","SCV","TechLabOnBarracks","SCV","SCV","StartIdle","StopIdleIn3Seconds","Ghost","Factory","SCV","SupplyDepot","SCV","CallMule","Ghost","SCV","SupplyDepot","ReactorOnFactory","SCV","SCV","SupplyDepot","Ghost","SCV","Hellion","HellionOnReactor","SCV","Ghost","SupplyDepot","CallMule","SCV","Armory","Hellion","HellionOnReactor","SCV","SCV","Hellion","HellionOnReactor","Ghost","SupplyDepot","SCV","SCV","Nuke","Hellion","HellionOnReactor","SCV","ScannerSweep","SupplyDepot","Hellion","HellionOnReactor","Ghost"],"CreationDate":1515686596308,"Description":"","Name":"Havoc 1base GhostHellbat Rush","Race":"Terran","SC2VersionID":"4.1.2","VisitedDate":1515688569313,"VsRace":"Zerg"}