{"BuildLengthInSeconds":359,"BuildOrderItems":["DefaultItem","SCV","SCV","SupplyDepot","SCV","SCV","Refinery","Barracks","SCV","Refinery","GasScv","GasScv","GasScv","SCV","SCV","GasScv","OrbitalCommand","Reaper","SupplyDepot","Factory","SCV","CallMule","ReactorOnBarracks","SCV","CommandCenter","SCV","SCV","SupplyDepot","LiftRaxFromReactor","TechLabOnBarracks","LandFactoryOnReactor","Factory","SCV","SCV","Hellion","HellionOnReactor","SCV","SCV","Hellion","HellionOnReactor","CallMule","OrbitalCommand","LiftRaxFromTechLab","Marine","LandFactoryOnTechLab","Cyclone","SCV","Marine","Hellion","HellionOnReactor","SCV","SCV","SupplyDepot","CallMule","GasScv","GasScv","SCV","SCV","Hellion","HellionOnReactor","Cyclone","Armory","CallMule","SupplyDepot","SCV","SCV","SupplyDepot","SCV","SCV","Hellion","HellionOnReactor","Starport","Refinery","SupplyDepot","SCV","SCV","Hellion","HellionOnReactor","Hellion","Refinery","SCV","SCV","CallMule","GasScv","GasScv","GasScv","SupplyDepot","CallMule","InfernalPreIgniter","SCV","SCV","SupplyDepot","ReactorOnStarport","GasScv","GasScv","GasScv","SCV","SCV","Cyclone","Hellion","HellionOnReactor","SupplyDepot","SupplyDepot","SCV","SCV","SCV","SCV","Liberator","LiberatorOnReactor","CommandCenter"],"CreationDate":1455381805033,"Description":"6 min third \nhas a plenty of mech oriented aggression to get into a strong position for playing mech in lotv","Name":"helbat clyclone 2 base timing into lib,factory, mech ","Race":"Terran","SC2VersionID":"3.0.0","VisitedDate":1470914150755,"VsRace":"Zerg"}