{"BuildLengthInSeconds":460,"BuildOrderItems":["DefaultItem","Probe","Probe","Pylon","Probe","Probe","Gateway","Assimilator","Probe","Probe","GasProbe","GasProbe","GasProbe","Probe","Probe","Nexus","CyberneticsCore","Probe","GoOutProbe","Assimilator","Probe","Pylon","Probe","GasProbe","GasProbe","GasProbe","WarpgateUpgrade","MothershipCore","Adept","Probe","TwilightCouncil","Probe","Probe","Probe","Probe","Gateway","Probe","Probe","Probe","Probe","Adept","Pylon","Blink","Probe","Probe","Forge","Probe","Probe","RoboticsFacility","Probe","Probe","Pylon","Gateway","Probe","Probe","Assimilator","Probe","Probe","SwitchToWarpgate","SwitchToWarpgate","PhotonCanon","PhotonCanon","WarpInSentry","WarpInStalker","GasProbe","GasProbe","GasProbe","Probe","Probe","Pylon","Observer","GroundWeaponsLevel1","Assimilator","Probe","Probe","SwitchToWarpgate","Pylon","Gateway","WarpInStalker","WarpInStalker","GasProbe","GasProbe","GasProbe","Probe","Probe","Observer","RoboticsBay","Probe","Probe","WarpInStalker","WarpInStalker","Pylon","Probe","Probe","Pylon","SwitchToWarpgate","WarpInStalker","WarpInStalker","WarpInStalker","WarpInStalker","Pylon","WarpInStalker","WarpInStalker","WarpInStalker","WarpInStalker","Disruptor","Nexus","Pylon","Pylon","Assimilator","Assimilator","Disruptor","Gateway","Gateway","Gateway","Gateway","Pylon","GroundArmorLevel1","Probe","Probe","PhotonCanon","Probe","Probe","Disruptor","WarpInAdept","WarpInAdept","WarpInAdept","WarpInAdept","Probe","Probe","Probe","SwitchToWarpgate","SwitchToWarpgate","SwitchToWarpgate","SwitchToWarpgate","WarpInStalker","WarpInStalker","WarpInStalker","WarpInStalker","GasProbe","GasProbe","GasProbe","GasProbe","GasProbe","GasProbe","Probe","Probe","Probe"],"CreationDate":1446220833946,"Description":"","Name":"Huk Fast Expand into Stalkers Disraptors","Race":"Protoss","SC2VersionID":"3.8.0","VisitedDate":1446220870567,"VsRace":"Terran"}