{"BuildLengthInSeconds":597,"BuildOrderItems":["DefaultItem","SCV","SCV","SCV","SCV","SupplyDepot","SCV","SCV","SCV","SCV","CommandCenter","SCV","SCV","Barracks","SCV","Refinery","SCV","GasScv","GasScv","GasScv","SCV","OrbitalCommand","Bunker","Marine","OrbitalCommand","Marine","Factory","SCV","CallMule","SCV","CallMule","Refinery","SCV","Marine","SCV","SupplyDepot","SCV","GasScv","GasScv","GasScv","SCV","ReactorOnBarracks","SCV","SCV","Starport","TechLabOnFactory","EngineeringBay","SupplyDepot","SCV","SCV","SCV","CallMule","SCV","LiftFactoryFromTechLab","CallMule","Marine","MarineOnReactor","SCV","SCV","LandStarportOnTechLab","Raven","SupplyDepot","MissileTurret","WidowMine","SCV","Marine","MarineOnReactor","SCV","Barracks","Barracks","SupplyDepot","SCV","SCV","Marine","MarineOnReactor","TechLabOnFactory","SCV","SCV","Refinery","InfantryWeaponsLevel1","SupplyDepot","Marine","MarineOnReactor","LiftStarportFromTechLab","Viking","SCV","SCV","CallMule","SupplyDepot","LiftFactoryFromTechLab","Refinery","CallMule","GasScv","GasScv","GasScv","LandRaxOnTechLab","LandRaxOnTechLab","SCV","SCV","Marine","MarineOnReactor","StimPack","Marine","Marine","CombatShield","GasScv","GasScv","GasScv","SCV","SCV","Barracks","Barracks","ReactorOnFactory","SupplyDepot","SCV","SCV","Medivac","Marine","MarineOnReactor","Marauder","Marauder","SCV","SCV","SupplyDepot","Marine","MarineOnReactor","SCV","SCV","Marauder","Marauder","ScannerSweep","SupplyDepot","LiftFactoryFromReactor","LandStarportOnReactor","CallMule","Medivac","MedivacOnReactor","SupplyDepot","ReactorOnBarracks","TechLabOnBarracks","ReactorOnFactory","SCV","SCV","Marine","MarineOnReactor","Marauder","Marauder","SCV","SCV","SupplyDepot","Marauder","Marine","MarineOnReactor","SupplyDepot","SCV","SCV","Marauder","Marauder","InfantryArmorLevel1","ConcussiveShells"],"CreationDate":1442827929777,"Description":"","Name":"Innovation 14CC into Raven 5Rax Push","Race":"Terran","SC2VersionID":"2.2.0","VisitedDate":1442827958936,"VsRace":"Protoss"}