{"BuildLengthInSeconds":312,"BuildOrderItems":["DefaultItem","SCV","SCV","SupplyDepot","SCV","SCV","Barracks","Refinery","SCV","SCV","GasScv","GasScv","GasScv","SCV","OrbitalCommand","Reaper","CommandCenter","SupplyDepot","SCV","CallMule","Marine","SCV","Factory","Refinery","SCV","ReactorOnBarracks","SCV","GasScv","GasScv","GasScv","SCV","SCV","OrbitalCommand","Starport","CallMule","SCV","LiftRaxFromReactor","LandFactoryOnReactor","Hellion","HellionOnReactor","TechLabOnBarracks","SCV","SCV","Starport","Refinery","CallMule","SCV","SCV","LiftRaxFromTechLab","LandStarportOnTechLab","TechLabOnBarracks","Hellion","HellionOnReactor","Viking","GasScv","GasScv","GasScv","SupplyDepot","SCV","SCV","LiftRaxFromTechLab","LandStarportOnTechLab","SupplyDepot","SCV","SCV","Banshee","Banshee","CallMule","SCV","SCV","SupplyDepot","Hellion","HellionOnReactor","CallMule","HyperflightRotors","SupplyDepot","SCV","SCV","SCV","SCV","Banshee","Banshee","Hellion","HellionOnReactor","SupplyDepot","SCV","SCV","CloakingField","SCV","SCV","ScannerSweep","CommandCenter"],"CreationDate":1514546795358,"Description":"","Name":"INnoVation ReaperCC into 1-1-2 Banshee-Helion","Race":"Terran","SC2VersionID":"4.11.3","VisitedDate":1514546861662,"VsRace":"Zerg"}