{"BuildLengthInSeconds":339,"BuildOrderItems":["DefaultItem","SCV","SCV","SupplyDepot","SCV","Barracks","SCV","Refinery","SCV","SCV","GoOutScv","GasScv","GasScv","GasScv","SCV","OrbitalCommand","Reaper","CommandCenter","SCV","CallMule","SupplyDepot","Marine","SCV","Factory","SCV","ReactorOnBarracks","Refinery","SCV","Bunker","SCV","GasScv","GasScv","GasScv","SCV","OrbitalCommand","CallMule","Factory","SCV","LiftRaxFromReactor","LandFactoryOnReactor","Hellion","HellionOnReactor","ReactorOnBarracks","SCV","SCV","CallMule","Hellion","HellionOnReactor","SCV","SCV","SupplyDepot","Armory","Refinery","SCV","SCV","LiftRaxFromReactor","LandFactoryOnReactor","SupplyDepot","SCV","SCV","GasScv","GasScv","GasScv","CallMule","Cyclone","Hellion","HellionOnReactor","SCV","SCV","SupplyDepot","SupplyDepot","CallMule","SCV","SCV","Hellion","HellionOnReactor","Cyclone","SCV","SCV","VehicleWeaponsLevel1","SupplyDepot","Hellion","HellionOnReactor","SCV","SCV","SupplyDepot","SupplyDepot","CallMule","SCV","SCV","Cyclone","Cyclone","SCV","SCV","CallMule","SupplyDepot","SupplyDepot","SCV","SCV","Cyclone","Hellion","HellionOnReactor","CommandCenter"],"CreationDate":1516278289057,"Description":"The idea is to push protoss with 10 hellbats + 8 cyclones with +1 upgrade (need ti figure out weapon or armor is better) with reinforcements of 2 hellions and 2 cyclones. You may take SCVs from your natural to make it all-in.\n\nIf you done enough damage you may continue play macro mech but if protoss defended this without loosing economy, it will be hard to transition.","Name":"INnoVation ReaperCC into Hellbat-Cyclone 2 Factory Push","Race":"Terran","SC2VersionID":"5.0.3","VisitedDate":1607959250513,"VsRace":"Protoss"}