{"BuildLengthInSeconds":346,"BuildOrderItems":["DefaultItem","SCV","SCV","SupplyDepot","SCV","SCV","Barracks","Refinery","SCV","SCV","GasScv","GasScv","GasScv","SCV","OrbitalCommand","Reaper","CommandCenter","GoOutScv","SupplyDepot","SCV","CallMule","Marine","SCV","Factory","Refinery","SCV","ReactorOnBarracks","SCV","GasScv","GasScv","GasScv","SCV","SCV","Starport","OrbitalCommand","CallMule","WidowMine","Marine","MarineOnReactor","SCV","Barracks","SCV","SCV","CallMule","Marine","MarineOnReactor","TechLabOnFactory","Viking","SCV","SCV","SupplyDepot","Marine","MarineOnReactor","SCV","SCV","LiftFactoryFromTechLab","TechLabOnFactory","SupplyDepot","SCV","SCV","LandRaxOnTechLab","StimPack","Marine","Marine","MarineOnReactor","CallMule","EngineeringBay","SCV","SCV","SiegeTank","SupplyDepot","Marine","Marine","MarineOnReactor","SCV","SCV","ScannerSweep","InfantryWeaponsLevel1","SupplyDepot","SCV","SCV","Marine","Marine","MarineOnReactor","SiegeTank","SCV","SCV","SupplyDepot","Marine","Marine","MarineOnReactor","Medivac","Refinery","SCV","SCV","CallMule","SupplyDepot","Marine","Marine","MarineOnReactor","SCV","SCV","SiegeTank","GasScv","GasScv","GasScv","SupplyDepot","CallMule","SupplyDepot","SCV","SCV","Marine","Marine","MarineOnReactor","Medivac","SCV","SCV","CommandCenter"],"CreationDate":1514548852693,"Description":"","Name":"INnoVation ReaperCC into 2-1-1 Marine-Tank-Medivac push","Race":"Terran","SC2VersionID":"5.0.3","VisitedDate":1514552219420,"VsRace":"Protoss"}