{"BuildLengthInSeconds":360,"BuildOrderItems":["DefaultItem","SCV","SCV","SupplyDepot","SCV","SCV","Barracks","Refinery","SCV","SCV","GasScv","GasScv","GasScv","SCV","OrbitalCommand","Reaper","CommandCenter","SupplyDepot","SCV","CallMule","Marine","SCV","Factory","Refinery","SCV","Bunker","ReactorOnBarracks","SCV","GasScv","GasScv","GasScv","SCV","Starport","OrbitalCommand","SCV","CallMule","LiftRaxFromReactor","LandFactoryOnReactor","SCV","Hellion","HellionOnReactor","TechLabOnBarracks","SCV","SCV","CallMule","SupplyDepot","Hellion","HellionOnReactor","LiftRaxFromTechLab","LandStarportOnTechLab","SCV","SCV","Banshee","CloakingField","SCV","SCV","TechLabOnBarracks","SCV","SCV","CallMule","CommandCenter","StimPack","Marine","SCV","SCV","SupplyDepot","Banshee","SCV","CallMule","LiftFactoryFromReactor","Barracks","Barracks","ReactorOnFactory","Marine","SCV","SCV","SupplyDepot","SCV","SCV","EngineeringBay","EngineeringBay","Refinery","Refinery","Marine","SCV","SCV","LiftStarportFromTechLab","LiftFactoryFromReactor","LandFactoryOnTechLab","LandRaxOnReactor","LandRaxOnReactor","SCV","SCV","GasScv","GasScv","GasScv","GasScv","GasScv","GasScv","OrbitalCommand","InfantryWeaponsLevel1","InfantryArmorLevel1","ScannerSweep","Marine","Liberator","SCV","SCV","Marine","MarineOnReactor","Marine","MarineOnReactor","CallMule","SupplyDepot","SCV","SCV","SiegeTank","CallMule","SCV","Marine","Marine","MarineOnReactor","Marine","MarineOnReactor","SCV","SCV","SupplyDepot","SupplyDepot","SCV","SCV","SCV","ReactorOnStarport","Armory"],"CreationDate":1451244737653,"Description":"This build was executed by Jiakji against Solar on GSL 2016 Pre-Season 2. \n\nThis is well-rounded build which allows stay safe while getting fast 3rd CC. Using hellions and cloackshee terran have some map control which allows to scout and control creep. Banshee would help to stay safe against Ravager aggression. Terran should stay defensive until 3 base economy is set up and 2-2 upgrades hit.\n\n","Name":"Jiakji Reaper CC into Hellion-Cloakshee with 3rd","Race":"Terran","SC2VersionID":"4.11.3","VisitedDate":1470914139213,"VsRace":"Zerg"}