{"BuildLengthInSeconds":310,"BuildOrderItems":["DefaultItem","SCV","SCV","SupplyDepot","SCV","SCV","Barracks","Refinery","SCV","SCV","GasScv","GasScv","GasScv","SCV","OrbitalCommand","Reaper","CommandCenter","SupplyDepot","SCV","CallMule","Marine","SCV","Factory","SCV","ReactorOnBarracks","SCV","SCV","CommandCenter","SCV","OrbitalCommand","Refinery","CallMule","LiftRaxFromReactor","LandFactoryOnReactor","SCV","Starport","Hellion","HellionOnReactor","GasScv","GasScv","GasScv","TechLabOnBarracks","SCV","CallMule","Refinery","SCV","SCV","LiftRaxFromTechLab","TechLabOnBarracks","SCV","SCV","LandStarportOnTechLab","GasScv","GasScv","GasScv","Banshee","SCV","OrbitalCommand","SCV","Marine","StimPack","CallMule","SCV","SCV","EngineeringBay","EngineeringBay","Marine","SCV","SCV","SCV","SupplyDepot","CallMule","CallMule","Liberator","SCV","SCV","SCV","InfantryWeaponsLevel1","InfantryArmorLevel1","Marine","SCV","SCV","SCV","LiftFactoryFromReactor","Barracks","Barracks","ReactorOnFactory","SupplyDepot","SCV","SCV","SCV","Marine","SCV","SCV","SCV","CallMule","Barracks","Barracks","LiftStarportFromTechLab","ReactorOnStarport"],"CreationDate":1451307471847,"Name":"Jiakji Reaper CC Into fast 3rd with 2 Hellions and Banshee","Race":"Terran","SC2VersionID":"5.0.3","VisitedDate":1470914141603,"VsRace":"Zerg"}