{"BuildLengthInSeconds":568,"BuildOrderItems":["DefaultItem","SCV","SCV","SCV","SCV","SupplyDepot","SCV","SCV","Barracks","SCV","Refinery","SCV","SCV","GasScv","GasScv","GasScv","OrbitalCommand","Marine","SupplyDepot","Marine","CallMule","SCV","Factory","TechLabOnBarracks","SCV","SCV","Marauder","SupplyDepot","SCV","WidowMine","SCV","Marauder","SupplyDepot","ConcussiveShells","SCV","CallMule","Marauder","SupplyDepot","SCV","WidowMine","SCV","Marauder","SCV","CommandCenter","WidowMine","SCV","SupplyDepot","Marauder","SCV","CallMule","StimPack","SCV","WidowMine","Marauder","SCV","Barracks","Barracks","Refinery","SCV","WidowMine","Marauder","OrbitalCommand","SCV","GasScv","GasScv","GasScv","EngineeringBay","SCV","Marine","CallMule","Starport","ReactorOnFactory","Refinery","Marine","Marine","SCV","CallMule","SCV","SupplyDepot","Marine","SCV","SCV","GasScv","GasScv","GasScv","Marine","Marine","SupplyDepot","SCV","SCV","Marine","LiftFactoryFromReactor","LandStarportOnReactor","Medivac","MedivacOnReactor","SupplyDepot","ReactorOnBarracks","TechLabOnBarracks","SCV","SCV","Marauder","SupplyDepot","SCV","SCV","CombatShield","Marauder","CallMule","CallMule","Marauder","CommandCenter"],"Description":"","Name":"MarauderMine_to_Bio","Race":"Terran","SC2VersionID":"2.2.0","VsRace":"Protoss","CreationDate":1427732523612,"VisitedDate":1427818987791}
