{"BuildLengthInSeconds":561,"BuildOrderItems":["DefaultItem","SCV","SCV","SCV","SCV","SupplyDepot","SCV","SCV","Barracks","SCV","Refinery","SCV","SCV","GoOutScv","GasScv","GasScv","GasScv","OrbitalCommand","Marine","SupplyDepot","Marine","SCV","CallMule","Factory","TechLabOnBarracks","SCV","SCV","Marauder","SupplyDepot","SCV","WidowMine","Marauder","ConcussiveShells","SCV","SupplyDepot","CallMule","SCV","Marauder","SCV","WidowMine","SupplyDepot","SCV","Marauder","SCV","WidowMine","SCV","Marauder","CommandCenter","Refinery","SCV","SCV","CallMule","LiftRaxFromTechLab","LandFactoryOnTechLab","SupplyDepot","SiegeTank","GasScv","GasScv","GasScv","Marine","Bunker","SCV","Marine","EngineeringBay","SCV","SiegeTank","SCV","Marine","MissileTurret","MissileTurret","SCV","CallMule","OrbitalCommand","Refinery","Marine","SCV","SiegeTank","SupplyDepot","SCV","SCV","CallMule","Factory","ReactorOnBarracks","GasScv","GasScv","GasScv","SCV","SCV","Starport","Refinery","SCV","SCV","SiegeTank","SupplyDepot","SCV","SCV","GasScv","GasScv","GasScv","SupplyDepot","CallMule","SCV","LiftRaxFromReactor","LandFactoryOnReactor"],"CreationDate":1437059266517,"Description":"","Name":"Marauder-Mine push into mech","Race":"Terran","SC2VersionID":"2.2.0","VisitedDate":1437059289418,"VsRace":"Protoss"}