{"BuildLengthInSeconds":359,"BuildOrderItems":["DefaultItem","Probe","Probe","Pylon","Probe","Probe","Probe","Nexus","Gateway","Probe","Probe","Assimilator","Assimilator","Probe","Pylon","GoOutProbe","Probe","GasProbe","GasProbe","GasProbe","GasProbe","GasProbe","GasProbe","CyberneticsCore","Probe","Zealot","Probe","Probe","Probe","Probe","Probe","MothershipCore","Stalker","WarpgateUpgrade","Probe","Probe","Probe","Probe","Probe","Probe","Probe","Nexus","Probe","Pylon","Probe","Sentry","Probe","Pylon","Probe","Probe","RoboticsFacility","Probe","Probe","Sentry","Probe","Probe","Gateway","Gateway","Probe","Probe","Gateway","Probe","Sentry","Probe","Forge","Pylon","Pylon","Probe","Probe","Probe","Observer","Probe","Probe","Probe","Assimilator","Assimilator","SwitchToWarpgate","SwitchToWarpgate","SwitchToWarpgate","Probe","Probe","Probe","GroundWeaponsLevel1","Chronoboost","Probe","Probe","Probe","SwitchToWarpgate","GasProbe","GasProbe","GasProbe","GasProbe","GasProbe","GasProbe","RoboticsBay","Pylon","Observer","Pylon","Gateway","Gateway","Probe","Probe","Probe","TwilightCouncil","WarpPrism","Probe","Probe","Probe","Pylon","Pylon","WarpInStalker","WarpInStalker","WarpInStalker","WarpInSentry","Probe","Probe","Probe","Assimilator","Assimilator","SwitchToWarpgate","SwitchToWarpgate","WarpInZealot","WarpInZealot","WarpInZealot","WarpInZealot","Pylon","Pylon","DarkShrine","WarpInAdept","WarpInAdept","Disruptor"],"CreationDate":1448452365023,"Description":"Fast greedy third base into lots of blink stalker disruptor. This works best vs quick 3 hatch style.\n\nHere on out the build is basically stalkers, maybe more adepts if they have lings, and disruptors with potential for triple stargate if you scout spire and later add a 2nd robo for immortals against ultras, this build is strong and can bring you some good success!","Name":"Mcanning Nexus First to MSC quick 3rd into Macro","Race":"Protoss","SC2VersionID":"3.8.0","VisitedDate":1448467009708,"VsRace":"Zerg"}