{"BuildLengthInSeconds":321,"BuildOrderItems":["DefaultItem","Probe","Probe","Pylon","Probe","Gateway","Probe","Probe","Assimilator","Probe","Probe","Nexus","Probe","GasProbe","GasProbe","GasProbe","Probe","CyberneticsCore","Probe","Gateway","Assimilator","Pylon","Probe","GasProbe","GasProbe","GasProbe","MothershipCore","WarpgateUpgrade","Adept","Adept","Probe","Probe","Probe","Probe","Probe","Pylon","Probe","TwilightCouncil","Probe","Probe","Probe","Probe","Probe","Probe","Gateway","Probe","RoboticsFacility","Probe","Blink","Probe","Probe","Probe","Pylon","Assimilator","Assimilator","Probe","Probe","Probe","Probe","SwitchToWarpgate","SwitchToWarpgate","SwitchToWarpgate","GasProbe","GasProbe","GasProbe","GasProbe","GasProbe","GasProbe","Pylon","WarpInStalker","WarpInStalker","WarpInStalker","Observer","Probe","Probe","Pylon","Probe","Probe","RoboticsBay","Forge","Probe","Probe","Observer","Probe","Probe","Gateway","Gateway","Probe","Probe","Nexus","GroundWeaponsLevel1","Chronoboost","Probe","Probe","Disruptor","Pylon"],"CreationDate":1448459815603,"Description":"This BO shows how to open safely in PvP and transition into the midgame to get the composition you want.","Name":"Mcanning Gate Expand into Blink Stalkers-Disraptor","Race":"Protoss","SC2VersionID":"3.8.0","VisitedDate":1448979471743,"VsRace":"Protoss"}