{"BuildLengthInSeconds":328,"BuildOrderItems":["DefaultItem","Probe","Probe","Pylon","Probe","Probe","Gateway","Probe","Assimilator","Probe","Probe","GasProbe","GasProbe","GasProbe","Probe","Nexus","CyberneticsCore","GoOutProbe","Probe","Probe","Assimilator","Pylon","Probe","GasProbe","GasProbe","GasProbe","MothershipCore","Adept","WarpgateUpgrade","Probe","Probe","Adept","Probe","RoboticsFacility","Probe","Probe","Probe","Probe","Probe","Probe","Pylon","Probe","Probe","Probe","Probe","Gateway","Gateway","WarpPrism","Probe","Probe","Pylon","Probe","Probe","Gateway","Gateway","Gateway","Immortal","SwitchToWarpgate","SwitchToWarpgate","SwitchToWarpgate","Pylon","WarpInAdept","WarpInAdept","WarpInAdept","Gateway","Pylon","Assimilator","Assimilator","SwitchToWarpgate","SwitchToWarpgate","SwitchToWarpgate","Immortal","Pylon","GasProbe","GasProbe","GasProbe","GasProbe","GasProbe","GasProbe","WarpInSentry","WarpInSentry","WarpInSentry","WarpInSentry","WarpInSentry","Pylon","SwitchToWarpgate","WarpInAdept","WarpInAdept","WarpInAdept","WarpInAdept","WarpInAdept","WarpInAdept","WarpInAdept","Observer"],"CreationDate":1452078973637,"Description":"MyuNgSiK vs aLive game 1. Protoss destroyed terran with 2 immortals and constant adepts warp ins.","Name":"MyuNgSiK 2 base Immortal Adept Sentry all in with Prism","Race":"Protoss","SC2VersionID":"3.8.0","VisitedDate":1470914158079,"VsRace":"Terran"}