{"BuildLengthInSeconds":335,"BuildOrderItems":["DefaultItem","Probe","Probe","Pylon","Probe","Probe","Probe","Nexus","Probe","Gateway","Assimilator","Probe","Assimilator","Probe","Gateway","GasProbe","GasProbe","GasProbe","Probe","GasProbe","GasProbe","GasProbe","Probe","CyberneticsCore","Probe","Probe","Probe","Probe","Probe","Pylon","Probe","Probe","Adept","Chronoboost","Adept","Chronoboost","MothershipCore","WarpgateUpgrade","Probe","Pylon","Probe","RoboticsFacility","Adept","Adept","Probe","Probe","Probe","Probe","Pylon","Gateway","Probe","Probe","Probe","Probe","WarpPrism","Probe","TwilightCouncil","Pylon","Pylon","Pylon","Immortal","Chronoboost","Charge","Chronoboost","SwitchToWarpgate","SwitchToWarpgate","SwitchToWarpgate","Gateway","Gateway","Gateway","Gateway","Gateway","WarpInSentry","WarpInSentry","Pylon","Pylon","Immortal","Chronoboost","WarpInZealot","WarpInZealot","WarpInZealot","SwitchToWarpgate","SwitchToWarpgate","SwitchToWarpgate","SwitchToWarpgate","SwitchToWarpgate","Observer","WarpInZealot","WarpInZealot","WarpInZealot","WarpInZealot","WarpInZealot","WarpInZealot","WarpInZealot","WarpInZealot"],"CreationDate":1449572315869,"Description":"","Name":"PartinG 17 Nexus into Chargelot Immortal All In","Race":"Protoss","SC2VersionID":"3.8.0","VisitedDate":1449576191683,"VsRace":"Zerg"}