{"BuildLengthInSeconds":390,"BuildOrderItems":["DefaultItem","Probe","Probe","Pylon","Probe","Probe","Gateway","Assimilator","Probe","Probe","GasProbe","GasProbe","Probe","Nexus","GoOutProbe","Probe","CyberneticsCore","GasProbe","Assimilator","Probe","Probe","Pylon","GasProbe","GasProbe","GasProbe","Probe","WarpgateUpgrade","MothershipCore","Adept","Probe","Probe","RoboticsFacility","Probe","Probe","Probe","Probe","Pylon","TwilightCouncil","Probe","Probe","Pylon","Probe","Probe","Observer","Probe","Probe","Probe","Probe","Blink","Observer","Probe","Probe","Gateway","Gateway","Assimilator","Assimilator","Probe","Probe","Observer","Probe","Probe","Pylon","SwitchToWarpgate","GasProbe","GasProbe","GasProbe","GasProbe","GasProbe","GasProbe","Probe","Probe","WarpInStalker","Pylon","Probe","Probe","Nexus","SwitchToWarpgate","SwitchToWarpgate","Probe","Probe","WarpInStalker","Probe","Probe","RoboticsBay","Probe","Probe","Pylon","Forge","Probe","Probe","Probe","Probe","Pylon","Probe","Probe","Gateway","Gateway","Gateway","Probe","Probe","ExtendedThermalLance","Chronoboost","Colossus","Chronoboost","GroundArmorLevel1","Chronoboost","Pylon","Probe","Probe","Probe","WarpInAdept","WarpInAdept","WarpInAdept","SwitchToWarpgate","SwitchToWarpgate","SwitchToWarpgate","WarpInAdept","WarpInAdept","WarpInAdept","Pylon","Pylon","WarpInSentry","WarpInSentry","WarpInSentry","Pylon","Pylon","WarpPrism"],"CreationDate":1449590454537,"Description":"","Name":"PartinG Gate-Gas Expand into Blink-Colossus","Race":"Protoss","SC2VersionID":"3.8.0","VisitedDate":1449590505586,"VsRace":"Terran"}