{"BuildLengthInSeconds":323,"BuildOrderItems":["DefaultItem","Probe","Probe","Pylon","Probe","Probe","Gateway","GoOutProbe","Probe","Assimilator","Probe","Probe","GasProbe","GasProbe","GasProbe","Probe","CyberneticsCore","Probe","Probe","Nexus","Pylon","Probe","Assimilator","MothershipCore","Adept","WarpgateUpgrade","GasProbe","GasProbe","GasProbe","Probe","Probe","Adept","TwilightCouncil","Probe","Probe","RoboticsFacility","Probe","Probe","Pylon","Probe","Probe","ResonatingGlaves","Probe","Probe","Probe","Probe","Probe","Probe","WarpPrism","Gateway","Gateway","Gateway","Probe","Probe","DarkShrine","Pylon","Assimilator","Assimilator","Probe","Probe","Observer","Probe","Probe","Pylon","GasProbe","GasProbe","GasProbe","GasProbe","GasProbe","GasProbe","SwitchToWarpgate","SwitchToWarpgate","SwitchToWarpgate","SwitchToWarpgate","Probe","Probe","Pylon","WarpInAdept","WarpInAdept","WarpInAdept","WarpInAdept","Pylon","WarpInAdept","WarpInAdept","WarpInAdept","WarpInAdept","WarpInDarkTemplar","WarpInDarkTemplar"],"CreationDate":1449935327078,"Description":"","Name":"Patience 2 base Adept drop into DT","Race":"Protoss","SC2VersionID":"3.8.0","VisitedDate":1449937718954,"VsRace":"Terran"}