{"BuildLengthInSeconds":367,"BuildOrderItems":["DefaultItem","Probe","Probe","Pylon","Probe","Probe","Gateway","Probe","Assimilator","Probe","Probe","GasProbe","GasProbe","GasProbe","Probe","Nexus","CyberneticsCore","Probe","Assimilator","Probe","Pylon","Probe","GasProbe","GasProbe","GasProbe","Adept","Chronoboost","WarpgateUpgrade","Chronoboost","Probe","TwilightCouncil","Probe","Adept","Chronoboost","Probe","Probe","Adept","Probe","Probe","ResonatingGlaves","Chronoboost","Probe","Probe","Gateway","Gateway","Probe","Probe","RoboticsFacility","Probe","Probe","Pylon","Pylon","Probe","Probe","Probe","Probe","SwitchToWarpgate","SwitchToWarpgate","SwitchToWarpgate","Probe","Probe","WarpInAdept","WarpInAdept","WarpInAdept","Observer","Nexus","Probe","Probe","Pylon","Forge","Probe","Probe","Charge","WarpInSentry","WarpInSentry","Observer","Probe","Probe","Pylon","Assimilator","Assimilator","Probe","Probe","GroundWeaponsLevel1","Chronoboost","Chronoboost","Chronoboost","Gateway","Gateway","Probe","Probe","GasProbe","GasProbe","GasProbe","GasProbe","GasProbe","GasProbe","Immortal","Chronoboost","Probe","Probe","Probe","TemplarArchives","Probe","Probe","Probe","Gateway","Gateway","Gateway","Immortal","Chronoboost","Probe","Probe","Probe","Gateway","Gateway","Pylon","Pylon","Pylon","Probe","Probe","Probe","Assimilator","Assimilator"],"CreationDate":1535393186663,"Name":"pig adept harass eco","Race":"Protoss","SC2VersionID":"5.0.3","VisitedDate":1608217794257,"VsRace":"Zerg"}