{"BuildLengthInSeconds":492,"BuildOrderItems":["DefaultItem","SCV","SCV","SCV","SCV","SupplyDepot","SCV","SCV","SCV","SCV","CommandCenter","SCV","SCV","Barracks","Refinery","SCV","SCV","GasScv","GasScv","GasScv","SCV","OrbitalCommand","Marine","OrbitalCommand","Barracks","Marine","SCV","CallMule","Factory","SCV","CallMule","SCV","ReactorOnBarracks","SCV","SupplyDepot","Bunker","SCV","SCV","TechLabOnBarracks","Barracks","SCV","SCV","SCV","LiftRaxFromReactor","LandFactoryOnReactor","Hellion","HellionOnReactor","SupplyDepot","StimPack","Marine","Marine","SCV","SCV","CallMule","SupplyDepot","CallMule","Hellion","HellionOnReactor","Marine","SCV","SCV","ReactorOnBarracks","TechLabOnBarracks","SupplyDepot","SCV","SupplyDepot","SCV","Marine","Hellion","HellionOnReactor","SCV","SCV","Refinery","SupplyDepot","Marine","Marine","SCV","SCV","CombatShield","Marine","MarineOnReactor","Hellion","HellionOnReactor","GasScv","GasScv","GasScv","SupplyDepot","SCV","SCV","CallMule","Marauder","Marauder","CallMule","Marine","MarineOnReactor","SupplyDepot","SCV","SCV","Hellion","HellionOnReactor","SupplyDepot","Marine","MarineOnReactor","Marauder","Marauder","SCV","SCV","Starport","EngineeringBay"],"CreationDate":1429117413043,"Description":"Thid build was used by Polt in the first game vs Hydra in WCS 2015 finals. It utilize strong Stim-Shield bio push with hellions or helbat support.\n\nYou can build Starport and Ebay yo follow up with drop play to be able to secure your 3rd like in this build or you can build Armory to execute strong 2 base bio-helbat timing.","Name":"Polt 14CC to MMH push","Race":"Terran","SC2VersionID":"2.2.0","VisitedDate":1429117413043,"VsRace":"Zerg"}