{"BuildLengthInSeconds":510,"BuildOrderItems":["DefaultItem","SCV","SCV","SCV","SCV","SupplyDepot","SCV","SCV","Barracks","Refinery","SCV","SCV","GasScv","GasScv","GasScv","SCV","OrbitalCommand","Reaper","GoOutScv","SupplyDepot","SCV","CallMule","Reaper","SCV","SCV","CommandCenter","SCV","Reaper","SCV","Factory","SCV","CallMule","CommandCenter","ReactorOnBarracks","SCV","SupplyDepot","SCV","OrbitalCommand","SCV","LiftRaxFromReactor","LandFactoryOnReactor","Hellion","HellionOnReactor","SCV","SCV","CallMule","CallMule","SCV","Refinery","TechLabOnBarracks","Hellion","HellionOnReactor","SCV","SCV","OrbitalCommand","GasScv","GasScv","GasScv","SCV","SCV","Hellion","HellionOnReactor","StimPack","SupplyDepot","Marine","SCV","SCV","SCV","CallMule","SCV","SCV","Marine","EngineeringBay","EngineeringBay","Hellion","HellionOnReactor","SupplyDepot","SCV","SCV","SCV","CallMule","CallMule","Marine","SupplyDepot","SCV","SCV","SCV","InfantryWeaponsLevel1","InfantryArmorLevel1","LiftFactoryFromReactor","ReactorOnFactory","Barracks","Barracks","Barracks","Barracks","Starport","Refinery"],"CreationDate":1429109380756,"Description":"This build was executed by Polt in 5th game of WCF finals series versus Hydra.\n\nThis build is targeting to get quick 3 bases with fasr bio upgrades while staing safe with reapers and hellions. There is not much preasure can be applied until terran hit 2-2 timing but after that point terran can start constant aggression from 3 base infrastructure.","Name":"Polt ReaperFE to 3CC-Double Ebay","Race":"Terran","SC2VersionID":"2.2.0","VisitedDate":1438246359925,"VsRace":"Zerg"}