{"BuildLengthInSeconds":540,"BuildOrderItems":["DefaultItem","SCV","SCV","SCV","SCV","SupplyDepot","SCV","SCV","SCV","SCV","CommandCenter","SCV","GoOutScv","Barracks","SCV","SCV","Barracks","SCV","Marine","OrbitalCommand","OrbitalCommand","Barracks","Marine","Marine","SCV","CallMule","SCV","CallMule","Marine","SCV","Marine","SupplyDepot","SCV","SCV","Refinery","Refinery","Marine","Marine","SCV","Marine","SCV","SupplyDepot","GasScv","GasScv","GasScv","GasScv","GasScv","GasScv","Bunker","SCV","SCV","Marine","Marine","TechLabOnBarracks","SCV","SCV","SupplyDepot","CallMule","Marine","Marine","CallMule","SCV","SCV","Marine","StimPack","EngineeringBay","SCV","SCV","Marine","Marine","Marine","Factory","SupplyDepot","SCV","SCV","Marine","Marine","InfantryWeaponsLevel1","Marine","Refinery","SupplyDepot","SCV","SCV","Marine","Marine","CallMule","Marine","SCV","SCV","GasScv","GasScv","GasScv","ScannerSweep","Starport","ReactorOnFactory","MissileTurret","SupplyDepot","Marine","Marine","Marauder","SCV","SCV","MissileTurret","SupplyDepot","Refinery","SCV","SCV","TechLabOnBarracks","Marine","Marauder","SCV","SCV","SupplyDepot","LiftFactoryFromReactor","LandStarportOnReactor","Medivac","MedivacOnReactor","GasScv","GasScv","GasScv","SCV","SCV","Marauder","Marine","Marauder","CombatShield","CallMule","SCV","SCV","ConcussiveShells","SupplyDepot","CallMule"],"CreationDate":1429698045701,"Description":"","Name":"Polt 14CC to 3Rax","Race":"Terran","SC2VersionID":"2.2.0","VisitedDate":1429698045701,"VsRace":"Protoss"}