{"BuildLengthInSeconds":459,"BuildOrderItems":["DefaultItem","SCV","SCV","SupplyDepot","SCV","SCV","Barracks","Refinery","SCV","SCV","GasScv","GasScv","GasScv","SCV","OrbitalCommand","Reaper","CommandCenter","SCV","CallMule","SupplyDepot","ReactorOnBarracks","SCV","Barracks","SCV","Factory","SCV","Bunker","Marine","MarineOnReactor","SCV","Refinery","OrbitalCommand","SCV","Marine","MarineOnReactor","CallMule","TechLabOnBarracks","GasScv","GasScv","GasScv","SCV","Marine","MarineOnReactor","SCV","SCV","CallMule","LiftRaxFromTechLab","LandFactoryOnTechLab","Cyclone","SupplyDepot","SCV","SCV","Marine","MarineOnReactor","SupplyDepot","SCV","SCV","LiftFactoryFromTechLab","LandRaxOnTechLab","Marauder","Marine","MarineOnReactor","StimPack","WidowMine","SCV","SCV","Refinery","Starport","CallMule","SCV","SCV","SupplyDepot","Marine","MarineOnReactor","Marauder","GasScv","GasScv","GasScv","SCV","SCV","CallMule","EngineeringBay","Marine","MarineOnReactor","SupplyDepot","SCV","SCV","Marauder","Medivac","SCV","SCV","InfantryWeaponsLevel1","SupplyDepot","ReactorOnFactory","Marine","MarineOnReactor","Marauder","SCV","SCV","ScannerSweep","CommandCenter","SCV","SCV","SupplyDepot","Medivac","Marine","MarineOnReactor","Marauder","CallMule","SCV","SCV","Refinery","Barracks","SupplyDepot","SCV","SCV","Marine","MarineOnReactor","Marauder","LiftFactoryFromReactor","TechLabOnFactory","LandStarportOnReactor","GasScv","GasScv","GasScv","SCV","SCV","CombatShield","Medivac","MedivacOnReactor","SCV","SCV","CallMule","SCV","SCV","LiftFactoryFromTechLab","LandRaxOnTechLab","ConcussiveShells","Barracks","Barracks","Barracks","OrbitalCommand","Marauder","Marauder","Marine","MarineOnReactor","Medivac","MedivacOnReactor","ScannerSweep","SupplyDepot","SupplyDepot","SCV","SCV","ReactorOnFactory","InfantryArmorLevel1","SCV","SCV","ScannerSweep","SCV","SCV","SupplyDepot","SupplyDepot","Marauder","Marauder","Marine","MarineOnReactor","Liberator","LiberatorOnReactor","TechLabOnBarracks","TechLabOnBarracks","SCV","SCV","LiftFactoryFromReactor","LandRaxOnReactor","ScannerSweep","SCV","SCV","SupplyDepot","SupplyDepot","Marauder","Marauder","Marine","MarineOnReactor","Marine","MarineOnReactor","Marauder","Marauder","SupplyDepot","SupplyDepot","Armory","EngineeringBay","ScannerSweep"],"CreationDate":1450091834953,"Name":"Polt Reaper CC into Cyclone Fast 3rd","Race":"Terran","SC2VersionID":"3.0.0","VisitedDate":1470912632885,"VsRace":"Protoss"}