{"BuildLengthInSeconds":297,"BuildOrderItems":["DefaultItem","SCV","SCV","SupplyDepot","SCV","SCV","Barracks","Refinery","SCV","SCV","GasScv","GasScv","GasScv","SCV","OrbitalCommand","Reaper","CommandCenter","SCV","CallMule","SupplyDepot","ReactorOnBarracks","GoOutScv","SCV","Barracks","Refinery","SCV","SCV","Factory","GasScv","GasScv","GasScv","Marine","MarineOnReactor","SCV","SCV","OrbitalCommand","CallMule","Marine","MarineOnReactor","TechLabOnBarracks","SCV","Starport","WidowMine","SCV","CallMule","SCV","Marine","Marine","MarineOnReactor","StimPack","SCV","SCV","SupplyDepot","SCV","SCV","ReactorOnFactory","Marauder","Marine","MarineOnReactor","SupplyDepot","SCV","SCV","Medivac","CallMule","Marauder","Marine","MarineOnReactor","EngineeringBay","SCV","SCV","SupplyDepot","Refinery","SCV","SCV","CallMule","Marauder","Marine","MarineOnReactor","LiftFactoryFromReactor","LandStarportOnReactor","SupplyDepot","SCV","SCV","GasScv","GasScv","GasScv","Medivac","MedivacOnReactor","SupplyDepot","SCV","SCV","InfantryWeaponsLevel1","Marauder","Marine","MarineOnReactor"],"CreationDate":1462808978540,"Description":"Standard ReaperCC into early 2nd rax with lab for stim. Push with stim and 3 medivacs if protoss play greedy. Orherwise start containing him while taking 3rd.","Name":"Polt 2rax stim with 3 medivacs","Race":"Terran","SC2VersionID":"5.0.3","VisitedDate":1463683404227,"VsRace":"Protoss"}