{"BuildLengthInSeconds":675,"BuildOrderItems":["DefaultItem","SCV","SCV","SCV","SCV","SupplyDepot","SCV","SCV","SCV","SCV","CommandCenter","SCV","Barracks","SCV","Barracks","SCV","SCV","Marine","OrbitalCommand","OrbitalCommand","Marine","Refinery","Refinery","Marine","SCV","CallMule","SCV","CallMule","Marine","Marine","GasScv","GasScv","GasScv","GasScv","GasScv","GasScv","SupplyDepot","SCV","SCV","SCV","Marine","Marine","Factory","SCV","SCV","SupplyDepot","Marine","Marine","SCV","SCV","Bunker","SCV","SCV","Refinery","SupplyDepot","Marine","Marine","CallMule","CallMule","SCV","SCV","Starport","WidowMine","GasScv","GasScv","GasScv","Marine","Marine","SCV","SCV","EngineeringBay","SCV","SCV","SupplyDepot","TechLabOnBarracks","ReactorOnBarracks","TechLabOnFactory","SCV","SCV","Medivac","SupplyDepot","SCV","SCV","StimPack","SiegeTank","ScannerSweep","InfernalPreIgniter","SCV","SCV","Marine","LiftRaxFromReactor","ReactorOnBarracks","CallMule","SupplyDepot","ReactorOnStarport","SCV","SCV","SupplyDepot","Factory","SCV","SCV","Marine","SupplyDepot","Factory","SCV","SCV","Marine","Marine","MarineOnReactor","SupplyDepot","SiegeTank","SCV","SCV","Marine","Marine","MarineOnReactor","CallMule","LandFactoryOnReactor","Hellion","HellionOnReactor","SupplyDepot","SCV","SCV","SupplyDepot","SCV","SCV","CallMule","SiegeTank","LiftStarportFromReactor","LandFactoryOnReactor","Hellion","HellionOnReactor","LiftRaxFromReactor","TechLabOnBarracks","SupplyDepot","Marauder","Hellion","HellionOnReactor","Armory","Hellion","HellionOnReactor","Marauder","SupplyDepot","ReactorOnStarport","SCV","SCV","Marauder","Hellion","HellionOnReactor","Hellion","HellionOnReactor","Marauder","CallMule","LiftFactoryFromTechLab","LandFactoryOnReactor","Hellion","HellionOnReactor","SupplyDepot","SupplyDepot","SCV","SCV","Marauder","CallMule","Hellion","HellionOnReactor","SupplyDepot","SupplyDepot","Viking","VikingOnReactor","Hellion","HellionOnReactor","Hellion","HellionOnReactor","Hellion","HellionOnReactor","Marauder","Marauder"],"CreationDate":1429705482575,"Description":"","Name":"Polt 14CC to Helbat-Bio-Viking Push","Race":"Terran","SC2VersionID":"2.2.0","VisitedDate":1429705482575,"VsRace":"Protoss"}