{"BuildLengthInSeconds":534,"BuildOrderItems":["DefaultItem","SCV","SCV","SCV","SCV","SupplyDepot","SCV","SCV","SCV","SCV","CommandCenter","SCV","SCV","Barracks","Refinery","SCV","SCV","GasScv","GasScv","GasScv","SCV","OrbitalCommand","Marine","OrbitalCommand","Barracks","Marine","SCV","CallMule","Factory","SCV","CallMule","SCV","ReactorOnBarracks","SCV","SupplyDepot","Bunker","SCV","SCV","TechLabOnBarracks","Barracks","SCV","SCV","SCV","LiftRaxFromReactor","LandFactoryOnReactor","Hellion","HellionOnReactor","SupplyDepot","StimPack","Marine","Marine","SCV","SCV","CallMule","SupplyDepot","CallMule","Hellion","HellionOnReactor","Marine","SCV","SCV","ReactorOnBarracks","TechLabOnBarracks","SupplyDepot","SCV","SupplyDepot","SCV","Marine","Hellion","HellionOnReactor","SCV","SCV","Marauder","Marauder","Refinery","SupplyDepot","SCV","SCV","Marine","MarineOnReactor","Hellion","HellionOnReactor","SupplyDepot","SCV","SCV","CallMule","Marauder","Marauder","GasScv","GasScv","GasScv","SupplyDepot","Marine","MarineOnReactor","CallMule","SCV","SCV","CombatShield","Hellion","HellionOnReactor","SupplyDepot","Marauder","Marauder","Marine","MarineOnReactor","SCV","SCV","SupplyDepot","Hellion","HellionOnReactor","Armory","Marauder","Marauder","Marine","MarineOnReactor","SCV","SCV","SupplyDepot","SCV","SCV","CallMule","Hellion","HellionOnReactor","Starport"],"CreationDate":1429109696696,"Description":"Thid build was used by Polt in the first game vs Hydra in WCS 2015 finals. It utilize strong Stim-Shield bio push with hellions or helbat support.\n\nYou can build Armory like in this build to use helbats or you can build starport and ebay like Polt did to continue with drop play.","Name":"Polt 14CC to MMHelbat push","Race":"Terran","SC2VersionID":"2.2.0","VisitedDate":1439456219915,"VsRace":"Zerg"}