{"BuildLengthInSeconds":272,"BuildOrderItems":["DefaultItem","SCV","SCV","SupplyDepot","SCV","Barracks","Refinery","Barracks","SCV","SCV","GasScv","GasScv","GasScv","OrbitalCommand","Reaper","Refinery","Reaper","SCV","GasScv","GasScv","GasScv","SCV","Reaper","SupplyDepot","SCV","Reaper","SCV","Factory","Reaper","SupplyDepot","Starport","CommandCenter","Cyclone","Bunker","EngineeringBay","Viking","Cyclone","SupplyDepot","ReactorOnBarracks","TechLabOnStarport"],"CreationDate":1500128650543,"Description":"Build by PiG from spawningtool.\nThis build is fantastic for countering fast expand openings, useful in a meta where there\u0027s lots of gas-rax-CC-Factory builds as you can do crucial damage before any cyclone or hellion emerges. It struggles to stay on par with one-base 2-gas builds, though with good control you can often still transition quite well.\n\nIaguz talks about the strength of the different openings at the start of this VoD: https://www.youtube.com/watch?v\u003d3M8gW_RJyvM","Name":"Proxy 2-rax Reaper Heavy Pressure Openning - TvT - Timing Attack","Race":"Terran","SC2VersionID":"3.8.0","VisitedDate":1512670877058,"VsRace":"Terran"}