{"BuildLengthInSeconds":505,"BuildOrderItems":["DefaultItem","Probe","Probe","Probe","Pylon","Probe","Probe","Chronoboost","Probe","Gateway","Probe","Chronoboost","Probe","Probe","Assimilator","Assimilator","Probe","Chronoboost","Probe","GasProbe","GasProbe","GasProbe","GasProbe","GasProbe","GasProbe","GoOutProbe","CyberneticsCore","Pylon","Probe","Probe","Probe","Stargate","Stalker","Chronoboost","WarpgateUpgrade","Probe","Pylon","Probe","Oracle","Chronoboost","Chronoboost","Probe","Probe","Probe","FleetBeacon","Gateway","Gateway","Pylon","Pylon","Tempest","Chronoboost","Chronoboost","SwitchToWarpgate","SwitchToWarpgate","SwitchToWarpgate","Pylon","Tempest","Chronoboost","WarpInZealot","WarpInZealot","WarpInZealot","Pylon","WarpInZealot","WarpInZealot","WarpInZealot","Tempest","Chronoboost","Chronoboost","Pylon"],"CreationDate":1438001196024,"Description":"Executed by First against Bomber in GSL Season 3 Code A game 1.\n\nBuild starts from proxy oracle and then transit into 3 tempest constant harras. Use tempests and oracle to kill as much economy and marines as possible. Spend minerals to warp zealots and push terran natural while harassing main.","Name":"Proxy Oracle into 3 Tempest All-in","Race":"Protoss","SC2VersionID":"2.2.0","VisitedDate":1438001201557,"VsRace":"Terran"}