{"BuildLengthInSeconds":313,"BuildOrderItems":["DefaultItem","Drone","Overlord","Drone","Drone","Drone","Drone","Hatchery","Drone","Drone","Extractor","SpawningPool","Drone","Drone","GasDrone","GasDrone","GasDrone","Drone","Overlord","Queen","Queen","Zergling","MetabolicBoost","Drone","Drone","Drone","Drone","Drone","Drone","Overlord","InjectLarva","InjectLarva","Zergling","Queen","Queen","Drone","Overlord","Zergling","Drone","InjectLarva","InjectLarva","Drone","Drone","Drone","Drone","Drone","Drone","Drone","Drone","Queen","PneumatizedCarapace","Zergling","Zergling","Overlord","InjectLarva","InjectLarva","Drone","Drone","EvolutionChamber","Drone","Hatchery","Drone","Drone","BanelingNest","Extractor","Queen","InjectLarva","InjectLarva","Overlord","MutateVentralSacs","MutateVentralSacs","MutateVentralSacs","Zergling","Zergling","Zergling","Zergling","Zergling","GasDrone","GasDrone","GasDrone","Drone","Drone","Overlord","InjectLarva","InjectLarva","Extractor","Baneling","Drone","Drone","Drone","Drone","Drone","Drone","Drone","Drone","Drone","Lair","GroundCarapaceLevel1","GasDrone","GasDrone","GasDrone","Overlord","Baneling","Baneling","Drone","Drone","InjectLarva","InjectLarva","InjectLarva","Hatchery"],"CreationDate":1514446137369,"Description":"Hatch Gas Pool\n\n@100 Gas Ling Speed and pull 2 drones from Gas\n\n@Pool build 2 Queens and Lings if you need... for scouting n stuff\n\n@2 Queens build 2 more queens and 2 more Drones into the Gas\n\n@4 Queens start 1 more queen and Overlord Speed and an evo chamber\n\n@50 gas Bane Nest\n\n@35 Drones take 1 more gas\n\n@300 minerals build a 3rd\n\n@Overlord Speed --\u003e Drop 4 Queens across the map and build 1 more so you can inject both main and nat\n\n@now Spam Lings and Banes to put pressure on your opponent\n\n@150 Gas carapace for Lings... maybe build 2nd evo for double Upgrades\n\n@100 Gas Lair feel free to drone as you see fit :)\n\n@Lair Spire (or Roaches if you prefer)\n\n","Name":"Railgan 4 Queen Drop Opener","Race":"Zerg","SC2VersionID":"5.0.3","VisitedDate":1514446264044,"VsRace":"Zerg"}