{"BuildLengthInSeconds":391,"BuildOrderItems":["DefaultItem","Drone","Overlord","Drone","Drone","Drone","Drone","Drone","Hatchery","Drone","Drone","Extractor","SpawningPool","Drone","GasDrone","GasDrone","GasDrone","Drone","Overlord","Drone","Queen","Queen","Zergling","Zergling","MetabolicBoost","MineralDrone","MineralDrone","MineralDrone","Drone","Drone","Drone","Drone","Drone","Drone","InjectLarva","InjectLarva","Hatchery","Queen","Overlord","Overlord","Drone","Drone","Drone","Drone","Drone","Drone","InjectLarva","InjectLarva","Drone","Drone","Drone","Drone","Drone","Drone","SporeCrawler","SporeCrawler","GasDrone","GasDrone","GasDrone","Overlord","SpawnCreepTumor","InjectLarva","InjectLarva","Drone","EvolutionChamber","Drone","Drone","Drone","Drone","Drone","Drone","Queen","SporeCrawler","InjectLarva","Zergling","Zergling","Zergling","Zergling","Extractor","Extractor","MeleeAttacksLevel1","InjectLarva","InjectLarva","Zergling","Zergling","Zergling","Zergling","Drone","Drone","Drone","Drone","Drone","Drone","GasDrone","GasDrone","GasDrone","GasDrone","GasDrone","GasDrone","Overlord","InjectLarva","BanelingNest","Drone","Drone","Drone","SpawnCreepTumor","Drone","Drone","Overlord","InjectLarva","InjectLarva","Lair","Queen","Queen","Overlord","InjectLarva","SpawnCreepTumor","Drone","Drone","Drone","Drone","Drone","Drone","Drone","Drone","Drone","Drone","Drone","Drone","Overlord","InjectLarva","InjectLarva","Extractor","Extractor","Drone","Drone","Drone","Drone","Drone","Drone","Drone","Drone","InjectLarva","SpawnCreepTumor","CentrifugalHooks","SpawnCreepTumor","SpawnCreepTumor","Drone","Drone","GasDrone","GasDrone","GasDrone","GasDrone","GasDrone","GasDrone","Overlord","HydraliskDen","InjectLarva","InjectLarva","Zergling","Zergling","Zergling","Zergling","Zergling","Zergling","Zergling","Zergling","Zergling","Overlord","InjectLarva","Overlord","Overlord","Overlord","Hatchery","Extractor","MuscularAugments","InjectLarva","InjectLarva","Baneling","Baneling","Baneling","Baneling","Baneling","Baneling","Baneling","Baneling","Baneling","Baneling","GasDrone","GasDrone","GasDrone","InjectLarva","Hydralisk","Hydralisk","Hydralisk","Hydralisk","Hydralisk","Hydralisk","Overseer","PneumatizedCarapace","SpawnCreepTumor","SpawnCreepTumor","Hydralisk","Hydralisk","Hydralisk","Hydralisk"],"CreationDate":1514493681075,"Description":"It\u0027s a strong current meta build.\n\nThis Strategy performs best vs Stargate Openers. Otherwise I suggest a Zergling Ravager into Ling Bane Ravager Playstyle.\n\nThe Build kickstarts its economy early on with a fast but safe 3 Hatch Opener. It then follows it up with a Spore Queen Defense versus the Stargate play while mining as little Gas as possible to maximize mineral Income.\n\nWe then follow it up with a quick +1 melee into a Lair and Baneling Nest to increase the Strength of our midgame Ling Bane Hydra timing.\n\nOnce the Lair is done. The Build finalizies the saturation of all mineral lines, takes a 4th and a macro hatch and prepares for a big hydralisk push.\n\nOnce the push left our base we reinforce with lings and banelings as they travel fast across the map than Hydralisks.\n\n","Name":"Railgan 3 Hatch Ling Bane Hydra","Race":"Zerg","SC2VersionID":"5.0.3","VisitedDate":1514493929247,"VsRace":"Protoss"}