{"BuildLengthInSeconds":306,"BuildOrderItems":["DefaultItem","Drone","Overlord","Drone","Drone","Drone","Drone","Drone","Hatchery","Drone","Extractor","SpawningPool","Drone","Drone","GasDrone","GasDrone","GasDrone","Drone","Overlord","Queen","Queen","Zergling","Zergling","Zergling","MetabolicBoost","Drone","Drone","Drone","Drone","Drone","InjectLarva","Drone","Queen","InjectLarva","Overlord","Drone","Drone","BanelingNest","Drone","Drone","Drone","InjectLarva","Drone","Drone","Drone","InjectLarva","Drone","Drone","Drone","Overlord","SpawnCreepTumor","Hatchery","Zergling","Overlord","InjectLarva","InjectLarva","Zergling","Baneling","Baneling","Baneling","Drone","Extractor","Extractor","SpawnCreepTumor","Drone","Drone","Drone","Drone","Drone","Drone","Drone","RoachWarren","Lair","GasDrone","GasDrone","GasDrone","GasDrone","GasDrone","GasDrone","InjectLarva","InjectLarva","Drone","Drone","Drone","Drone","Drone","Drone","Drone","Overlord","Drone","Extractor","EvolutionChamber","Overlord","InjectLarva","InjectLarva","InjectLarva","Roach","Roach","Roach","Roach","Roach","Roach","Roach","SpawnCreepTumor","MissleAttacksLevel1","GlialReconstitution"],"CreationDate":1514447025393,"Description":"17 Hatch 17 Gas 17 Pool\n\nDrone to 19 then Overlord\n\nStart 2 Queens + 6 Lings immediatly\n\nUse Lings for Scouting / Defending\n\n@100 Gas Ling Speed -\u003e Mine Gas with 2 Drones only\n\n@Queen in Main done move it to Natural to kill OL\u0027s and build a 3rd Queens in Main\n\n@2:45-3:00 Bane Nest --\u003e 1 more drone in Gas --\u003e Always have Lings at home ready to morph into Banes!!\n\n@3:30 3rd Base (can be build quicker if you feel safe)\n\n@4:00 (or 35 Drones) take 2-3 additional Gasses and start a Lair + Roach Warren and Evo Chamber\n\n@Evo get + 1 Missile\n\n@41 Drones take your last Gas\n\nThen either Spam Roaches or Drone up your 3rd and transition to Roach Ravager / Roach Muta / Ling Muta / Roach Hydra as you feel\n\n","Name":"Railgan 3 Hatch Ling Bane into Roach Opener","Race":"Zerg","SC2VersionID":"5.0.3","VisitedDate":1514447087123,"VsRace":"Zerg"}