{"BuildLengthInSeconds":420,"BuildOrderItems":["DefaultItem","SCV","SCV","SupplyDepot","SCV","SCV","Barracks","Refinery","SCV","SCV","GasScv","GasScv","GasScv","SCV","OrbitalCommand","Reaper","CommandCenter","SCV","CallMule","SupplyDepot","Marine","SCV","Factory","SCV","ReactorOnBarracks","SCV","Bunker","SCV","OrbitalCommand","SCV","CallMule","LiftRaxFromReactor","LandFactoryOnReactor","Hellion","HellionOnReactor","TechLabOnBarracks","Barracks","Barracks","Refinery","SCV","SCV","SCV","CallMule","StimPack","GasScv","GasScv","GasScv","Marauder","Hellion","HellionOnReactor","SCV","SCV","SupplyDepot","SCV","SCV","Marauder","SupplyDepot","ReactorOnBarracks","ReactorOnBarracks","SCV","SCV","Hellion","HellionOnReactor","CallMule","Marauder","SCV","SCV","SupplyDepot","EngineeringBay","SCV","SCV","WidowMine","WidowMineOnReactor","CallMule","SupplyDepot","Marauder","Marine","MarineOnReactor","Marine","MarineOnReactor","SCV","SCV","InfantryWeaponsLevel1","SupplyDepot","SCV","SCV","WidowMine","WidowMineOnReactor","Marauder","SupplyDepot","SCV","SCV","Marine","MarineOnReactor","Marine","MarineOnReactor","CallMule","Starport","Refinery","SCV","SCV","SupplyDepot","WidowMine","WidowMineOnReactor","Marauder","Marine","MarineOnReactor","CallMule","CombatShield","GasScv","GasScv","GasScv","SupplyDepot","SCV","SCV","Marine","MarineOnReactor","Marine","MarineOnReactor","Marauder","ReactorOnStarport","SupplyDepot","SCV","SCV","WidowMine","WidowMineOnReactor","SupplyDepot","Marine","MarineOnReactor","Marine","MarineOnReactor","Marauder","SCV","SCV","SupplyDepot","SupplyDepot","CallMule","SCV","SCV","Medivac","MedivacOnReactor","Marine","MarineOnReactor","Marine","MarineOnReactor","WidowMine","WidowMineOnReactor","Marauder","SCV","SCV","CallMule","SupplyDepot","SupplyDepot","Marine","MarineOnReactor","Marine","MarineOnReactor","SCV","SCV","Marauder","Medivac","MedivacOnReactor","SCV","SCV","LiftFactoryFromReactor","TechLabOnFactory","CommandCenter"],"CreationDate":1516035551621,"Description":"","Name":"RaxGasReaperCC-to-MMMHW push","Race":"Terran","SC2VersionID":"5.0.3","VisitedDate":1516035596669,"VsRace":"Zerg"}