{"BuildLengthInSeconds":349,"BuildOrderItems":["DefaultItem","SCV","SCV","SupplyDepot","SCV","SCV","Barracks","Refinery","GoOutScv","SCV","SCV","GasScv","GasScv","GasScv","SCV","OrbitalCommand","ReactorOnBarracks","CommandCenter","SCV","CallMule","SupplyDepot","SCV","Marine","MarineOnReactor","Factory","SCV","Marine","MarineOnReactor","SCV","Bunker","SCV","Marine","MarineOnReactor","SCV","CallMule","OrbitalCommand","TechLabOnFactory","Marine","MarineOnReactor","SCV","Refinery","Cyclone","SCV","Marine","MarineOnReactor","SCV","CallMule","SupplyDepot","GasScv","GasScv","GasScv","SCV","SCV","Barracks","Marine","MarineOnReactor","SupplyDepot","SCV","SCV","LiftFactoryFromTechLab","LiftRaxFromReactor","LandRaxOnTechLab","LandFactoryOnReactor","StimPack","Marauder","WidowMine","WidowMineOnReactor","SCV","CallMule","SCV","SupplyDepot","SCV","SCV","EngineeringBay","Refinery","Marauder","SCV","SCV","CallMule","SupplyDepot","LiftFactoryFromReactor","LandRaxOnReactor","Marine","MarineOnReactor","Starport","ReactorOnFactory","GasScv","GasScv","GasScv","SCV","SCV","Marauder","InfantryWeaponsLevel1","Marine","MarineOnReactor","SCV","SCV","SupplyDepot","SCV","SCV","Marauder","Marine","MarineOnReactor","ScannerSweep","SupplyDepot","SCV","SCV","LiftFactoryFromReactor","LandStarportOnReactor","Medivac","MedivacOnReactor","Refinery","SCV","SCV","CallMule","SupplyDepot","Marauder","Marine","MarineOnReactor","GasScv","GasScv","GasScv","SCV","SCV","CommandCenter","Medivac","MedivacOnReactor"],"CreationDate":1450353151293,"Name":"Reactor CC into Cyclone safe 3rd version2","Race":"Terran","SC2VersionID":"3.0.0","VisitedDate":1470914128227,"VsRace":"Protoss"}