{"BuildLengthInSeconds":321,"BuildOrderItems":["DefaultItem","SCV","SCV","SupplyDepot","SCV","SCV","Barracks","Refinery","SCV","GoOutScv","SCV","GasScv","GasScv","GasScv","SCV","ReactorOnBarracks","OrbitalCommand","CommandCenter","SCV","CallMule","SupplyDepot","SCV","Marine","MarineOnReactor","Factory","SCV","Marine","MarineOnReactor","SCV","Marine","MarineOnReactor","SCV","SCV","OrbitalCommand","Starport","CallMule","Refinery","LiftRaxFromReactor","LandFactoryOnReactor","Marine","Hellion","HellionOnReactor","SCV","GasScv","GasScv","GasScv","Marine","SCV","SupplyDepot","SCV","CallMule","Hellion","HellionOnReactor","Armory","TechLabOnBarracks","SCV","SCV","Medivac","SupplyDepot","Hellion","HellionOnReactor","SCV","SCV","CallMule","LiftRaxFromTechLab","SupplyDepot","SCV","LandStarportOnTechLab","Hellion","HellionOnReactor","Banshee","CloakingField","CallMule","SCV","SCV","SupplyDepot","Marine","SCV","Hellion","HellionOnReactor","EngineeringBay","EngineeringBay","SCV","SCV","TechLabOnBarracks","SCV","SCV","CallMule","Hellion","HellionOnReactor","CommandCenter","StimPack","InfantryWeaponsLevel1","InfantryArmorLevel1"],"CreationDate":1520939645123,"Name":"ReactorCC into Helbat push","Race":"Terran","SC2VersionID":"5.0.3","VisitedDate":1607959249778,"VsRace":"Zerg"}