{"BuildLengthInSeconds":324,"BuildOrderItems":["DefaultItem","SCV","SCV","SupplyDepot","SCV","SCV","Barracks","Refinery","SCV","SCV","GasScv","GasScv","GasScv","GoOutScv","SCV","ReactorOnBarracks","OrbitalCommand","CommandCenter","SCV","CallMule","SupplyDepot","SCV","Factory","Marine","MarineOnReactor","SCV","SCV","Marine","MarineOnReactor","SCV","Marine","MarineOnReactor","SCV","OrbitalCommand","WidowMine","Starport","CallMule","Refinery","SCV","Marine","MarineOnReactor","SupplyDepot","SCV","CallMule","GasScv","GasScv","GasScv","SCV","WidowMine","Marine","MarineOnReactor","SCV","SCV","Medivac","SCV","Marine","MarineOnReactor","SupplyDepot","SCV","SCV","SCV","Barracks","Barracks","TechLabOnFactory","TechLabOnStarport","CallMule","Marine","MarineOnReactor","SCV","SCV","SupplyDepot","SCV","SCV","LiftFactoryFromTechLab","LiftStarportFromTechLab","CallMule","ReactorOnStarport","Marine","MarineOnReactor","SCV","SCV","Refinery","Refinery","SupplyDepot","Marine","MarineOnReactor","SCV","SCV","LandRaxOnTechLab","StimPack","LandRaxOnTechLab","CombatShield","Marauder","Marauder","GasScv","GasScv","GasScv","GasScv","GasScv","GasScv","EngineeringBay","EngineeringBay","SCV","SCV","SupplyDepot","Marine","MarineOnReactor","ScannerSweep","Medivac","MedivacOnReactor","SupplyDepot","InfantryWeaponsLevel1","InfantryArmorLevel1"],"CreationDate":1449908219818,"Description":"","Name":"Reactor-CC into 2 Mine drop","Race":"Terran","SC2VersionID":"4.11.3","VisitedDate":1449908276143,"VsRace":"Protoss"}