{"BuildLengthInSeconds":250,"BuildOrderItems":["DefaultItem","SCV","SCV","SupplyDepot","SCV","SCV","Barracks","Refinery","SCV","SCV","GasScv","GasScv","GasScv","SCV","OrbitalCommand","Reaper","CommandCenter","CallMule","SCV","Barracks","ReactorOnBarracks","SCV","SupplyDepot","SCV","Refinery","Factory","SCV","Marine","MarineOnReactor","GasScv","GasScv","GasScv","SCV","TechLabOnBarracks","OrbitalCommand","SCV","Marine","MarineOnReactor","CallMule","StimPack","Marine","SCV","Marine","MarineOnReactor","CallMule","Starport","SCV","SCV","ReactorOnFactory","Marine","Marine","MarineOnReactor","SCV","SCV","SupplyDepot","SCV","SCV","Marine","Marine","MarineOnReactor","SupplyDepot","SCV","SCV","LiftFactoryFromReactor","LandStarportOnReactor","CallMule","Medivac","MedivacOnReactor","Marine","Marine","SupplyDepot","MarineOnReactor"],"CreationDate":1521006035550,"Description":"The most optimized LOTV 2 medivac 16 marines stim drop where you have 2 medivacs ready at 4:30 with 16 marines. Stim is ready at 5:00 when you should be dropping opponent\u0027s base.\n\n","Name":"ReaperCC into 2-1-1 fast stim 2 medivacs drop","Race":"Terran","SC2VersionID":"5.0.3","VisitedDate":1607959249021,"VsRace":"Zerg"}