{"BuildLengthInSeconds":330,"BuildOrderItems":["DefaultItem","SCV","SCV","SupplyDepot","SCV","Refinery","SCV","Barracks","GasScv","GasScv","GasScv","SCV","GoOutScv","SCV","SCV","Reaper","OrbitalCommand","CommandCenter","SCV","CallMule","Factory","SCV","ReactorOnBarracks","SupplyDepot","SCV","Refinery","Bunker","SCV","GasScv","GasScv","GasScv","WidowMine","Marine","MarineOnReactor","SCV","OrbitalCommand","SCV","CallMule","Armory","WidowMine","SCV","Marine","MarineOnReactor","SCV","CallMule","SCV","SupplyDepot","TechLabOnFactory","Marine","MarineOnReactor","SCV","SCV","SCV","SCV","Thor","Marine","MarineOnReactor","SupplyDepot","SCV","CallMule","SCV","SupplyDepot","SCV","Factory","SCV","Marine","MarineOnReactor","SCV","SupplyDepot","CallMule","SCV","Thor","SCV","Marine","MarineOnReactor","SupplyDepot","SCV","SCV","Refinery","Refinery","LiftRaxFromReactor","LandFactoryOnReactor","Cyclone","HellionOnReactor","SCV","SCV","Marine","SupplyDepot","SupplyDepot","CallMule","GasScv","GasScv","GasScv","GasScv","GasScv","GasScv","SCV","SCV","Cyclone","SCV","SCV","Cyclone"],"CreationDate":1519815228557,"Name":"ReaperCC into 2Thor-Marines-Cyclone push","Race":"Terran","SC2VersionID":"5.0.3","VisitedDate":1607959248231,"VsRace":"Protoss"}