{"BuildLengthInSeconds":322,"BuildOrderItems":["DefaultItem","SCV","SCV","SupplyDepot","SCV","Refinery","SCV","Barracks","GasScv","GasScv","GasScv","SCV","GoOutScv","SCV","SCV","OrbitalCommand","Reaper","CommandCenter","CallMule","SCV","Factory","SCV","ReactorOnBarracks","SupplyDepot","SCV","Refinery","SCV","GasScv","GasScv","GasScv","SCV","LiftRaxFromReactor","LandFactoryOnReactor","Hellion","HellionOnReactor","OrbitalCommand","SCV","CallMule","Cyclone","SCV","SupplyDepot","SCV","SCV","CallMule","SCV","SCV","Cyclone","SupplyDepot","SCV","SCV","SCV","SCV","TechLabOnBarracks","CallMule","CommandCenter","EngineeringBay","SCV","SCV","LiftFactoryFromReactor","LiftRaxFromTechLab","LandFactoryOnTechLab","SiegeTank","SCV","SCV","SupplyDepot","ScannerSweep","Factory","SCV","SCV","MissileTurret","MissileTurret","SCV","SCV","SiegeTank","Refinery","Refinery","SCV","SCV","Starport","CallMule","SCV","SCV","GasScv","GasScv","GasScv","GasScv","GasScv","GasScv","LandFactoryOnReactor","OrbitalCommand","Hellion","HellionOnReactor","ReactorOnBarracks","SCV","SCV","SupplyDepot","SiegeTank"],"CreationDate":1522753843637,"Name":"ReaperCC into 4Cyclone Mech","Race":"Terran","SC2VersionID":"5.0.3","VisitedDate":1607959246693,"VsRace":"Terran"}