{"BuildLengthInSeconds":353,"BuildOrderItems":["DefaultItem","SCV","SCV","SupplyDepot","SCV","Refinery","SCV","Barracks","GasScv","GasScv","GasScv","SCV","SCV","SCV","OrbitalCommand","Reaper","CommandCenter","SCV","CallMule","Factory","SCV","SupplyDepot","ReactorOnBarracks","Refinery","SCV","SCV","GasScv","GasScv","GasScv","SCV","Starport","Marine","MarineOnReactor","WidowMine","OrbitalCommand","SCV","CallMule","Marine","MarineOnReactor","SCV","Cyclone","SCV","SCV","CallMule","Marine","MarineOnReactor","Medivac","SupplyDepot","SCV","SCV","Marine","MarineOnReactor","SCV","SCV","TechLabOnFactory","SupplyDepot","SCV","SCV","LiftRaxFromReactor","TechLabOnBarracks","Barracks","Barracks","ReactorOnStarport","CallMule","SCV","SCV","SupplyDepot","SiegeTank","Refinery","EngineeringBay","SCV","SCV","CallMule","StimPack","Marine","SCV","SCV","SupplyDepot","GasScv","GasScv","GasScv","SCV","SCV","LiftStarportFromReactor","LandRaxOnReactor","LandRaxOnReactor","Marine","Marine","MarineOnReactor","Marine","MarineOnReactor","ReactorOnStarport","SiegeTank","SupplyDepot","SCV","SCV","InfantryWeaponsLevel1","SupplyDepot","Marine","Marine","MarineOnReactor","Marine","MarineOnReactor","CallMule","SCV","SCV","SupplyDepot","SCV","SCV","CallMule","Medivac","MedivacOnReactor","SupplyDepot","Marine","Marine","MarineOnReactor","Marine","MarineOnReactor","SCV","SCV","SiegeTank","SCV","SCV","CommandCenter"],"CreationDate":1514219744854,"Description":"Safe build which might be used for any matchup.","Name":"ReaperCC-311","Race":"Terran","SC2VersionID":"5.0.3","VisitedDate":1514287767718,"VsRace":"Zerg"}