{"BuildLengthInSeconds":666,"BuildOrderItems":["DefaultItem","SCV","SCV","SCV","SCV","SupplyDepot","SCV","SCV","Barracks","Refinery","SCV","SCV","GasScv","GasScv","GasScv","SCV","GoOutScv","Reaper","OrbitalCommand","SCV","CallMule","CommandCenter","ReactorOnBarracks","SCV","SupplyDepot","SCV","Factory","SCV","Marine","MarineOnReactor","SCV","CallMule","Marine","MarineOnReactor","SCV","OrbitalCommand","WidowMine","SCV","Starport","Marine","MarineOnReactor","SCV","SupplyDepot","SCV","SCV","CallMule","Marine","MarineOnReactor","WidowMine","SCV","SCV","SupplyDepot","Medivac","Marine","MarineOnReactor","CallMule","SCV","SCV","SupplyDepot","EngineeringBay","SCV","SCV","Marine","MarineOnReactor","SCV","SCV","SupplyDepot","LiftRaxFromReactor","LandFactoryOnReactor","WidowMine","WidowMineOnReactor","TechLabOnBarracks","Bunker","Refinery","Refinery","SCV","SCV","CallMule","MissileTurret","SCV","SCV","Marine","StimPack","SupplyDepot","GasScv","GasScv","GasScv","GasScv","GasScv","GasScv","CallMule","WidowMine","WidowMineOnReactor","SCV","SCV","Medivac","Marine","Barracks","Barracks","SCV","SCV","SupplyDepot","InfantryWeaponsLevel1","SCV","SCV","WidowMine","WidowMineOnReactor","SupplyDepot","Marauder","SCV","SCV","TechLabOnStarport","SupplyDepot","CallMule","SupplyDepot","SCV","SCV","LiftFactoryFromReactor","LiftStarportFromTechLab","LandRaxOnTechLab","LandRaxOnReactor","CombatShield","Marauder","Marine","MarineOnReactor","Marauder","CallMule","SCV","SCV","SupplyDepot","ReactorOnStarport","Refinery","WidowMine","SCV","SCV","Barracks","Barracks","Marine","MarineOnReactor","Marauder","Marauder","SupplyDepot","GasScv","GasScv","GasScv","SCV","SCV","WidowMine","Marine","MarineOnReactor","Medivac","MedivacOnReactor","SCV","SCV","CallMule","Marauder","Marauder","SupplyDepot","SupplyDepot","ConcussiveShells","SCV","SCV","Marine","MarineOnReactor","TechLabOnBarracks","ReactorOnBarracks","Marauder","Marauder","Medivac","MedivacOnReactor","ScannerSweep","SCV","SCV","SupplyDepot","SupplyDepot","InfantryArmorLevel1"],"CreationDate":1439552843590,"Description":"Maru use this style alot. \n\nOpen with safe Reaper FE. Scout with your reaper and make sure that you are ready for oracle or DT. Start pressure with drop 4 mines on main and poke natural with 12 marines. Try to save medivac to continue pressure. Build up 5 rax infrastructure and try to scout protoss tech and 3rd timing. You can go for SCV pull vs greedy 3rd or continue drop play while building viking count.","Name":"Reaper FE - 4 mine 12 Marines harras - 5 rax pressure","Race":"Terran","SC2VersionID":"2.2.0","VisitedDate":1439552847185,"VsRace":"Protoss"}