{"BuildLengthInSeconds":406,"BuildOrderItems":["DefaultItem","SCV","SCV","SupplyDepot","SCV","Refinery","SCV","Barracks","GasScv","GasScv","GasScv","SCV","SCV","SCV","OrbitalCommand","Reaper","CommandCenter","Factory","CallMule","SCV","Refinery","SCV","ReactorOnBarracks","SupplyDepot","SCV","GasScv","GasScv","GasScv","SCV","LiftRaxFromReactor","LandFactoryOnReactor","SCV","Cyclone","OrbitalCommand","CycloneOnReactor","CallMule","SCV","SCV","SCV","CallMule","SCV","SCV","Cyclone","CycloneOnReactor","CommandCenter","SupplyDepot","SCV","SCV","Starport","SupplyDepot","SCV","SCV","CallMule","SCV","SCV","Hellion","HellionOnReactor","SupplyDepot","Refinery","Refinery","SCV","SCV","Medivac","CallMule","SCV","SCV","Hellion","HellionOnReactor","TechLabOnBarracks","GasScv","GasScv","GasScv","GasScv","GasScv","GasScv","SCV","SCV","OrbitalCommand","LiftRaxFromTechLab","LiftFactoryFromReactor","LandFactoryOnTechLab","SiegeTank","SCV","SCV","Factory","Factory","SCV","SCV","ScannerSweep","SCV","SCV","SCV","ScannerSweep","Armory","Armory","TechLabOnBarracks","ReactorOnStarport","SupplyDepot","SCV","SCV","SCV","CallMule","SupplyDepot","SiegeTank","SCV","SCV","SCV","LiftRaxFromTechLab","LandFactoryOnReactor","LandFactoryOnTechLab","SiegeTank","Hellion","HellionOnReactor","SCV","SCV","SCV","SupplyDepot","SupplyDepot","SCV","SCV","SCV","VehicleWeaponsLevel1","VehicleAndShipPlatingLevel1","SmartServos","SiegeTank","CallMule","Hellion","HellionOnReactor","CallMule","SCV","SCV","SCV","SupplyDepot","SupplyDepot","SiegeTank","Refinery","Refinery","Hellion","HellionOnReactor","SiegeTank","CallMule","CommandCenter"],"CreationDate":1515338758801,"Description":"","Name":"ReaperCC-4Cyclones-4HellionDrop into Mech","Race":"Terran","SC2VersionID":"5.0.3","VisitedDate":1515480131445,"VsRace":"Terran"}