{"BuildLengthInSeconds":346,"BuildOrderItems":["DefaultItem","SCV","SCV","SupplyDepot","SCV","SCV","Barracks","Refinery","GoOutScv","SCV","SCV","GasScv","GasScv","GasScv","SCV","OrbitalCommand","Reaper","CommandCenter","SCV","CallMule","SupplyDepot","Marine","SCV","Factory","SCV","Marine","Refinery","SCV","Marine","SCV","GasScv","GasScv","GasScv","SCV","Starport","CallMule","OrbitalCommand","TechLabOnBarracks","Hellion","SCV","Barracks","StimPack","SCV","Marine","SCV","CallMule","Hellion","Medivac","SCV","SCV","Marine","SupplyDepot","SCV","SCV","Hellion","EngineeringBay","ReactorOnBarracks","CallMule","SCV","SCV","Marine","SupplyDepot","TechLabOnFactory","ReactorOnStarport","SCV","SCV","InfantryWeaponsLevel1","Refinery","Marine","SupplyDepot","SCV","SCV","ScannerSweep","SiegeTank","Marine","MarineOnReactor","SCV","SCV","GasScv","GasScv","GasScv","Refinery","Marine","SupplyDepot","Marine","MarineOnReactor","SCV","SCV","SiegeTank","Marine","CallMule","SupplyDepot","SCV","SCV","Marine","MarineOnReactor","SCV","SCV","CombatShield","SupplyDepot","Marine","Marine","MarineOnReactor","CallMule","SCV","SCV","SiegeTank","SupplyDepot","Medivac","MedivacOnReactor","Marine","Marine","MarineOnReactor"],"CreationDate":1448986114746,"Description":"","Name":"Reaper CC into 3 tank 2 medivac stim push","Race":"Terran","SC2VersionID":"4.11.3","VisitedDate":1449147562698,"VsRace":"Terran"}