{"BuildLengthInSeconds":481,"BuildOrderItems":["DefaultItem","SCV","SCV","SCV","SCV","SupplyDepot","SCV","SCV","Barracks","Refinery","SCV","SCV","GasScv","GasScv","GasScv","GoOutScv","SCV","OrbitalCommand","Reaper","MineralScv","SCV","CallMule","StartIdle","StopIdleIn3Seconds","MineralScv","MineralScv","ReactorOnBarracks","CommandCenter","SCV","SupplyDepot","SCV","SCV","Marine","MarineOnReactor","Barracks","Barracks","GasScv","GasScv","GasScv","SCV","Marine","MarineOnReactor","CallMule","SCV","SCV","OrbitalCommand","Marine","MarineOnReactor","SupplyDepot","TechLabOnBarracks","SCV","Marine","Marine","MarineOnReactor","SCV","CombatShield","Marauder","CallMule","SCV","SCV","SupplyDepot","Marine","Marine","MarineOnReactor","SCV","CallMule","SCV","Marauder","SCV","SupplyDepot","SCV","Marine","Marine","MarineOnReactor","SCV","SCV","Marauder","Refinery","EngineeringBay","SupplyDepot","Marine","SCV","SCV","Marine","MarineOnReactor","Marauder","ScannerSweep","GasScv","GasScv","GasScv","Bunker","SCV","SCV","Factory","TechLabOnBarracks","Refinery","Marine","MarineOnReactor","CallMule","Marauder","StimPack","SCV","SCV"],"CreationDate":1437574670932,"Description":"If scv scout 2 fast gas from protoss make sure to build EBay and bunker before additional barracks. Reaper should show if you need turrets or bunkers.\n\nIf reaper scout twilight tech check if something being reaserched in it. If nothing researched - this is DT. Prefere to go Stim vs Shield against Robo tech.\n\nMove out with 2 marauders and all marines at 7:10 when it is 30 seconds before shield complete. Bank 1 scan i case late dark templars. Kill as many workers as possible.","Name":"Reaper CC into 3 Rax Shield timing","Race":"Terran","SC2VersionID":"2.2.0","VisitedDate":1444505602830,"VsRace":"Protoss"}