{"BuildLengthInSeconds":434,"BuildOrderItems":["DefaultItem","SCV","SCV","SCV","SCV","SupplyDepot","SCV","SCV","Barracks","Refinery","SCV","SCV","GasScv","GasScv","GasScv","SCV","Reaper","OrbitalCommand","SCV","CallMule","CommandCenter","ReactorOnBarracks","SCV","SupplyDepot","SCV","Factory","SCV","Marine","MarineOnReactor","SCV","CallMule","Marine","MarineOnReactor","SCV","Starport","SCV","OrbitalCommand","LiftRaxFromReactor","LandFactoryOnReactor","Hellion","HellionOnReactor","SCV","SupplyDepot","Marine","SCV","SCV","CallMule","Medivac","Marine","Hellion","HellionOnReactor","SupplyDepot","SCV","SCV","CallMule","SCV","SCV","SupplyDepot","TechLabOnBarracks","WidowMine","WidowMineOnReactor","SCV","SCV","StimPack","Barracks","Barracks","Refinery","Refinery","SCV","SCV","TechLabOnStarport","SupplyDepot","Marine"],"CreationDate":1433493134474,"Description":"This build was execured by Dream in the second game of Semi-Finals against Hero. Reaper used to scout and then he transition into marines drop with hellion attack into natural mineral line.","Name":"Reaper FE into marine drop with hellions attack","Race":"Terran","SC2VersionID":"2.2.0","VisitedDate":1433753393570,"VsRace":"Protoss"}