{"BuildLengthInSeconds":380,"BuildOrderItems":["DefaultItem","SCV","SCV","SupplyDepot","SCV","SCV","Barracks","Refinery","SCV","GoOutScv","SCV","GasScv","GasScv","GasScv","SCV","OrbitalCommand","Reaper","CommandCenter","SCV","CallMule","SupplyDepot","Marine","SCV","Factory","SCV","Bunker","ReactorOnBarracks","SCV","Refinery","SCV","GasScv","GasScv","GasScv","SCV","Hellion","OrbitalCommand","CallMule","Marine","MarineOnReactor","SCV","Starport","TechLabOnFactory","SCV","SCV","CallMule","Marine","MarineOnReactor","SupplyDepot","SCV","SCV","LiftFactoryFromTechLab","Marine","MarineOnReactor","LandStarportOnTechLab","SCV","SCV","Raven","Barracks","SupplyDepot","TechLabOnFactory","SCV","SCV","Marine","MarineOnReactor","CallMule","SCV","SCV","SiegeTank","SupplyDepot","Refinery","Marine","MarineOnReactor","SCV","SCV","EngineeringBay","CallMule","LiftStarportFromTechLab","SupplyDepot","SCV","SCV","LandRaxOnTechLab","Marine","MarineOnReactor","Marine","GasScv","GasScv","GasScv","StimPack","Barracks","SCV","SCV","InfantryWeaponsLevel1","SupplyDepot","Marine","MarineOnReactor","Marine","SCV","SCV","SiegeTank","CallMule","ReactorOnStarport","SCV","SCV","Marine","MarineOnReactor","Marine","SupplyDepot","SupplyDepot","SCV","SCV","CallMule","Marine","MarineOnReactor","Marine","SCV","SCV","LiftFactoryFromTechLab","LandRaxOnTechLab","CombatShield","Marine","ReactorOnFactory","Refinery","SupplyDepot","SupplyDepot","Medivac","MedivacOnReactor","SCV","SCV","Marine","MarineOnReactor","Marauder","Marauder","GasScv","GasScv","GasScv","SCV","SCV","SupplyDepot","SupplyDepot","Marine","MarineOnReactor","Marauder","Marauder","CallMule","Medivac","MedivacOnReactor","WidowMine","WidowMineOnReactor"],"CreationDate":1606509706247,"Description":"https://youtu.be/XEHR0gczbcM\n\n","Name":"Reaper-CC into Raven-2xTanks 3-1-1","Race":"Terran","SC2VersionID":"5.0.3","VisitedDate":1607551056397,"VsRace":"Protoss"}