{"BuildLengthInSeconds":378,"BuildOrderItems":["DefaultItem","SCV","SCV","SupplyDepot","SCV","Refinery","SCV","Barracks","GasScv","GasScv","GasScv","SCV","SCV","SCV","Reaper","OrbitalCommand","CommandCenter","SCV","CallMule","Factory","SupplyDepot","SCV","ReactorOnBarracks","Refinery","SCV","SCV","GasScv","GasScv","GasScv","SCV","Starport","Marine","MarineOnReactor","TechLabOnFactory","OrbitalCommand","SCV","CallMule","Marine","MarineOnReactor","LiftFactoryFromTechLab","SCV","SCV","SCV","CallMule","Marine","MarineOnReactor","LandStarportOnTechLab","CloakingField","Banshee","SupplyDepot","SCV","SCV","Marine","MarineOnReactor","EngineeringBay","Refinery","SCV","SCV","TechLabOnFactory","SupplyDepot","SCV","SCV","GasScv","GasScv","GasScv","LiftRaxFromReactor","LiftFactoryFromTechLab","LandRaxOnTechLab","ScannerSweep","Banshee","StimPack","Marine","SCV","SCV","ReactorOnFactory","SupplyDepot","SCV","SCV","InfantryWeaponsLevel1","Marine","CallMule","SCV","SCV","Barracks","Barracks","SCV","SCV","Marine","LiftFactoryFromReactor","LiftStarportFromTechLab","LandFactoryOnTechLab","SiegeTank","ReactorOnStarport","SupplyDepot","Refinery","SCV","SCV","Marine","SupplyDepot","SCV","SCV","CallMule","GasScv","GasScv","GasScv","SCV","SCV","LandRaxOnReactor","LandRaxOnReactor","SiegeTank","Marine","Marine","MarineOnReactor","Marine","MarineOnReactor","SupplyDepot","Medivac","MedivacOnReactor","CallMule","SCV","SCV","SupplyDepot","Marine","Marine","MarineOnReactor","Marine","MarineOnReactor","SCV","SCV","SupplyDepot","SiegeTank","SupplyDepot","SCV","SCV","Medivac","MedivacOnReactor","Marine","Marine","MarineOnReactor","Marine","MarineOnReactor","SCV","SCV","CombatShield","ScannerSweep","InfantryArmorLevel1"],"CreationDate":1515237538241,"Description":"This is safe ReaperCC build which transit into relatievely fast stim pack and +1 upgrade.\n\nYou may vary if you want to build 2 or 3 banshees. Usually 2 is enough to put some preasure on your enemy and force anti-air investment. If he didn\u0027t build engybay at 4 minute, he would be in real trouble.\n\nBanshees also can be used deffensivly if opponent doing some cyclones pushes or things like that.\n\nUse your early stim timing to drop your opponent or delay his 3rd while you getting your own.","Name":"ReaperCC into Cloakshee","Race":"Terran","SC2VersionID":"5.0.3","VisitedDate":1515237551282,"VsRace":"Terran"}