{"BuildLengthInSeconds":361,"BuildOrderItems":["DefaultItem","SCV","SCV","SupplyDepot","SCV","SCV","Barracks","Refinery","SCV","SCV","GasScv","GasScv","GasScv","SCV","OrbitalCommand","Reaper","CommandCenter","SCV","CallMule","SupplyDepot","ReactorOnBarracks","SCV","Bunker","SCV","Factory","SCV","Marine","MarineOnReactor","SCV","SCV","OrbitalCommand","Marine","MarineOnReactor","CallMule","Barracks","Barracks","Refinery","SCV","Marine","MarineOnReactor","TechLabOnFactory","SCV","SCV","CallMule","GasScv","GasScv","GasScv","SCV","SCV","LiftRaxFromReactor","LiftFactoryFromTechLab","LandRaxOnTechLab","ReactorOnFactory","StimPack","Marauder","SupplyDepot","SCV","SCV","LandRaxOnReactor","Marine","Marine","MarineOnReactor","SCV","SCV","Marauder","SupplyDepot","CallMule","Starport","SCV","SCV","LiftFactoryFromReactor","LandRaxOnReactor","Marine","MarineOnReactor","Marine","MarineOnReactor","ReactorOnFactory","SupplyDepot","SCV","SCV","Marauder","CallMule","Refinery","Marine","MarineOnReactor","Marine","MarineOnReactor","SupplyDepot","SCV","SCV","SupplyDepot","GasScv","GasScv","GasScv","LiftFactoryFromReactor","LandStarportOnReactor","Medivac","MedivacOnReactor","Marauder","Marine","MarineOnReactor","Marine","MarineOnReactor","SCV","SCV","SupplyDepot","CallMule","SCV","SCV","Marine","Marine","MarineOnReactor","Marine","MarineOnReactor","SCV","SCV","CommandCenter","EngineeringBay","EngineeringBay","ScannerSweep","SupplyDepot","SCV","SCV","CombatShield","SCV","SCV","InfantryWeaponsLevel1","InfantryArmorLevel1","Marauder","Marine","MarineOnReactor","Marine","MarineOnReactor","SCV","SCV","Medivac","MedivacOnReactor"],"CreationDate":1449478066668,"Description":"Standard Reaper CC opener with transition into 2 base timing attack with Stimed bio + 2 medivacs. \n\nUse reaper to scout any early aggression from zerg and react with bunkers. Try to hide reaper before zergling speed and suicide it later to scout 2 base muta or nydus.\n\nBuild 3rd CC and 2 ebays while pushing. Use medivacs to drop zerg if he has to much army. Push forward if he has lack of army.","Name":"Reaper CC into 3 Rax 2 medivacs Stim push","Race":"Terran","SC2VersionID":"4.11.3","VisitedDate":1449478254547,"VsRace":"Zerg"}