{"BuildLengthInSeconds":435,"BuildOrderItems":["DefaultItem","SCV","SCV","SupplyDepot","SCV","Refinery","SCV","Barracks","GasScv","GasScv","GasScv","SCV","SCV","GoOutScv","SCV","Reaper","OrbitalCommand","CommandCenter","SCV","CallMule","Factory","SCV","ReactorOnBarracks","Refinery","SupplyDepot","SCV","GasScv","GasScv","GasScv","SCV","LiftRaxFromReactor","LandFactoryOnReactor","Hellion","HellionOnReactor","SCV","OrbitalCommand","CallMule","SCV","Cyclone","SCV","SupplyDepot","SCV","CallMule","TechLabOnBarracks","SCV","SCV","Cyclone","SupplyDepot","SCV","SCV","LiftRaxFromTechLab","EngineeringBay","SCV","SCV","ScannerSweep","SCV","SCV","LiftFactoryFromReactor","LandFactoryOnTechLab","MissileTurret","MissileTurret","SCV","SCV","CommandCenter","SiegeTank","ScannerSweep","SCV","SCV","SupplyDepot","Factory","SCV","SCV","Refinery","Refinery","SCV","SCV","Starport","ReactorOnBarracks","SCV","SCV","ScannerSweep","GasScv","GasScv","GasScv","GasScv","GasScv","GasScv","SupplyDepot","SiegeTank","SCV","SCV","LandFactoryOnReactor","SCV","SCV","ScannerSweep","OrbitalCommand","LiftRaxFromReactor","LandStarportOnReactor","Liberator","LiberatorOnReactor","SCV","SCV","SiegeTank","Hellion","HellionOnReactor","SupplyDepot","SCV","SCV","SCV","CallMule","SupplyDepot","SCV","SCV","SCV","CallMule","Hellion","HellionOnReactor","Armory","Armory","SiegeTank","SupplyDepot","SCV","SCV","SCV","SupplyDepot","Viking","VikingOnReactor","CallMule","InfernalPreIgniter","SCV","SCV","SCV","SupplyDepot","Hellion","HellionOnReactor","SiegeTank","SupplyDepot","Refinery","Refinery","SCV","SCV","SCV","ScannerSweep","VehicleWeaponsLevel1","VehicleAndShipPlatingLevel1","Hellion","HellionOnReactor","SCV","SCV","SCV","SupplyDepot","GasScv","GasScv","GasScv","GasScv","GasScv","GasScv","CallMule","CommandCenter"],"CreationDate":1522904570697,"Name":"ReaperCC into 4Cyclone","Race":"Terran","SC2VersionID":"5.0.3","VisitedDate":1607959247462,"VsRace":"Terran"}