{"BuildLengthInSeconds":317,"BuildOrderItems":["DefaultItem","SCV","SCV","SupplyDepot","SCV","Refinery","SCV","Barracks","GasScv","GasScv","GasScv","SCV","GoOutScv","SCV","SCV","OrbitalCommand","Reaper","CommandCenter","SCV","CallMule","Factory","SCV","ReactorOnBarracks","SupplyDepot","SCV","Refinery","SCV","GasScv","GasScv","GasScv","Hellion","Marine","MarineOnReactor","SCV","Starport","OrbitalCommand","SCV","CallMule","Marine","MarineOnReactor","TechLabOnFactory","SCV","SCV","SCV","CallMule","Marine","MarineOnReactor","LiftFactoryFromTechLab","LandStarportOnTechLab","Raven","SupplyDepot","SCV","SCV","WidowMine","Marine","MarineOnReactor","SCV","SCV","Barracks","SupplyDepot","WidowMine","SCV","Marine","MarineOnReactor","SCV","CallMule","SCV","LiftStarportFromTechLab","TechLabOnStarport","SupplyDepot","SCV","LandFactoryOnTechLab","SiegeTank","Marine","MarineOnReactor","SCV","Refinery","SCV","CallMule","SupplyDepot","SCV","Marine","MarineOnReactor","LiftStarportFromTechLab","LandRaxOnTechLab","StimPack","Marine","ReactorOnStarport","SCV","SCV","GasScv","GasScv","GasScv","SupplyDepot","SCV","SiegeTank","Marine","MarineOnReactor","Marine","SCV","SupplyDepot","SCV","SCV","CallMule","Marine","MarineOnReactor","Marine","Medivac","MedivacOnReactor"],"CreationDate":1520134969130,"Name":"ReaperCC into Raven","Race":"Terran","SC2VersionID":"5.0.3","VisitedDate":1607959245880,"VsRace":"Terran"}