{"BuildLengthInSeconds":480,"BuildOrderItems":["DefaultItem","SCV","SCV","SupplyDepot","SCV","SCV","Barracks","Refinery","SCV","SCV","GoOutScv","GasScv","GasScv","GasScv","SCV","Reaper","OrbitalCommand","CommandCenter","SCV","CallMule","Barracks","ReactorOnBarracks","SCV","SupplyDepot","SCV","Refinery","SCV","Factory","Marine","MarineOnReactor","GasScv","GasScv","GasScv","SCV","TechLabOnBarracks","OrbitalCommand","SCV","CallMule","Marine","MarineOnReactor","Marine","SCV","SCV","SCV","CallMule","Starport","ReactorOnFactory","Marine","MarineOnReactor","Marine","SCV","SCV","StimPack","SupplyDepot","Marine","MarineOnReactor","Marine","SCV","SCV","SupplyDepot","SCV","SCV","CallMule","Medivac","Hellion","HellionOnReactor","Marine","MarineOnReactor","SCV","SCV","Marine","SupplyDepot","SupplyDepot","CallMule","Marine","MarineOnReactor","Marine","Medivac","SupplyDepot","SCV","SCV","Hellion","HellionOnReactor","Armory","Marine","MarineOnReactor","Marine","SCV","SCV","Hellion","HellionOnReactor","SCV","SCV","CallMule","Marine","MarineOnReactor","Marine","SupplyDepot","TechLabOnStarport","SupplyDepot","SCV","SCV","Marine","MarineOnReactor","Marine","CallMule","LiftStarportFromTechLab","LandFactoryOnTechLab","SCV","SCV","CommandCenter","EngineeringBay","EngineeringBay","ReactorOnStarport","SCV","SCV","CombatShield","DrillingClaws","Marine","MarineOnReactor","Marine","WidowMine","SCV","SCV","SupplyDepot","SupplyDepot","SCV","SCV","CallMule","Marine","MarineOnReactor","InfantryWeaponsLevel1","InfantryArmorLevel1","LiftStarportFromReactor","ReactorOnStarport","WidowMine","SCV","SCV","Marine","Marine","MarineOnReactor","Factory","SCV","SCV","ScannerSweep","Marine","MarineOnReactor","Marine","Barracks","Barracks","Barracks","OrbitalCommand","WidowMine","SCV","SCV","LiftStarportFromReactor","ReactorOnStarport","SupplyDepot","Refinery","Refinery","SCV","SCV","Marine","MarineOnReactor","Marauder","SupplyDepot","SupplyDepot","SCV","SCV","SCV","CallMule","CallMule","LiftFactoryFromTechLab","LandFactoryOnReactor","WidowMine","WidowMineOnReactor","LandFactoryOnReactor","WidowMine","WidowMineOnReactor","GasScv","GasScv","GasScv","GasScv","GasScv","GasScv","ConcussiveShells","Marine","MarineOnReactor","Marauder","SCV","SCV","SCV","SupplyDepot","SupplyDepot","LandRaxOnTechLab","ReactorOnBarracks","ReactorOnBarracks","WidowMine","WidowMineOnReactor","WidowMine","WidowMineOnReactor","CallMule","Marine","MarineOnReactor","SupplyDepot","SupplyDepot","Medivac","MedivacOnReactor","SCV","SCV","SCV","Marauder","Marauder","Marine","MarineOnReactor","WidowMine","WidowMineOnReactor","WidowMine","WidowMineOnReactor"],"CreationDate":1521007736680,"Name":"ReaperCC to Helbat push into Claws","Race":"Terran","SC2VersionID":"5.0.3","VisitedDate":1607959245023,"VsRace":"Zerg"}