{"BuildLengthInSeconds":407,"BuildOrderItems":["DefaultItem","SCV","SCV","SupplyDepot","SCV","Refinery","SCV","Barracks","GasScv","GasScv","GasScv","SCV","SCV","SCV","OrbitalCommand","Reaper","CommandCenter","Factory","CallMule","SCV","Refinery","SCV","ReactorOnBarracks","SupplyDepot","SCV","GasScv","GasScv","GasScv","SCV","LiftRaxFromReactor","LandFactoryOnReactor","SCV","Cyclone","OrbitalCommand","CycloneOnReactor","CallMule","SCV","SCV","SCV","CallMule","SCV","SCV","Cyclone","CycloneOnReactor","CommandCenter","SupplyDepot","SCV","SCV","Starport","SupplyDepot","SCV","SCV","CallMule","SCV","SCV","Hellion","HellionOnReactor","SupplyDepot","Refinery","Refinery","SCV","SCV","CallMule","Liberator","Hellion","HellionOnReactor","TechLabOnBarracks","SCV","SCV","GasScv","GasScv","GasScv","GasScv","GasScv","GasScv","OrbitalCommand","SCV","SCV","LiftRaxFromTechLab","LiftFactoryFromReactor","LandFactoryOnTechLab","SiegeTank","SCV","SCV","Armory","Armory","ScannerSweep","SCV","SCV","SCV","CallMule","Viking","SCV","SCV","SCV","Factory","Factory","TechLabOnBarracks","CallMule","SupplyDepot","SiegeTank","SCV","SCV","SCV","EngineeringBay","SCV","SCV","SCV","VehicleWeaponsLevel1","VehicleAndShipPlatingLevel1","SupplyDepot","SupplyDepot","SCV","SCV","SCV","SiegeTank","ReactorOnStarport","Refinery","Refinery","LiftRaxFromTechLab","LandFactoryOnTechLab","LandFactoryOnReactor","ScannerSweep","SCV","SCV","SCV","SupplyDepot","SiegeTank","ScannerSweep","Hellion","HellionOnReactor","SCV","SCV","SCV","GasScv","GasScv","GasScv","GasScv","GasScv","GasScv","SupplyDepot","InfernalPreIgniter","SupplyDepot","SCV","SCV","SCV","ScannerSweep","SiegeTank","Hellion","HellionOnReactor","SiegeTank"],"CreationDate":1515484148834,"Description":"Standard gas first Reaper CC with reactored Cyclones transition. 4 cyclones with 4 hellions followup should be able to hold esrly game agression while you building your 3 base economy.\n\nIf zerg play greedy by going to fast 3rd, you should be able to deny his 3rd with reaper and 2-4 cyclones. \n\nIf zerg plays standard you may use liberator harrass with hellions run by to keep his worker count under control.\n\nWith siege tanks you should be able to secure your 3rd base and start working on your upgrades and production.\n\nGeneral goal is to push with 2-2 upgrades and almost 200 supply mech army before zerg could switch to T3.\n\nKeep scanning after 6 minute to not be surprised with muta switch. Start adding some thors when you have 6-8 tanks. You may also add Liberators if have enough gas for that.\n","Name":"ReaperCC-4Cyclones-4Hellion-Liberator-into-Mech","Race":"Terran","SC2VersionID":"5.0.3","VisitedDate":1515484151219,"VsRace":"Zerg"}