{"BuildLengthInSeconds":254,"BuildOrderItems":["DefaultItem","SCV","SCV","SupplyDepot","SCV","Refinery","SCV","Barracks","GasScv","GasScv","GasScv","SCV","SCV","SCV","Reaper","OrbitalCommand","CommandCenter","Factory","SCV","CallMule","Refinery","Reaper","SCV","SupplyDepot","GasScv","GasScv","GasScv","SCV","Cyclone","Barracks","ReactorOnBarracks","SCV","OrbitalCommand","CallMule","SCV","EngineeringBay","SCV","Cyclone","SCV","CallMule","TechLabOnBarracks","SCV","InfantryWeaponsLevel1","SCV","Marine","MarineOnReactor","SCV","SCV","Marine","SupplyDepot","StimPack","Marine","MarineOnReactor","SCV","SCV","Marine","CallMule","Starport","SCV","SCV","SupplyDepot","Marine","MarineOnReactor","ReactorOnFactory"],"CreationDate":1514303959177,"Description":"","Name":"ReaperCC - 2Reaper-2Cyclone safe","Race":"Terran","SC2VersionID":"4.11.3","VisitedDate":1514304031325,"VsRace":"Terran"}