{"BuildLengthInSeconds":333,"BuildOrderItems":["DefaultItem","SCV","SCV","SupplyDepot","SCV","Refinery","SCV","Barracks","GasScv","GasScv","GasScv","SCV","SCV","SCV","OrbitalCommand","Reaper","CommandCenter","Factory","CallMule","SCV","SupplyDepot","SCV","ReactorOnBarracks","SCV","Refinery","Barracks","SCV","Hellion","GasScv","GasScv","GasScv","SCV","Marine","MarineOnReactor","SCV","OrbitalCommand","TechLabOnFactory","CallMule","Marine","MarineOnReactor","SCV","LiftFactoryFromTechLab","LandRaxOnTechLab","StimPack","SCV","Marine","Marine","MarineOnReactor","SCV","CallMule","Starport","TechLabOnFactory","SCV","SCV","SupplyDepot","Marine","Marine","MarineOnReactor","SCV","SCV","SupplyDepot","SCV","SCV","Marine","Marine","MarineOnReactor","SiegeTank","ScannerSweep","Medivac","SCV","SCV","SupplyDepot","Marine","Marine","MarineOnReactor","SCV","SCV","CallMule","SupplyDepot","EngineeringBay","Refinery","SCV","SCV","Marine","Marine","MarineOnReactor","SiegeTank","SupplyDepot","Medivac","SCV","SCV","GasScv","GasScv","GasScv","InfantryWeaponsLevel1","Marine","Marine","MarineOnReactor","CallMule","SCV","SCV","SupplyDepot","CombatShield","Marine","Marine","MarineOnReactor","SiegeTank","ReactorOnStarport","CommandCenter"],"CreationDate":1514528874023,"Description":"","Name":"ReaperCC into 2-1-1","Race":"Terran","SC2VersionID":"5.0.3","VisitedDate":1514559727640,"VsRace":"Terran"}