{"BuildLengthInSeconds":393,"BuildOrderItems":["DefaultItem","SCV","SCV","SupplyDepot","SCV","SCV","Barracks","Refinery","SCV","SCV","GasScv","GasScv","GasScv","SCV","OrbitalCommand","Reaper","CommandCenter","SupplyDepot","SCV","CallMule","Marine","SCV","Factory","Refinery","SCV","ReactorOnBarracks","SCV","GasScv","GasScv","GasScv","SCV","Starport","OrbitalCommand","SCV","CallMule","LiftRaxFromReactor","LandFactoryOnReactor","Hellion","HellionOnReactor","SCV","EngineeringBay","SCV","SCV","CallMule","SupplyDepot","Hellion","HellionOnReactor","Medivac","SCV","SCV","SCV","SCV","LiftFactoryFromReactor","LandRaxOnReactor","TechLabOnFactory","Marine","MarineOnReactor","SupplyDepot","SCV","SCV","Viking","SCV","SCV","ScannerSweep","Marine","MarineOnReactor","SiegeTank","InfantryWeaponsLevel1","SupplyDepot","SCV","SCV","CallMule","Refinery","Marine","MarineOnReactor","SCV","SCV","CommandCenter","SupplyDepot","GasScv","GasScv","GasScv","LiftRaxFromReactor","SCV","SCV","TechLabOnBarracks","SiegeTank","SCV","SCV","StimPack","Barracks","CallMule","Barracks","ReactorOnStarport","Marine","SCV","SCV","SupplyDepot","SCV","SCV","SiegeTank","CallMule","Armory","SCV","SCV","EngineeringBay","Marine","Refinery","SCV","SCV","OrbitalCommand","Barracks","Barracks","LiftStarportFromReactor","LandRaxOnReactor","LandRaxOnReactor","ReactorOnStarport","SiegeTank","GasScv","GasScv","GasScv","SCV","SCV","Marine","Marine","MarineOnReactor","Marine","MarineOnReactor","InfantryArmorLevel1","CallMule","InfantryWeaponsLevel2","SupplyDepot","SCV","SCV","SCV","CallMule","Marine","Marine","MarineOnReactor","Marine","MarineOnReactor","SupplyDepot","SupplyDepot","CallMule","SiegeTank","Viking","VikingOnReactor"],"CreationDate":1448278933087,"Description":"Macro oriented TvT build that can defend against aggressive one base openings or take a fast third Command Centre. It can transition into MMM without Tanks when facing Mech, or into Marine Tank Medivac when facing Bio Tank.\n\nhttp://www.twitch.tv/basetradetv/v/23311385?t\u003d03h04m02s\n\nhttp://www.twitch.tv/basetradetv/v/23311385?t\u003d02h21m27s","Name":"Reaper FE into 1-1-1 with Fast 3rd","Race":"Terran","SC2VersionID":"5.0.3","VisitedDate":1448381622072,"VsRace":"Terran"}