{"BuildLengthInSeconds":282,"BuildOrderItems":["DefaultItem","Probe","Probe","Pylon","Probe","Probe","Gateway","GoOutProbe","Probe","Probe","Nexus","CyberneticsCore","Assimilator","Assimilator","Probe","Probe","GasProbe","GasProbe","GasProbe","GasProbe","GasProbe","GasProbe","Probe","Pylon","Zealot","WarpgateUpgrade","Chronoboost","Probe","Probe","MothershipCore","Adept","Chronoboost","Probe","Probe","Probe","Pylon","Adept","Probe","Probe","Probe","Probe","Probe","Probe","Gateway","Gateway","Gateway","Probe","Probe","Adept","Stargate","Probe","Probe","Pylon","Probe","Probe","Pylon","Probe","Probe","SwitchToWarpgate","SwitchToWarpgate","SwitchToWarpgate","SwitchToWarpgate","WarpInAdept","WarpInAdept","WarpInAdept","WarpInAdept","Probe","Probe","Oracle","Chronoboost","Pylon","Nexus"],"CreationDate":1449920453100,"Description":"","Name":"Safe Gateway Expand Adept pressure into Oracle","Race":"Protoss","SC2VersionID":"3.8.0","VisitedDate":1449920469823,"VsRace":"Zerg"}