{"BuildLengthInSeconds":347,"BuildOrderItems":["DefaultItem","Drone","Overlord","Drone","Drone","Drone","Drone","Drone","Hatchery","Drone","Drone","Hatchery","Drone","SpawningPool","Extractor","Drone","Drone","Drone","GasDrone","GasDrone","GasDrone","Drone","Drone","Overlord","Drone","Queen","Queen","Zergling","Queen","Drone","MetabolicBoost","Drone","Drone","Drone","Drone","Drone","Drone","InjectLarva","InjectLarva","Overlord","Drone","Drone","InjectLarva","Drone","Drone","Drone","Queen","Overlord","Drone","Drone","Drone","InjectLarva","InjectLarva","Drone","Drone","Drone","SpawnCreepTumor","RoachWarren","Zergling","Zergling","Zergling","Zergling","Drone","Overlord","InjectLarva","InjectLarva","Extractor","Extractor","Drone","Drone","Drone","Drone","Overlord","Overlord","SpawnCreepTumor","Drone","Drone","Overlord","InjectLarva","Zergling","Zergling","Zergling","Zergling","Zergling","GasDrone","GasDrone","GasDrone","GasDrone","GasDrone","GasDrone","InjectLarva","InjectLarva","Roach","Roach","Roach","Roach","Roach","Roach","Roach","Roach","SpawnCreepTumor","Overlord","InjectLarva","Roach","Roach","Roach","Roach","Roach","Overlord","Overlord","Drone","Drone","InjectLarva","InjectLarva","Drone","Drone","Drone","Drone","Drone","Drone","InjectLarva","Zergling","Zergling","Zergling","Zergling","Zergling","SpawnCreepTumor","Overlord","Overlord","EvolutionChamber","EvolutionChamber","Ravager","Ravager","Ravager","SpawnCreepTumor","SpawnCreepTumor","SpawnCreepTumor","Drone","Drone","Drone","Drone","Drone","Drone","Drone","Drone","Drone","Drone","InjectLarva","Lair","MeleeAttacksLevel1","GroundCarapaceLevel1"],"CreationDate":1447925982501,"Description":"This build is good on larger maps since zerg will be able to detect incoming aggression and react accordingly. Drone as hard as possible while trying to find out what terran is going to do. Use roach-ling force to defend any helbat timings. Morph ravagers and set spore crawlers against liberators or banshees.","Name":"Solar 3 Hatch into RoachLing","Race":"Zerg","SC2VersionID":"5.0.3","VisitedDate":1447925991479,"VsRace":"Terran"}