{"BuildLengthInSeconds":378,"BuildOrderItems":["DefaultItem","Probe","Probe","Pylon","Probe","Probe","Gateway","Probe","Assimilator","Probe","Probe","GasProbe","GasProbe","GasProbe","Probe","Nexus","CyberneticsCore","Probe","Assimilator","Probe","Pylon","Probe","GasProbe","GasProbe","GasProbe","Adept","Chronoboost","Probe","Stargate","Probe","Adept","Chronoboost","WarpgateUpgrade","Probe","Probe","Oracle","Chronoboost","Probe","Probe","Probe","Probe","TwilightCouncil","Probe","Probe","Gateway","Gateway","Pylon","Phoenix","Probe","Probe","Probe","Probe","ResonatingGlaves","Chronoboost","Chronoboost","Chronoboost","Chronoboost","Pylon","Probe","Probe","Adept","Adept","Adept","Probe","Probe","Pylon","Probe","Probe","Assimilator","Assimilator","SwitchToWarpgate","SwitchToWarpgate","SwitchToWarpgate","Probe","Probe","WarpInAdept","WarpInAdept","WarpInAdept","Pylon","RoboticsFacility","GasProbe","GasProbe","GasProbe","GasProbe","GasProbe","GasProbe","Probe","Probe","WarpInAdept","WarpInAdept","WarpInAdept","Gateway","Gateway","Gateway","Gateway","Gateway","Immortal","Chronoboost","Pylon","Pylon","Pylon","SwitchToWarpgate","SwitchToWarpgate","SwitchToWarpgate","SwitchToWarpgate","SwitchToWarpgate","Immortal","Chronoboost","WarpInSentry","WarpInSentry","WarpInSentry","WarpInSentry","WarpInSentry","WarpInSentry","WarpInAdept","WarpInAdept","Pylon","Pylon","Charge","Chronoboost","Chronoboost","Chronoboost","Pylon"],"CreationDate":1520435457497,"Name":"sos Gladept push ointo 3rd base","Race":"Protoss","SC2VersionID":"5.0.3","VisitedDate":1608217793423,"VsRace":"Zerg"}