{"BuildLengthInSeconds":509,"BuildOrderItems":["DefaultItem","Drone","Drone","Drone","Overlord","Drone","Drone","Drone","Drone","Drone","Drone","Hatchery","Drone","Drone","Drone","Extractor","SpawningPool","Drone","Overlord","GasDrone","GasDrone","GasDrone","Drone","Drone","Queen","Queen","MetabolicBoost","MineralDrone","MineralDrone","Zergling","Drone","Drone","Overlord","Drone","Drone","Drone","InjectLarva","InjectLarva","Drone","Drone","Overlord","Drone","Drone","Hatchery","Queen","InjectLarva","InjectLarva","Drone","Drone","Drone","Drone","Drone","Overlord","Drone","Drone","Drone","Drone","Drone","Drone","InjectLarva","InjectLarva","Lair","SpawnCreepTumor","GasDrone","GasDrone","Extractor","Drone","Drone","Drone","Drone","Drone","Overlord","Drone","Drone","Drone","Drone","GasDrone","GasDrone","GasDrone","InjectLarva","Drone","Drone","Drone","Drone","Overlord","Drone","Hatchery","InjectLarva","Drone","Drone","Drone","Drone","Extractor","Extractor","Overlord","Zergling","Zergling","Zergling","Zergling","Zergling","InjectLarva","InjectLarva","GasDrone","GasDrone","GasDrone","GasDrone","GasDrone","GasDrone","Overlord","Overlord","HydraliskDen","Drone","Drone","Drone","Drone","Drone","Drone","Drone","Drone","Drone","Drone","SpineCrawler","SpineCrawler","InjectLarva","InjectLarva","GroovedSpines","Hydralisk","Hydralisk","Hydralisk","Hydralisk","Hydralisk","Hydralisk","Hydralisk","Hydralisk","Overlord","Overlord"],"CreationDate":1428423872067,"Description":"","Name":"SoS Hydra Opening","Race":"Zerg","SC2VersionID":"2.2.0","VisitedDate":1428423872067,"VsRace":"Protoss"}