{"BuildLengthInSeconds":568,"BuildOrderItems":["DefaultItem","Drone","Drone","Drone","Overlord","Drone","Drone","Drone","Drone","Drone","Drone","Hatchery","Drone","Drone","SpawningPool","Drone","Drone","Overlord","Drone","Drone","Queen","Queen","Zergling","Overlord","Drone","Drone","Drone","Drone","Drone","Drone","Queen","InjectLarva","Queen","InjectLarva","Overlord","Drone","Drone","Extractor","Extractor","Drone","Drone","InjectLarva","InjectLarva","Overlord","Drone","Drone","Drone","Drone","Drone","Drone","Drone","Drone","SpawnCreepTumor","SpawnCreepTumor","GasDrone","GasDrone","GasDrone","GasDrone","GasDrone","GasDrone","Overlord","Drone","Drone","Drone","Drone","Drone","Drone","Overlord","InjectLarva","InjectLarva","Lair","Extractor","Extractor","EvolutionChamber","EvolutionChamber","SpawnCreepTumor","SpawnCreepTumor","Drone","Drone","Drone","Drone","Drone","Drone","GasDrone","GasDrone","GasDrone","GasDrone","GasDrone","GasDrone","RoachWarren","Drone","InjectLarva","InjectLarva","MissleAttacksLevel1","GroundCarapaceLevel1","SpawnCreepTumor","SpawnCreepTumor","Overlord","Drone","Drone","InjectLarva","InjectLarva","GlialReconstitution","Overlord","Overlord","Overlord","Overlord","Overlord","Overlord","SpawnCreepTumor","Hatchery","SpawnCreepTumor","Drone","Drone","Drone","Drone","Drone","Drone","InjectLarva","InjectLarva","SpawnCreepTumor","Roach","Roach","Roach","Roach","Roach","Roach","Roach","SpawnCreepTumor","Roach","Roach","Roach","Roach","Roach","Roach","Roach","InjectLarva","InjectLarva","Roach","Roach","Roach","Roach","Roach","SpawnCreepTumor","SpawnCreepTumor","Roach","Roach","Roach","Roach","Roach","Roach","Roach","Roach","InjectLarva","InjectLarva","Roach","Roach","Roach","SpawnCreepTumor"],"CreationDate":1428166412546,"Description":"","Name":"Soukkey 1-1 Roach Push","Race":"Zerg","SC2VersionID":"2.2.0","VisitedDate":1428166412546,"VsRace":"Terran"}