{"BuildLengthInSeconds":637,"BuildOrderItems":["DefaultItem","Drone","Drone","Drone","Overlord","Drone","Drone","Drone","Drone","Drone","Drone","Hatchery","Drone","Drone","SpawningPool","Drone","Drone","Overlord","Drone","Drone","Queen","Queen","Zergling","Overlord","Drone","Drone","Drone","Drone","Overlord","Queen","InjectLarva","Queen","InjectLarva","Drone","Drone","Drone","Drone","Extractor","Extractor","Overlord","Drone","Drone","InjectLarva","InjectLarva","Drone","Drone","Drone","Drone","Drone","Drone","Drone","Drone","SpawnCreepTumor","SpawnCreepTumor","Overlord","GasDrone","GasDrone","GasDrone","GasDrone","GasDrone","GasDrone","Hatchery","Drone","Drone","Drone","InjectLarva","InjectLarva","MetabolicBoost","Extractor","EvolutionChamber","EvolutionChamber","SpawnCreepTumor","SpawnCreepTumor","Drone","Drone","Drone","Drone","Drone","Overlord","Drone","GasDrone","GasDrone","GasDrone","Drone","InjectLarva","InjectLarva","MeleeAttacksLevel1","GroundCarapaceLevel1","SpawnCreepTumor","SpawnCreepTumor","Overlord","Drone","Drone","Drone","Drone","Drone","Drone","Lair","Extractor","Drone","Drone","Drone","InjectLarva","InjectLarva","InjectLarva","Drone","Drone","Overlord","Drone","Drone","SpawnCreepTumor","Zergling","Zergling","Zergling","Zergling","Zergling","Zergling","GasDrone","GasDrone","GasDrone","Overlord","BanelingNest","RoachWarren","Drone","Drone","Drone","Drone","InjectLarva","InjectLarva","InjectLarva","Drone","Drone","Drone","Drone","Drone","Drone","Drone","SpawnCreepTumor","Hatchery","Overlord","Overlord","Overlord","Overlord","Overlord","Overlord","InjectLarva","InjectLarva","InjectLarva","Drone","Drone","Drone","GlialReconstitution","CentrifugalHooks","Extractor","SpawnCreepTumor","Overlord","Overlord","InjectLarva","InjectLarva","InjectLarva","GasDrone","GasDrone","GasDrone","Roach","Roach","Roach","Roach","Roach","Roach","Roach","Roach","Roach","Roach","Roach","Roach","Roach","Roach","SpawnCreepTumor","Roach","Roach","Roach","Roach","Roach","Roach","Roach","Roach","Roach","Roach","Zergling","Zergling","Zergling","Zergling","Zergling","Zergling","Zergling","Zergling","Zergling","Zergling","Zergling","Zergling","InjectLarva","InjectLarva","InjectLarva","Baneling","Baneling","Baneling","Baneling","Baneling","Baneling","Baneling","Baneling","Baneling","Baneling","Baneling","Baneling","Baneling","Baneling","Baneling","Baneling","Baneling","Baneling","Baneling","Baneling","Baneling","Baneling","Baneling","Baneling","Baneling","Overseer","Overseer","Overseer"],"CreationDate":1428164475200,"Description":"","Name":"Soulkey 3 Base Speed Roach-Baneling Push","Race":"Zerg","SC2VersionID":"2.2.0","VisitedDate":1428412626681,"VsRace":"Terran"}