{"BuildLengthInSeconds":411,"BuildOrderItems":["DefaultItem","Probe","Probe","Pylon","Probe","Probe","Gateway","Assimilator","Probe","Chronoboost","Probe","GasProbe","GasProbe","GasProbe","Probe","Chronoboost","Probe","Pylon","Probe","Nexus","CyberneticsCore","Probe","Assimilator","Pylon","Probe","Probe","GasProbe","GasProbe","GasProbe","Stargate","Adept","WarpgateUpgrade","Probe","Probe","Adept","Probe","Chronoboost","Probe","Probe","Probe","Oracle","Chronoboost","ShieldBattery","Probe","Probe","Assimilator","Probe","Probe","Probe","Probe","GasProbe","GasProbe","GasProbe","Phoenix","Chronoboost","Pylon","Assimilator","Probe","Probe","Probe","Probe","Oracle","GasProbe","GasProbe","GasProbe","Pylon","Stargate","Probe","Probe","Probe","Probe","SwitchToWarpgate","WarpInZealot","Probe","Probe","Oracle","Chronoboost","Oracle","Chronoboost","Pylon","WarpInStalker","Nexus","Probe","Probe","Pylon","Probe","Probe","WarpInStalker","Oracle","Chronoboost","Oracle","Chronoboost","Probe","Probe","Pylon","Probe","Probe","WarpInStalker","Pylon","Probe","Probe","Oracle","Chronoboost","Oracle","Probe","Probe","TwilightCouncil","Forge","WarpInSentry","Probe","Probe","Probe","RoboticsFacility","Nexus","Probe","Probe","Probe","GroundWeaponsLevel1","Chronoboost","Chronoboost","Blink","Chronoboost","Chronoboost","Gateway","Gateway","Gateway","Gateway","Probe","Probe","Probe","WarpInSentry","Pylon","Observer","Gateway","Gateway","Gateway","Gateway"],"CreationDate":1514380519469,"Description":"","Name":"Standard 1 Gate Expand into Oracles","Race":"Protoss","SC2VersionID":"5.0.3","VisitedDate":1514380550344,"VsRace":"Zerg"}