{"BuildLengthInSeconds":356,"BuildOrderItems":["DefaultItem","Probe","Probe","Pylon","Probe","Gateway","Probe","Assimilator","Probe","Chronoboost","Probe","GasProbe","GasProbe","GasProbe","Probe","Probe","Nexus","CyberneticsCore","Probe","Assimilator","Pylon","Probe","GasProbe","GasProbe","GasProbe","Probe","WarpgateUpgrade","Adept","Chronoboost","Probe","Probe","Adept","Chronoboost","Stargate","Probe","Probe","Adept","Probe","Probe","Probe","Probe","Oracle","Chronoboost","Adept","Probe","Probe","Pylon","Pylon","Probe","Probe","Gateway","Gateway","Probe","Probe","Phoenix","Chronoboost","Probe","Probe","Assimilator","Assimilator","Pylon","Probe","Probe","SwitchToWarpgate","RoboticsFacility","Oracle","Chronoboost","GasProbe","GasProbe","GasProbe","GasProbe","GasProbe","GasProbe","Probe","Probe","SwitchToWarpgate","SwitchToWarpgate","TwilightCouncil","Probe","Probe","Gateway","Pylon","Probe","Probe","WarpInZealot","WarpInZealot","WarpInZealot","Nexus","WarpPrism","Charge","Chronoboost","Chronoboost","Chronoboost","TemplarArchives","Pylon","SwitchToWarpgate","Forge","Gateway","Gateway","Probe","Probe","Pylon","Probe","Probe","GroundWeaponsLevel1","Chronoboost","Chronoboost","Chronoboost","WarpInHighTemplar","WarpInHighTemplar","WarpInHighTemplar","WarpInHighTemplar"],"CreationDate":1514379220354,"Description":"This is probably the safest and most standard PvZ style right now.","Name":"Stats 2 Oracle archon drop into IAC","Race":"Protoss","SC2VersionID":"5.0.3","VisitedDate":1514379329399,"VsRace":"Zerg"}