{"BuildLengthInSeconds":375,"BuildOrderItems":["DefaultItem","SCV","SCV","SupplyDepot","SCV","SCV","Barracks","Refinery","SCV","GoOutScv","SCV","GasScv","GasScv","GasScv","SCV","OrbitalCommand","Reaper","CommandCenter","SupplyDepot","CallMule","SCV","ReactorOnBarracks","SCV","SCV","Factory","SCV","Marine","MarineOnReactor","SCV","CommandCenter","SCV","CallMule","OrbitalCommand","Marine","MarineOnReactor","Refinery","SCV","TechLabOnFactory","Marine","MarineOnReactor","SCV","SCV","CallMule","GasScv","GasScv","GasScv","Cyclone","SCV","SCV","Marine","MarineOnReactor","Bunker","SCV","SCV","Marine","MarineOnReactor","OrbitalCommand","SCV","SCV","CallMule","SiegeTank","SupplyDepot","SCV","SCV","Marine","MarineOnReactor","SCV","SCV","SCV","CallMule","CallMule","Barracks","Barracks","SupplyDepot","Marine","MarineOnReactor","SCV","SCV","SCV","SiegeTank","SCV","SCV","SCV","EngineeringBay","EngineeringBay","Marine","MarineOnReactor","SupplyDepot","SCV","SCV","SCV","Refinery","Refinery","SupplyDepot","ScannerSweep","SCV","SCV","SCV","LiftFactoryFromTechLab","LandRaxOnTechLab","TechLabOnBarracks","Marine","MarineOnReactor","StimPack","InfantryWeaponsLevel1","InfantryArmorLevel1","GasScv","GasScv","GasScv","GasScv","GasScv","GasScv","SCV","SCV","SCV","SupplyDepot","CallMule","Marine","CallMule","Starport","ReactorOnFactory","Marine","MarineOnReactor","Marauder","SCV","SCV","SCV","SupplyDepot","CombatShield","SCV","SCV","SCV","Marine","Marine","MarineOnReactor","Marauder","Barracks","Barracks","SCV","SCV","SCV","ScannerSweep","LiftFactoryFromReactor","LandStarportOnReactor","Medivac","MedivacOnReactor","ReactorOnFactory","Armory"],"CreationDate":1449247771273,"Description":"This is unique TY style to play TvP in Legacy of the Void. Almost in each TvP TY use Reaper for scout and Cyclone as a basic defensive tool. TY\u0027s goal is to get quick 3 CC and not die while building infrastructure and researching upgrades. Early 3rd CC boost TY\u0027s economy for strong mid-late game aggression. He also add 2 siege tanks in order to be able to defend protoss 2 base timings.","Name":"TY Reaper CC into Cyclone fast 3rd","Race":"Terran","SC2VersionID":"3.0.0","VisitedDate":1449247778846,"VsRace":"Protoss"}