{"BuildLengthInSeconds":392,"BuildOrderItems":["DefaultItem","SCV","SCV","SupplyDepot","SCV","Barracks","SCV","Refinery","SCV","SCV","GasScv","GasScv","GasScv","SCV","OrbitalCommand","Reaper","CommandCenter","SupplyDepot","SCV","CallMule","Marine","SCV","Factory","SCV","Bunker","ReactorOnBarracks","SCV","SCV","OrbitalCommand","SCV","Barracks","Barracks","Refinery","CallMule","LiftRaxFromReactor","LandFactoryOnReactor","Hellion","HellionOnReactor","SCV","TechLabOnBarracks","GasScv","GasScv","GasScv","SCV","CallMule","SCV","Hellion","HellionOnReactor","StimPack","Marauder","SCV","SCV","SupplyDepot","ReactorOnBarracks","ReactorOnBarracks","SCV","SCV","SupplyDepot","SCV","SCV","CallMule","Hellion","HellionOnReactor","Marauder","SCV","SCV","SupplyDepot","SupplyDepot","Marine","MarineOnReactor","Marine","MarineOnReactor","CallMule","WidowMine","WidowMineOnReactor","EngineeringBay","SCV","SCV","Marauder","Marine","MarineOnReactor","Marine","MarineOnReactor","SCV","SCV","SupplyDepot","SupplyDepot","WidowMine","WidowMineOnReactor","InfantryWeaponsLevel1","SCV","SCV","Starport","CallMule","Marauder","Marine","MarineOnReactor","Marine","MarineOnReactor","SCV","SCV","SupplyDepot","SupplyDepot","WidowMine","WidowMineOnReactor","SCV","SCV","Marauder","CallMule","CombatShield","Marine","MarineOnReactor","Marine","MarineOnReactor","SCV","SCV","ReactorOnStarport","SupplyDepot","SupplyDepot","Refinery","SCV","SCV","WidowMine","WidowMineOnReactor","Marauder","Marine","MarineOnReactor","Marine","MarineOnReactor","SCV","SCV","GasScv","GasScv","GasScv","SupplyDepot","SupplyDepot","CallMule","SCV","SCV","Medivac","MedivacOnReactor","Marine","MarineOnReactor","Marine","MarineOnReactor","Marauder","SCV","SCV","CallMule","CommandCenter"],"CreationDate":1520134975597,"Description":"The goal of this build is to push zerg\u0027s 3rd base with big marine-marauder-hellion-widow mines force with stim-shields and +1 weapon upgrades.\n\nIf build executed well enough pusb is very strong and may kill zerg if he droned too hard. \n\nTake your 3rd while pushing out and transition into 2-2 push if zerg survives.","Name":"yaRus ReaperCC into 3-1-1 MMMHWm Push","Race":"Terran","SC2VersionID":"5.0.3","VisitedDate":1607959244056,"VsRace":"Zerg"}