{"BuildLengthInSeconds":349,"BuildOrderItems":["DefaultItem","Probe","Chronoboost","Probe","Pylon","Probe","Probe","Gateway","GoOutProbe","Probe","Assimilator","Probe","GasProbe","GasProbe","GasProbe","Probe","Nexus","Probe","CyberneticsCore","Probe","Assimilator","Probe","Pylon","Probe","GasProbe","GasProbe","GasProbe","Stalker","Chronoboost","WarpgateUpgrade","Probe","Probe","Probe","Chronoboost","Stalker","Chronoboost","Probe","Probe","RoboticsFacility","Probe","Probe","TwilightCouncil","Probe","Probe","Probe","Chronoboost","Probe","Gateway","Gateway","Probe","Probe","Pylon","Observer","Chronoboost","Blink","Chronoboost","Chronoboost","Probe","Probe","Probe","Probe","Nexus","Probe","Probe","SwitchToWarpgate","SwitchToWarpgate","SwitchToWarpgate","Assimilator","Assimilator","Pylon","Probe","WarpInStalker","WarpInStalker","WarpInStalker","Probe","Probe","Pylon","GasProbe","GasProbe","GasProbe","GasProbe","GasProbe","GasProbe","Probe","Probe","Forge","Forge","Probe","Probe","WarpInSentry","WarpInSentry","WarpInSentry","Probe","Probe","GroundWeaponsLevel1","Chronoboost","Chronoboost","GroundArmorLevel1","Chronoboost","Chronoboost","Charge","Chronoboost","Chronoboost","Probe","Probe","Probe","Pylon","Probe","Probe","Probe","Gateway","Gateway","Gateway","Gateway","Gateway","Probe","Probe","Probe","Assimilator","Assimilator"],"CreationDate":1514296613006,"Description":"Zest is best, and so is blink-robo. Zest has effectively brought back his old blink-robo style that he used nonstop for the longest time and it is insanely good. Mass blink stalkers and chargelots with double forge upgrades into templar is extremely strong on the patch at tge moment and is an incredibly solid way to play. unlike all those Oracle cheeses that are going on, this is less likely to be effected in any upcoming balance changes, so come be an honorable protoss with our friend Zest.","Name":"Zest Gate-Nexus into Blink-Robo double Forge","Race":"Protoss","SC2VersionID":"4.11.3","VisitedDate":1514296616749,"VsRace":"Terran"}