{"BuildLengthInSeconds":322,"BuildOrderItems":["DefaultItem","Probe","Probe","Pylon","Probe","Gateway","Probe","Chronoboost","Probe","Assimilator","Probe","Probe","GasProbe","GasProbe","GasProbe","Probe","Nexus","CyberneticsCore","Probe","Assimilator","Pylon","Probe","GasProbe","GasProbe","GasProbe","Probe","Stalker","Chronoboost","WarpgateUpgrade","Probe","TwilightCouncil","Probe","Chronoboost","Adept","Probe","Probe","Probe","RoboticsFacility","Probe","Chronoboost","Probe","Probe","Probe","DarkShrine","Probe","Probe","Probe","Probe","Chronoboost","Gateway","Gateway","Gateway","Probe","Probe","WarpPrism","Chronoboost","Pylon","Probe","Probe","Assimilator","Assimilator","Pylon","Probe","Probe","SwitchToWarpgate","Pylon","SwitchToWarpgate","SwitchToWarpgate","Pylon","GasProbe","GasProbe","GasProbe","GasProbe","GasProbe","GasProbe","Probe","Probe","SwitchToWarpgate","WarpInDarkTemplar","WarpInDarkTemplar","WarpInDarkTemplar","WarpInDarkTemplar","Probe","Probe","Probe","Probe","ArchonFromTwoDT","ArchonFromTwoDT","Pylon","WarpInZealot","WarpInZealot","WarpInZealot","WarpInZealot","Probe","Probe","Pylon","Probe","Probe","WarpInDarkTemplar","WarpInDarkTemplar","WarpInDarkTemplar","WarpInDarkTemplar"],"CreationDate":1514542232168,"Description":"","Name":"Zest Dark Templar Opening","Race":"Protoss","SC2VersionID":"4.11.3","VisitedDate":1514542357829,"VsRace":"Zerg"}